Workbook

Sheet Balance
D1: BRIGHTEC ENERGY DYNAMICS S DE RL DE CV
A3: Balance General | D3: =B3+1 | F3: =D3+1 | H3: =F3+1&" "&"("&IF('Edo de resultados'!K2=1,"Enero",IF('Edo de resultados'!K2=2,"Febrero",IF('Edo de resultados'!K2=3,"Marzo",IF('Edo de resultados'!K2=4,"Abril",IF('Edo de resultados'!K2=5,"Mayo",IF('Edo de resultados'!K2=6,"Junio",IF('Edo de resultados'!K2=7,"Julio",IF('Edo de resultados'!K2=8,"Agosto",IF('Edo de resultados'!K2=9,"Septiembre",IF('Edo de resultados'!K2=10,"Octubre",IF('Edo de resultados'!K2=11,"Noviembre",IF('Edo de resultados'!K2=12,"Diciembre","INCORRECTO"))))))))))))&")" | K3: ="Razones"&" "&B3 | L3: ="Razones"&" "&B3+1 | M3: ="Razones"&" "&B3+2 | N3: ="Razones"&" "&B3+3
B4: Saldo | D4: Saldo | F4: Saldo | H4: Saldo
A5: Activos | K5: A) SOLVENCIA(LIQUIDEZ) Y OPERACIÓN | L5: A) SOLVENCIA(LIQUIDEZ) Y OPERACIÓN | M5: A) SOLVENCIA(LIQUIDEZ) Y OPERACIÓN | N5: A) SOLVENCIA(LIQUIDEZ) Y OPERACIÓN
A6: ACTIVO | K6: Razon circulante | L6: Razon circulante | M6: Razon circulante | N6: Razon circulante
A7: ACTIVO- CIRCULANTE | B7: Analisis vertical | D7: Analisis vertical | F7: Analisis vertical | H7: Analisis vertical | J7: HORIZ | K7: Activo circulante/pasivo circulante | L7: Activo circulante/pasivo circulante | M7: Activo circulante/pasivo circulante | N7: Activo circulante/pasivo circulante
B8: Importe | C8: % | D8: Importe | E8: % | F8: Importe | G8: % | H8: Importe | I8: % | K8: =B19/B61 | L8: =D19/D61 | M8: =F19/F61 | N8: =H19/H61
A9: CAJA | C9: =B9/$B$43 | E9: =D9/$D$43 | F9: ='2025'!H4 | G9: =F9/$F$43 | I9: =H9/$H$43
A10: BANCOS | C10: =B10/$B$43 | E10: =D10/$D$43 | F10: ='2025'!H5 | G10: =F10/$F$43 | I10: =H10/$H$43 | K10: Prueba del acido | L10: Prueba del acido | M10: Prueba del acido | N10: Prueba del acido
A11: CLIENTES | C11: =B11/$B$43 | E11: =D11/$D$43 | F11: ='2025'!H6 | G11: =F11/$F$43 | I11: =H11/$H$43 | K11: Activo circulantes-inventario/ Pasivos circulantes | L11: Activo circulantes-inventario/ Pasivos circulantes | M11: Activo circulantes-inventario/ Pasivos circulantes | N11: Activo circulantes-inventario/ Pasivos circulantes
A12: CUENTAS POR COBRAR | C12: =B12/$B$43 | E12: =D12/$D$43 | F12: ='2025'!H7 | G12: =F12/$F$43 | I12: =H12/$H$43 | K12: =(B19-B16)/B61 | L12: =(D19-D16)/D61 | M12: =(F19-F16)/F61 | N12: =(H19-H16)/H61
A13: DEUDORES DIVERSOS | C13: =B13/$B$43 | E13: =D13/$D$43 | F13: ='2025'!H8 | G13: =F13/$F$43 | I13: =H13/$H$43
A14: ISR DIFERIDO | C14: =B14/$B$43 | E14: =D14/$D$43 | F14: ='2025'!H9 | G14: =F14/$F$43 | I14: =H14/$H$43 | K14: Efectivo a pasivo circulante | L14: Efectivo a pasivo circulante | M14: Efectivo a pasivo circulante | N14: Efectivo a pasivo circulante
A15: IMPUESTOS A FAVOR | C15: =B15/$B$43 | E15: =D15/$D$43 | F15: ='2025'!H10 | G15: =F15/$F$43 | I15: =H15/$H$43 | K15: efectivo/pasivo circulate | L15: efectivo/pasivo circulate | M15: efectivo/pasivo circulate | N15: efectivo/pasivo circulate
A16: INVENTARIOS | C16: =B16/$B$43 | E16: =D16/$D$43 | F16: ='2025'!H11 | G16: =F16/$F$43 | I16: =H16/$H$43 | K16: =(B9+B10)/B61 | L16: =(D9+D10)/D61 | M16: =(F9+F10)/F61 | N16: =(H9+H10)/H61
A17: PAGOS ANTICIPADOS | C17: =B17/$B$43 | E17: =D17/$D$43 | F17: ='2025'!H12 | G17: =F17/$F$43 | I17: =H17/$H$43 | K17: B) ACTIVIDAD O ROTACIONES | L17: B) ACTIVIDAD O ROTACIONES | M17: B) ACTIVIDAD O ROTACIONES | N17: B) ACTIVIDAD O ROTACIONES
A18: ANTICIPO PROVEEDORES | C18: =B18/$B$43 | E18: =D18/$D$43 | F18: ='2025'!H13 | G18: =F18/$F$43 | I18: =H18/$H$43 | K18: Rotacion de cuentas por cobrar | L18: Rotacion de cuentas por cobrar | M18: Rotacion de cuentas por cobrar | N18: Rotacion de cuentas por cobrar
A19: Total - CIRCULANTE | B19: =SUM(B9:B18) | C19: =B19/$B$43 | D19: =SUM(D9:D18) | E19: =D19/$D$43 | F19: =SUM(F9:F18) | G19: =F19/$F$43 | H19: =SUM(H9:H18) | I19: =H19/$H$43 | K19: Ventas/Cuentas por cobrar ( Clientes) | L19: Ventas/Cuentas por cobrar ( Clientes) | M19: Ventas/Cuentas por cobrar ( Clientes) | N19: Ventas/Cuentas por cobrar ( Clientes)
K20: ='Edo de resultados'!B7/Balance!B11 | L20: ='Edo de resultados'!D7/Balance!D11 | M20: ='Edo de resultados'!F7/Balance!F11 | N20: ='Edo de resultados'!H7/Balance!H11 | O20: veces por año
B21: - - - - - - - - - - - - - | D21: - - - - - - - - - - - - - | F21: - - - - - - - - - - - - - | H21: - - - - - - - - - - - - -
K22: Periodo promedio de cobro | L22: Periodo promedio de cobro | M22: Periodo promedio de cobro | N22: Periodo promedio de cobro
A23: ACTIVO- FIJO | K23: 365/rotacion de cuentas por cobrar | L23: 365/rotacion de cuentas por cobrar | M23: 365/rotacion de cuentas por cobrar | N23: 365/rotacion de cuentas por cobrar
A24: EDIFICIOS | C24: =B24/$B$43 | E24: =D24/$D$43 | F24: ='2025'!H15 | G24: =F24/$F$43 | I24: =H24/$H$43 | K24: =365/K20 | L24: =365/L20 | M24: =365/M20 | N24: =365/N20 | O24: dias
A25: MAQ, Y EQU. | C25: =B25/$B$43 | E25: =D25/$D$43 | F25: ='2025'!H16 | G25: =F25/$F$43 | I25: =H25/$H$43
A26: EQ. TRANSPORTE | C26: =B26/$B$43 | E26: =D26/$D$43 | F26: ='2025'!H17 | G26: =F26/$F$43 | I26: =H26/$H$43 | K26: Rotacion de inventarios | L26: Rotacion de inventarios | M26: Rotacion de inventarios | N26: Rotacion de inventarios
A27: MOB. Y EQUIPO | C27: =B27/$B$43 | E27: =D27/$D$43 | F27: ='2025'!H18 | G27: =F27/$F$43 | I27: =H27/$H$43 | K27: costo de ventas/inventario | L27: costo de ventas/inventario | M27: costo de ventas/inventario | N27: costo de ventas/inventario
A28: EQU. COMPUTO | C28: =B28/$B$43 | E28: =D28/$D$43 | F28: ='2025'!H19 | G28: =F28/$F$43 | I28: =H28/$H$43 | K28: =('Edo de resultados'!B8/Balance!B16)*-1 | L28: =('Edo de resultados'!D8/Balance!D16)*-1 | M28: =('Edo de resultados'!F8/Balance!F16)*-1 | N28: =('Edo de resultados'!H8/Balance!H16)*-1 | O28: veces por año
A29: OTROS ACTIVOS | C29: =B29/$B$43 | E29: =D29/$D$43 | F29: ='2025'!H20 | G29: =F29/$F$43 | I29: =H29/$H$43
A30: TERRENOS | C30: =B30/$B$43 | E30: =D30/$D$43 | F30: ='2025'!H21 | G30: =F30/$F$43 | I30: =H30/$H$43 | K30: Dias de Inventario | L30: Dias de Inventario | M30: Dias de inventario | N30: Dias de inventario
A31: DEPRECIACION ACUMULADA(MENOS) | C31: =B31/$B$43 | E31: =D31/$D$43 | F31: ='2025'!H22 | G31: =F31/$F$43 | I31: =H31/$H$43 | K31: Dias del periodo/rotacion de inventarios | L31: Dias del periodo/rotacion de inventarios | M31: Dias del periodo/rotacion de inventarios | N31: Dias del periodo/rotacion de inventarios
K32: =365/K28 | L32: =365/L28 | M32: =365/M28 | N32: =365/N28 | O32: dias
A33: Total- FIJO | B33: =SUM(B24:B31) | C33: =B33/$B$43 | D33: =SUM(D24:D31) | E33: =D33/$D$43 | F33: =SUM(F24:F31) | G33: =F33/$F$43 | H33: =SUM(H24:H31) | I33: =H33/$H$43
B34: - - - - - - - - - - - - - | D34: - - - - - - - - - - - - - | F34: - - - - - - - - - - - - - | H34: - - - - - - - - - - - - - | K34: Rotacion de cuentas x pagar | L34: Rotacion de cuentas x pagar | M34: Rotacion de cuentas x pagar | N34: Rotacion de cuentas x pagar
K35: Costo de ventas / proveedores | L35: Costo de ventas / proveedores | M35: Costo de ventas / proveedores | N35: Costo de ventas / proveedores
A36: ACTIVO- DIFERIDO | K36: =('Edo de resultados'!B8/Balance!B52)*-1 | L36: =('Edo de resultados'!D8/Balance!D52)*-1 | M36: =('Edo de resultados'!F8/Balance!F52)*-1 | N36: =('Edo de resultados'!H8/Balance!H52)*-1 | O36: veces por año
A37: GASTOS DE INSTALACION | C37: =B37/$B$43 | E37: =D37/$D$43 | F37: ='2025'!H24 | G37: =F37/$F$43 | I37: =H37/$H$43 | K37: Periodo prom de pago DIAS de cuentas x pagar | L37: Periodo prom de pago DIAS de cuentas x pagar | M37: Periodo prom de pago DIAS de cuentas x pagar | N37: Periodo prom de pago DIAS de cuentas x pagar
A38: DEPOSITOS EN GARANTIA | C38: =B38/$B$43 | E38: =D38/$D$43 | F38: ='2025'!H25 | G38: =F38/$F$43 | I38: =H38/$H$43 | K38: 365/ rotacion de ctas x pagar | L38: 365/ rotacion de ctas x pagar | M38: 365/ rotacion de ctas x pagar | N38: 365/ rotacion de ctas x pagar
A39: OTROS ACTIVOS A LARGO PLAZO | C39: =B39/$B$43 | E39: =D39/$D$43 | F39: ='2025'!H26 | G39: =F39/$F$43 | I39: =H39/$H$43 | K39: =365/K36 | L39: =365/L36 | M39: =365/M36 | N39: =365/N36 | O39: dias
A40: Total- DIFERIDO | B40: =SUM(B37:B39) | C40: =B40/$B$43 | D40: =SUM(D37:D39) | E40: =D40/$D$43 | F40: =SUM(F37:F39) | G40: =F40/$F$43 | H40: =SUM(H37:H39) | I40: =H40/$H$43 | K40: C) ENDEUDAMIENTO | L40: C) ENDEUDAMIENTO | M40: C) ENDEUDAMIENTO | N40: C) ENDEUDAMIENTO
B41: - - - - - - - - - - - - - | D41: - - - - - - - - - - - - - | F41: - - - - - - - - - - - - - | H41: - - - - - - - - - - - - - | K41: Razon de endeudamiento ( PT/AT) | L41: Razon de endeudamiento ( PT/AT) | M41: Razon de endeudamiento ( PT/AT) | N41: Razon de endeudamiento ( PT/AT)
K42: Pasivo Total/Activo total | L42: Pasivo Total/Activo total | M42: Pasivo Total/Activo total | N42: Pasivo Total/Activo total
A43: TOTAL ACTIVOS | B43: =B40+B19+B33 | C43: =B43/$B$43 | D43: =D40+D19+D33 | E43: =D43/$D$43 | F43: =F40+F19+F33 | G43: =F43/$F$43 | H43: =H40+H19+H33 | I43: =H43/$H$43 | K43: =B70/B43 | L43: =D70/D43 | M43: =F70/F43 | N43: =H70/H43
O44: RAZONES
B45: =B43 | C45: =B45/$B$43 | D45: =D43 | E45: =D45/$D$43 | F45: =F43 | G45: =F45/$F$43 | H45: =H43 | I45: =H45/$H$43 | K45: Razon de Apalancamiento( PT/CT) | L45: Razon de Apalancamiento( PT/CT) | M45: Razon de Apalancamiento( PT/CT) | N45: Razon de Apalancamiento( PT/CT) | O45: DE
B46: ============= | D46: ============= | F46: ============= | H46: ============= | K46: Pasivo Total/Capital Contable | L46: Pasivo Total/Capital Contable | M46: Pasivo Total/Capital Contable | N46: Pasivo Total/Capital Contable | O46: ENDEUDAMIENTO
A47: PASIVO | K47: =B70/B82 | L47: =D70/D82 | M47: =F70/F82 | N47: =H70/H82
A48: Pasivos | B48: Importe | C48: % | D48: Importe | E48: % | F48: Importe | G48: % | H48: Importe | I48: %
K49: DEUDA/EBITDA | L49: DEUDA/EBITDA | M49: DEUDA/EBITDA | N49: DEUDA/EBITDA
A50: PASIVO- CIRCULANTE | J50: HORIZ | K50: =(B53+B54+B64)/'Edo de resultados'!B30 | L50: =(D53+D54+D64)/'Edo de resultados'!D30 | M50: =(F53+F54+F64)/'Edo de resultados'!F30 | N50: =(H53+H54+H64)/'Edo de resultados'!H30 | O50: DEUDA/ UTILIDAD DE OPERACIÓN | Q50: Veces
A52: PROVEEDORES | C52: =B52/$B$84 | E52: =D52/$D$84 | F52: ='2025'!H28 | G52: =F52/$F$84 | I52: =H52/$H$84 | K52: D) RENTABILIDAD Y COBERTURA | L52: D) RENTABILIDAD Y COBERTURA | M52: D) RENTABILIDAD Y COBERTURA | N52: D) RENTABILIDAD Y COBERTURA
A53: PRESTAMOS BANCARIOS A CP | C53: =B53/$B$84 | E53: =D53/$D$84 | F53: ='2025'!H29 | G53: =F53/$F$84 | I53: =H53/$H$84 | J53: =I53-E53 | K53: Rotacion de activos totales | L53: Rotacion de activos totales | M53: Rotacion de activos totales | N53: Rotacion de activos totales | O53: A | P53: ABC | Q53: Dupont
A54: ACREEDORES DIVERSOS | C54: =B54/$B$84 | E54: =D54/$D$84 | F54: ='2025'!H30 | G54: =F54/$F$84 | I54: =H54/$H$84 | K54: Ventas/total de activos | L54: Ventas/total de activos | M54: Ventas/total de activos | N54: Ventas/total de activos
A55: OTROS PASIVOS | C55: =B55/$B$84 | E55: =D55/$D$84 | F55: ='2025'!H31 | G55: =F55/$F$84 | I55: =H55/$H$84 | K55: ='Edo de resultados'!B7/B43 | L55: ='Edo de resultados'!D7/D43 | M55: ='Edo de resultados'!F7/F43 | N55: ='Edo de resultados'!H7/H43
A56: IMPUESTOS ACUMULADOS | C56: =B56/$B$84 | E56: =D56/$D$84 | F56: ='2025'!H32 | G56: =F56/$F$84 | I56: =H56/$H$84
A57: ANTICIPO DE CLIENTES | C57: =B57/$B$84 | E57: =D57/$D$84 | F57: ='2025'!H33 | G57: =F57/$F$84 | I57: =H57/$H$84 | K57: Rendimiento sobre activo total (ROA) | L57: Rendimiento sobre activo total (ROA) | M57: Rendimiento sobre activo total (ROA) | N57: Rendimiento sobre activo total (ROA) | O57: Return Over Assests
K58: utilidad neta/total de activos | L58: utilidad neta/total de activos | M58: utilidad neta/total de activos | N58: utilidad neta/total de activos
K59: ='Edo de resultados'!B25/Balance!B43 | L59: ='Edo de resultados'!D25/Balance!D43 | M59: ='Edo de resultados'!F25/Balance!F43 | N59: ='Edo de resultados'!H25/Balance!H43
A61: Total CIRCULANTE | B61: =SUM(B52:B59) | C61: =B61/$B$84 | D61: =SUM(D52:D59) | E61: =D61/$D$84 | F61: =SUM(F52:F59) | G61: =F61/$F$84 | H61: =SUM(H52:H59) | I61: =H61/$H$84 | K61: Rendimiento sobre capital contable (ROE) | L61: Rendimiento sobre capital contable (ROE) | M61: Rendimiento sobre capital contable (ROE) | N61: Rendimiento sobre capital contable (ROE) | O61: Return Over Equity
B62: - - - - - - - - - - - - - | D62: - - - - - - - - - - - - - | F62: - - - - - - - - - - - - - | H62: - - - - - - - - - - - - - | K62: Utilidad neta/ capital contable | L62: Utilidad neta/ capital contable | M62: Utilidad neta/ capital contable | N62: Utilidad neta/ capital contable
A63: PASIVO A LARGO PLAZO | K63: ='Edo de resultados'!B25/Balance!B82 | L63: ='Edo de resultados'!D25/Balance!D82 | M63: ='Edo de resultados'!F25/Balance!F82 | N63: ='Edo de resultados'!H25/Balance!H82
A64: PRESTAMOS BANCARIOS A LARGO PLAZO | C64: =B64/$B$84 | E64: =D64/$D$84 | F64: ='2025'!H35 | G64: =F64/$F$84 | I64: =H64/$H$84
A65: OTRAS CUENTAS POR PAGAR A LP | C65: =B65/$B$84 | E65: =D65/$D$84 | F65: ='2025'!H36 | G65: =F65/$F$84 | I65: =H65/$H$84 | K65: Razon de generacion basica de utilidades | L65: Razon de generacion basica de utilidades | M65: Razon de generacion basica de utilidades | N65: Razon de generacion basica de utilidades
K66: Utilidad de operacion/Activos totales | L66: Utilidad de operacion/Activos totales | M66: Utilidad de operacion/Activos totales | N66: Utilidad de operacion/Activos totales
A67: Total LARGO PLAZO | B67: =B64+B65 | C67: =B67/$B$84 | D67: =D64+D65 | E67: =D67/$D$84 | F67: =F64+F65 | G67: =F67/$F$84 | H67: =H64+H65 | I67: =H67/$H$84 | K67: ='Edo de resultados'!B14/Balance!B43 | L67: ='Edo de resultados'!D14/Balance!D43 | M67: ='Edo de resultados'!F14/F43 | N67: ='Edo de resultados'!H14/H43
B68: - - - - - - - - - - - - - | D68: - - - - - - - - - - - - - | F68: - - - - - - - - - - - - - | H68: - - - - - - - - - - - - -
K69: Rotacion de activos fijos | L69: Rotacion de activos fijos | M69: Rotacion de activos fijos | N69: Rotacion de activos fijos
A70: TOTAL PASIVOS | B70: =SUM(B67+B61) | C70: =B70/$B$84 | D70: =SUM(D67+D61) | E70: =D70/$D$84 | F70: =SUM(F67+F61) | G70: =F70/$F$84 | H70: =SUM(H67+H61) | I70: =H70/$H$84 | K70: Ventas totales/ activos fijos | L70: Ventas totales/ activos fijos | M70: Ventas totales/ activos fijos | N70: Ventas totales/ activos fijos
K71: ='Edo de resultados'!B7/B33 | L71: ='Edo de resultados'!D7/D33 | M71: ='Edo de resultados'!F7/F33 | N71: ='Edo de resultados'!H7/H33
A73: CAPITAL | K73: Cobertura de Intereses | L73: Cobertura de Intereses | M73: Cobertura de Intereses | N73: Cobertura de Intereses
A74: CAPITAL SOCIAL | C74: =B74/$B$84 | E74: =D74/$D$84 | F74: ='2025'!H38 | G74: =F74/$F$84 | I74: =H74/$H$84 | K74: Utilidad de Operacion/Intereses pagados | L74: Utilidad de Operacion/Intereses pagados | M74: Utilidad de Operacion/Intereses pagados | N74: Utilidad de Operacion/Intereses pagados
A75: RESERVA LEGAL | C75: =B75/$B$84 | E75: =D75/$D$84 | F75: ='2025'!H39 | G75: =F75/$F$84 | I75: =H75/$H$84 | K75: =('Edo de resultados'!B14/'Edo de resultados'!B15)*-1 | L75: =('Edo de resultados'!D14/'Edo de resultados'!D15)*-1 | M75: =('Edo de resultados'!F14/'Edo de resultados'!F15)*-1 | N75: =('Edo de resultados'!H14/'Edo de resultados'!H15)*-1
A76: APORTACIONES PARA FUTUROS AUMENTOS | C76: =B76/$B$84 | E76: =D76/$D$84 | F76: ='2025'!H40 | G76: =F76/$F$84 | I76: =H76/$H$84 | M76: MODELO DUPONT
A77: RESULTADO DE EJERCICIOS ANTERIORES | C77: =B77/$B$84 | E77: =D77/$D$84 | F77: ='2025'!H41 | G77: =F77/$F$84 | I77: =H77/$H$84 | K77: Margen de utilidad sobre ventas | L77: Margen de utilidad sobre ventas | M77: Margen de utilidad sobre ventas | N77: Margen de utilidad sobre ventas
A78: UTILIDAD DEL EJERCICIO | C78: =B78/$B$84 | E78: =D78/$D$84 | F78: ='2025'!H42 | G78: =F78/$F$84 | I78: =H78/$H$84 | K78: Utilidad Neta/ventas | L78: Utilidad Neta/ventas | M78: Utilidad Neta/ventas | N78: Utilidad Neta/ventas | O78: B
B79: - - - - - - - - - - - - - | D79: - - - - - - - - - - - - - | F79: - - - - - - - - - - - - - | H79: - - - - - - - - - - - - - | K79: ='Edo de resultados'!B25/'Edo de resultados'!B7 | L79: ='Edo de resultados'!D25/'Edo de resultados'!D7 | M79: ='Edo de resultados'!F25/'Edo de resultados'!F7 | N79: ='Edo de resultados'!H25/'Edo de resultados'!H7
A80: Sumas | B80: =SUM(B74:B78) | C80: =B80/$B$84 | D80: =SUM(D74:D78) | E80: =D80/$D$84 | F80: =SUM(F74:F78) | G80: =F80/$F$84 | H80: =SUM(H74:H78) | I80: =H80/$H$84
K81: Multiplicador del capital | L81: Multiplicador del capital | M81: Multiplicador del capital | N81: Multiplicador del capital
A82: TOTAL CAPITAL CONTABLE | B82: =B80 | C82: =B82/$B$84 | D82: =D80 | E82: =D82/$D$84 | F82: =F80 | G82: =F82/$F$84 | H82: =H80 | I82: =H82/$H$84 | K82: Acivo Total/Capital Contable | L82: Acivo Total/Capital Contable | M82: Acivo Total/Capital Contable | N82: Acivo Total/Capital Contable | O82: C
K83: =B43/B82 | L83: =D43/D82 | M83: =F43/F82 | N83: =H43/H82
A84: PASIVO MAS CAPITAL | B84: =B82+B70 | C84: =B84/$B$84 | D84: =D82+D70 | E84: =D84/$D$84 | F84: =F82+F70 | G84: =F84/$F$84 | H84: =H82+H70 | I84: =H84/$H$84
B85: ============= | D85: ============= | F85: ============= | H85: ============= | K85: FORMULA DUPONT ROA | L85: FORMULA DUPONT ROA | M85: FORMULA DUPONT ROA | N85: FORMULA DUPONT ROA
K86: =K55*K79 | L86: =L55*L79 | M86: =M55*M79 | N86: =N55*N79 | O86: ROA
A88: ECUACION DE EQUILIBIO | B88: =(B43-B84) | D88: =(D43-D84) | F88: =(F43-F84) | H88: =(H43-H84) | K88: FORMULA DUPONT ROE | L88: FORMULA DUPONT ROE | M88: FORMULA DUPONT ROE | N88: FORMULA DUPONT ROE
K89: =K86*K83 | L89: =L86*L83 | M89: =M86*M83 | N89: =N86*N83 | O89: ROE
M91: ROCE( Return on capital Employed)
K92: Rendimiento sobre utilización de capital(ROCE) | L92: Rendimiento sobre utilización de capital(ROCE) | M92: Rendimiento sobre utilización de capital(ROCE) | N92: Rendimiento sobre utilización de capital(ROCE)
K93: ebitda/ capital contable + pasivo largo plazo | L93: ebitda/ capital contable + pasivo largo plazo | M93: ebitda/ capital contable + pasivo largo plazo | N93: ebitda/ capital contable + pasivo largo plazo
K94: ='Edo de resultados'!B30/(Balance!B82+Balance!B67) | L94: ='Edo de resultados'!D30/(Balance!D82+Balance!D67) | M94: ='Edo de resultados'!F30/(Balance!F82+Balance!F67) | N94: ='Edo de resultados'!H30/(Balance!H82+Balance!H67)
K95: ='Edo de resultados'!B30/(B43-B61) | L95: ='Edo de resultados'!D30/(D43-D61) | M95: ='Edo de resultados'!F30/(F43-F61) | N95: ='Edo de resultados'!H30/(H43-H61) | O95: Ebitda/activos totales - pasivo circulante)
M96: NECESIDADES DE CAPITAL DE TRABAJO EN PESOS
J99: CLIENTES | K99: =B11 | L99: =D11 | M99: =F11 | N99: =H11
J100: INVENTARIO | K100: =B16 | L100: =D16 | M100: =F16 | N100: =H16
J101: TOTALES | K101: =K99+K100 | L101: =L99+L100 | M101: =M99+M100 | N101: =N99+N100
J103: PROVEEDORES | K103: =+B52 | L103: =D52 | M103: =F52 | N103: =H52
J105: NECESIDADES | K105: =K101-K103 | L105: =L101-L103 | M105: =M101-M103 | N105: =N101-N103
M108: NECESIDADES DE CAPITAL DE TRABAJO EN DIAS
J110: CLIENTES | K110: =K24 | L110: =L24 | M110: =M24 | N110: =N24
J111: INVENTARIO | K111: =K32 | L111: =L32 | M111: =M32 | N111: =N32
K112: =K110+K111 | L112: =L110+L111 | M112: =M110+M111 | N112: =N110+N111
J114: PROVEEDORES | K114: =K39 | L114: =L39 | M114: =M39 | N114: =N39
...

Sheet Edo de resultados
A1: =Balance!D1
A3: Estado de Resultados | B3: =Balance!B3 | D3: =B3+1 | F3: =D3+1 | H3: =F3+1&" "&"("&IF(K2=1,"enero",IF(K2=2,"febrero",IF(K2=3,"marzo",IF(K2=4,"abril",IF(K2=5,"mayo",IF(K2=6,"junio",IF(K2=7,"julio",IF(K2=8,"agosto",IF(K2=9,"septiembre",IF(K2=10,"octubre",IF(K2=11,"noviembre",IF(K2=12,"diciembre","INCORRECTO"))))))))))))&")" | J3: =F3+1&" "&"anualizado"
B4: Saldo | C4: % | D4: Saldo | E4: % | F4: Saldo | G4: % | H4: Saldo | I4: % | J4: Saldo | K4: %
A5: 40000000 - VENTAS
A6: menos bonificaciones o rebajas
A7: VENTAS | F7: ='2025'!H46 | J7: =(+H7/$K$2)*12
A8: COSTO DE VENTAS | C8: =(B8/$B$7)*-1 | E8: =(D8/$D$7)*-1 | F8: ='2025'!H47 | G8: =(F8/$F$7)*-1 | I8: =(H8/$H$7)*-1 | J8: =(+H8/$K$2)*12 | K8: =(J8/$J$7)*-1 | L8: CAPTURAR EN NEGATIVO PORQUE ES RESTA
A9: Utilidad Bruta | B9: =B7+B8 | C9: =B9/$B$7 | D9: =D7+D8 | E9: =D9/$D$7 | F9: =F7+F8 | G9: =F9/$F$7 | H9: =H7+H8 | I9: =H9/$H$7 | J9: =J7+J8 | K9: =J9/$J$7
A10: Gastos Generales | C10: =(B10/$B$7)*-1 | E10: =(D10/$D$7)*-1 | F10: ='2025'!H49 | G10: =(F10/$F$7)*-1 | I10: =(H10/$H$7)*-1 | J10: =(+H10/$K$2)*12 | K10: =(J10/$J$7)*-1 | L10: CAPTURAR EN NEGATIVO PORQUE ES RESTA
A11: Gastos de administración | C11: =(B11/$B$7)*-1 | E11: =(D11/$D$7)*-1 | F11: ='2025'!H50 | G11: =(F11/$F$7)*-1 | I11: =(H11/$H$7)*-1 | J11: =(+H11/$K$2)*12 | K11: =(J11/$J$7)*-1 | L11: CAPTURAR EN NEGATIVO PORQUE ES RESTA
A12: TOTAL GASTOS DE OPERACION | B12: =B10+B11 | C12: =(B12/$B$7)*-1 | D12: =D10+D11 | E12: =(D12/$D$7)*-1 | F12: =F10+F11 | G12: =(F12/$F$7)*-1 | H12: =H10+H11 | I12: =(H12/$H$7)*-1 | J12: =+J10+J11 | K12: =(J12/$J$7)*-1
A14: Utilidad de Operación(EBIT) | B14: =B9+B12 | C14: =B14/$B$7 | D14: =D9+D12 | E14: =D14/$D$7 | F14: =F9+F12 | G14: =F14/$F$7 | H14: =H9+H12 | I14: =H14/$H$7 | J14: =J9+J12 | K14: =J14/$J$7
A15: GASTOS FINANCIEROS(menos) | C15: =(B15/$B$7)*-1 | E15: =(D15/$D$7)*-1 | F15: ='2025'!H52 | G15: =(F15/$F$7)*-1 | I15: =(H15/$H$7)*-1 | J15: =(+H15/$K$2)*12 | K15: =(J15/$J$7)*-1 | L15: CAPTURAR EN NEGATIVO PORQUE ES RESTA
A16: PRODUCTOS FINANCIEROS(mas) | C16: =(B16/$B$7) | E16: =(D16/$D$7) | F16: ='2025'!H53 | G16: =(F16/$F$7) | I16: =(H16/$H$7) | J16: =(+H16/$K$2)*12 | K16: =(J16/$J$7)
A17: Utilidad/ perdida cambiaria | C17: =(B17/$B$7) | E17: =(D17/$D$7) | F17: ='2025'!H54 | G17: =(F17/$F$7) | I17: =(H17/$H$7) | J17: =(+H17/$K$2)*12 | K17: =(J17/$J$7)
A18: Total Financieros | B18: =B15+B16+B17 | C18: =(B18/$B$7)*-1 | D18: =D15+D16+D17 | E18: =(D18/$D$7)*-1 | F18: =F15+F16+F17 | G18: =(F18/$F$7)*-1 | H18: =H15+H16+H17 | I18: =(H18/$F$7)*-1 | J18: =J15+J16+J17 | K18: =(J18/$J$7)*-1
A19: Utilidad despues de intereses | B19: =B14+B18 | C19: =B19/$B$7 | D19: =D14+D18 | E19: =D19/$D$7 | F19: =F14+F18 | G19: =F19/$F$7 | H19: =H14+H18 | I19: =H19/$H$7 | J19: =J14+J18 | K19: =J19/$J$7
A20: OTROS GASTOS(menos) | C20: =B20/$B$7 | E20: =D20/$D$7 | F20: ='2025'!H56 | G20: =F20/$F$7 | I20: =H20/$H$7 | J20: =(+H20/$K$2)*12 | K20: =J20/$J$7 | L20: CAPTURAR EN NEGATIVO PORQUE ES RESTA
A21: OTROS INGRESOS(mas) | C21: =B21/$B$7 | E21: =D21/$D$7 | F21: ='2025'!H57 | G21: =F21/$F$7 | I21: =H21/$H$7 | J21: =(+H21/$K$2)*12 | K21: =J21/$J$7
A22: Utilidad antes de impuestos | B22: =B19+B20+B21 | C22: =B22/$B$7 | D22: =D19+D20+D21 | E22: =D22/$D$7 | F22: =F19+F20+F21 | G22: =F22/$F$7 | H22: =H19+H20+H21 | I22: =H22/$H$7 | J22: =J19+J20+J21 | K22: =J22/$J$7
A24: IMPUESTOS | C24: =(B24/$B$7)*-1 | E24: =(D24/$D$7)*-1 | F24: ='2025'!H59 | G24: =(F24/$F$7)*-1 | I24: =(H24/$H$7)*-1 | J24: =(+H24/$K$2)*12 | K24: =(J24/$J$7)*-1 | L24: CAPTURAR EN NEGATIVO PORQUE ES RESTA
A25: Utilidad Neta | B25: =B22+B24 | C25: =B25/$B$7 | D25: =D22+D24 | E25: =D25/$D$7 | F25: =F22+F24 | G25: =F25/$F$7 | H25: =H22+H24 | I25: =H25/$H$7 | J25: =J22+J24 | K25: =J25/$J$7
B26: ============= | D26: ============= | F26: ============= | H26: ============ | J26: ============
A29: DEPRECIACION | D29: =(+Balance!D31-Balance!B31)*-1 | F29: ='2025'!H61 | H29: =(+Balance!H31-Balance!F31)*-1 | J29: =(+H29/$K$2)*12 | L29: CAPTURARLA( ES LA DIFERENCIA ENTRE DEP ACUM DEL ULTIMO AÑO MENOS LA DEL AÑO ANTERIOR
A30: TOTAL EBITDA(UTIL DE OPER + DEP) | B30: =B29+B14 | D30: =D29+D14 | F30: =F29+F14 | H30: =H29+H14 | J30: =J29+J14 | L30: EBITDA

Sheet Flujo
B1: ESTADO DE FLUJO DE EFECTIVO | C1: =Balance!B3 | E1: =C1+1 | G1: =E1+1 | J1: Saldos en Balances Generales
B2: Flujo Operativo | C2: Saldos | D2: Totales | E2: Saldos | F2: Totales | G2: Saldos | H2: Totales | J2: =K2-1 | K2: =E1 | L2: =K2+1 | M2: =L2+1
B3: Utilidad neta | C3: =+'Edo de resultados'!D25 | E3: =+'Edo de resultados'!F25 | G3: =+'Edo de resultados'!H25 | K3: =C3 | L3: =E3 | M3: =G3
A4: * | B4: Depreciacion | C4: =J4-K4 | E4: =K4-L4 | G4: =L4-M4 | J4: =Balance!B31 | K4: =Balance!D31 | L4: =Balance!F31 | M4: =Balance!H31
A5: * | B5: Cambio en Clientes | C5: =J5-K5 | E5: =K5-L5 | G5: =L5-M5 | J5: =Balance!B11 | K5: =Balance!D11 | L5: =Balance!F11 | M5: =Balance!H11
A6: * | B6: Cambio en cuentas por cobrar | C6: =J6-K6 | E6: =K6-L6 | G6: =L6-M6 | J6: =Balance!B12 | K6: =Balance!D12 | L6: =Balance!F12 | M6: =Balance!H12
A7: * | B7: Cambio en Deudores Diversos | C7: =J7-K7 | E7: =K7-L7 | G7: =L7-M7 | J7: =Balance!B13 | K7: =Balance!D13 | L7: =Balance!F13 | M7: =Balance!H13
B8: Cambio en ISR Diferido | C8: =J8-K8 | E8: =K8-L8 | G8: =L8-M8 | J8: =Balance!B14 | K8: =Balance!D14 | L8: =Balance!F14 | M8: =Balance!H14
B9: Cambio en Impuestos a favor | C9: =J9-K9 | E9: =K9-L9 | G9: =L9-M9 | J9: =Balance!B15 | K9: =Balance!D15 | L9: =Balance!F15 | M9: =Balance!H15
B10: Cambio en Inventarios | C10: =J10-K10 | E10: =K10-L10 | G10: =L10-M10 | J10: =Balance!B16 | K10: =Balance!D16 | L10: =Balance!F16 | M10: =Balance!H16
B11: Cambio en Anticipo a Proveedores | C11: =J11-K11 | E11: =K11-L11 | G11: =L11-M11 | J11: =Balance!B18 | K11: =Balance!D18 | L11: =Balance!F18 | M11: =Balance!H18
B12: Cambio en Otros Activos no Circulantes | C12: =J12-K12 | E12: =K12-L12 | G12: =L12-M12 | J12: =+Balance!B40 | K12: =+Balance!D40 | L12: =+Balance!F40 | M12: =+Balance!H40
A13: * | B13: Cambio en Compañías Afiliadas (Activo) | C13: =J13-K13 | E13: =K13-L13 | G13: =L13-M13 | J13: =Balance!B17 | K13: =Balance!D17 | L13: =Balance!F17 | M13: =Balance!H17
A14: * | B14: Cambio en Proveedores | C14: =K14-J14 | E14: =L14-K14 | G14: =M14-L14 | J14: =Balance!B52 | K14: =Balance!D52 | L14: =Balance!F52 | M14: =Balance!H52
B15: Cambio en Pagos Anticipados | C15: =K15-J15 | E15: =L15-K15 | G15: =M15-L15 | J15: =Balance!B55 | K15: =Balance!D55 | L15: =Balance!F55 | M15: =Balance!H55
B16: Cambio en impuestos por pagar | C16: =K16-J16 | E16: =L16-K16 | G16: =M16-L16 | J16: =Balance!B56 | K16: =Balance!D56 | L16: =Balance!F56 | M16: =Balance!H56
B17: Cambio en Acreedores Diversos | C17: =K17-J17 | E17: =L17-K17 | G17: =M17-L17 | J17: =+Balance!B54 | K17: =+Balance!D54 | L17: =+Balance!F54 | M17: =+Balance!H54
A18: * | B18: Cambio en Anticipo de clientes | C18: =K18-J18 | E18: =L18-K18 | G18: =M18-L18 | J18: =+Balance!B57 | K18: =+Balance!D57 | L18: =+Balance!F57 | M18: =+Balance!H57
B19: Cambio en otras cuentas por pagar LP | C19: =K19-J19 | E19: =L19-K19 | G19: =M19-L19 | J19: =+Balance!B65 | K19: =+Balance!D65 | L19: =+Balance!F65 | M19: =+Balance!H65
B20: Ajustes por dictamen | C20: =K20-J20 | E20: =L20-K20 | G20: =M20-L20 | J20: =+Balance!B66
B22: Efectivo de actividades operativas | D22: =SUM(C3:C21) | F22: =SUM(E3:E21) | H22: =SUM(G3:G21)
B24: Flujo de Inversion
B25: Cambio en Edificios | C25: =J25-K25 | E25: =K25-L25 | G25: =L25-M25 | J25: =+Balance!B24 | K25: =+Balance!D24 | L25: =+Balance!F24 | M25: =+Balance!H24
B26: Cambio en Maq. y Eq. Transporte | C26: =J26-K26 | E26: =K26-L26 | G26: =L26-M26 | J26: =+Balance!B25 | K26: =+Balance!D25 | L26: =+Balance!F25 | M26: =+Balance!H25
B27: Cambio en Equipo Transporte | C27: =J27-K27 | E27: =K27-L27 | G27: =L27-M27 | J27: =+Balance!B26 | K27: =+Balance!D26 | L27: =+Balance!F26 | M27: =+Balance!H26
B28: Cambio en Mob y Equ | C28: =J28-K28 | E28: =K28-L28 | G28: =L28-M28 | J28: =+Balance!B27 | K28: =+Balance!D27 | L28: =+Balance!F27 | M28: =+Balance!H27
B29: Cambio en Eq. Computo | C29: =J29-K29 | E29: =K29-L29 | G29: =L29-M29 | J29: =+Balance!B28 | K29: =+Balance!D28 | L29: =+Balance!F28 | M29: =+Balance!H28
B30: Cambio en Otros Activos | C30: =J30-K30 | E30: =K30-L30 | G30: =L30-M30 | J30: =+Balance!B29 | K30: =+Balance!D29 | L30: =+Balance!F29 | M30: =+Balance!H29
B31: Cambio en Terrenos | C31: =J31-K31 | E31: =K31-L31 | G31: =L31-M31 | J31: =+Balance!B30 | K31: =+Balance!D30 | L31: =+Balance!F30 | M31: =+Balance!H30
B32: Efectivo de actividades Inversion | D32: =SUM(C25:C31) | F32: =SUM(E25:E31) | H32: =SUM(G25:G31)
B34: Flujo de financiamiento
B35: Cambio en documentos por pagar CP | C35: =K35-J35 | E35: =L35-K35 | G35: =M35-L35 | J35: =+Balance!B53 | K35: =+Balance!D53 | L35: =+Balance!F53 | M35: =+Balance!H53
B36: Cambio en documentos por pagar LP | C36: =K36-J36 | E36: =L36-K36 | G36: =M36-L36 | J36: =+Balance!B64 | K36: =+Balance!D64 | L36: =+Balance!F64 | M36: =+Balance!H64
B37: Cambio en capital Pagado | C37: =K37-J37 | E37: =L37-K37 | G37: =M37-L37 | J37: =Balance!B74 | K37: =Balance!D74 | L37: =Balance!F74 | M37: =+Balance!H74
B38: Cambio Otros Rdos Integrales | C38: =K38-J38 | E38: =L38-K38 | G38: =M38-L38 | J38: =+Balance!B76 | K38: =+Balance!D76 | L38: =+Balance!F76 | M38: =+Balance!H76
B39: Dividendos decretados | C39: =K39-J39 | E39: =L39-K39 | G39: =M39-L39
B40: Diferencia en Rdo ej anteriores | C40: =K40-J40 | E40: =L40-K40 | G40: =M40-L40 | J40: =-Balance!D77+Balance!B77+Balance!B78 | K40: =IFERROR(+Balance!E77-Balance!C77-Balance!C78,0) | L40: =+Balance!F77-Balance!D77-Balance!D78 | M40: =+Balance!H77-Balance!F77-Balance!F78+L40
B41: Rdo 2021 | C41: =K41-J41 | E41: =L41-K41 | G41: =M41-L41
B44: Efectivo de actividades Financiamiento | D44: =SUM(C35:C42) | F44: =SUM(E35:E42) | H44: =SUM(G35:G42)
B46: Aumento/disminución en efectivo | D46: =SUM(D22:D44) | F46: =SUM(F22:F44) | H46: =SUM(H22:H44)
B48: Cambio en Impuestos a favor | J48: =SUM(Balance!D17:D22) | L48: =SUM(Balance!F17:F22)
B49: Cambioe Impuestos por pagar | J49: =SUM(Balance!D56:D57) | L49: =SUM(Balance!F56:F57)
B50: Mas Saldo inicial caja y bancos | D50: =SUM(Balance!B9:B10) | F50: =SUM(Balance!D9:D10) | H50: =SUM(Balance!F9:F10)
B52: Total Saldo final en caja y bancos | D52: =D46+D50 | F52: =F46+F50 | H52: =H46+H50
B54: Saldo Final caja y bancos Balance | D54: =+Balance!D10+Balance!D9 | F54: =+Balance!F10+Balance!F9 | H54: =+Balance!H10+Balance!H9
B56: Diferencia | D56: =+D54-D52 | F56: =+F54-F52 | H56: =+H54-H52

Sheet Edo de res AN HORIZ
A1: =Balance!D1 | M1: AÑO 1 VS AÑO 2 | Q1: AÑO 2 VS AÑO 3 | U1: AÑO 3 VS AÑO 4
K2: ='Edo de resultados'!K2 | M2: ANALISIS HORIZONTAL | Q2: ANALISIS HORIZONTAL | U2: ANALISIS HORIZONTAL
A3: Estado de Resultados | B3: ='Edo de resultados'!B3:C3 | D3: ='Edo de resultados'!D3:E3 | F3: ='Edo de resultados'!F3:G3 | H3: ='Edo de resultados'!H3:I3 | J3: ='Edo de resultados'!J3:K3 | M3: VARIACION $ | N3: VARIACION % | O3: INDICES | Q3: VARIACION $ | R3: VARIACION % | S3: INDICES | U3: VARIACION $ | V3: VARIACION % | W3: INDICES
A4: VENTAS | B4: ='Edo de resultados'!B7 | D4: ='Edo de resultados'!D7 | F4: ='Edo de resultados'!F7 | H4: ='Edo de resultados'!H7 | J4: =+(H4/$K$2)*12 | M4: =+D4-B4 | N4: =M4/B4 | O4: =D4/B4 | Q4: =F4-D4 | R4: =Q4/D4 | S4: =F4/D4 | U4: =H4-F4 | V4: =U4/F4 | W4: =H4/F4
A5: COSTO DE VENTAS | B5: ='Edo de resultados'!B8 | C5: =B5/B$4 | D5: ='Edo de resultados'!D8 | E5: =D5/D$4 | F5: ='Edo de resultados'!F8 | G5: =F5/F$4 | H5: ='Edo de resultados'!H8 | I5: =H5/H$4 | J5: =+(H5/$K$2)*12 | K5: =J5/J$4 | M5: =+D5-B5 | N5: =M5/B5 | O5: =D5/B5 | Q5: =F5-D5 | R5: =Q5/D5 | S5: =F5/D5 | U5: =H5-F5 | V5: =U5/F5 | W5: =H5/F5
A6: Utilidad Bruta | B6: =B4+B5 | C6: =B6/B$4 | D6: =D4+D5 | E6: =D6/D$4 | F6: =F4+F5 | G6: =F6/F$4 | H6: =H4+H5 | I6: =H6/H$4 | J6: =J4+J5 | K6: =J6/J$4 | M6: =+D6-B6 | N6: =M6/B6 | O6: =D6/B6 | Q6: =F6-D6 | R6: =Q6/D6 | S6: =F6/D6 | U6: =H6-F6 | V6: =U6/F6 | W6: =H6/F6
A7: GASTOS DE OPERACION | B7: ='Edo de resultados'!B12 | C7: =B7/B$4 | D7: ='Edo de resultados'!D12 | E7: =D7/D$4 | F7: ='Edo de resultados'!F12 | G7: =F7/F4 | H7: ='Edo de resultados'!H12 | I7: =H7/H4 | J7: =+(H7/$K$2)*12 | K7: =J7/J4 | M7: =+D7-B7 | N7: =M7/B7 | O7: =D7/B7 | Q7: =F7-D7 | R7: =Q7/D7 | S7: =F7/D7 | U7: =H7-F7 | V7: =U7/F7 | W7: =H7/F7
A8: Utilidad de Operación(EBIT) | B8: ='Edo de resultados'!B14 | C8: =B8/B$4 | D8: ='Edo de resultados'!D14 | E8: =D8/D$4 | F8: ='Edo de resultados'!F14 | G8: =F8/F$4 | H8: ='Edo de resultados'!H14 | I8: =H8/H$4 | J8: =+J6+J7 | K8: =J8/J$4 | M8: =+D8-B8 | N8: =M8/B8 | O8: =D8/B8 | Q8: =F8-D8 | R8: =Q8/D8 | S8: =F8/D8 | U8: =H8-F8 | V8: =U8/F8 | W8: =H8/F8
A9: GASTOS FINANCIEROS/PRODUCTOS | B9: ='Edo de resultados'!B18 | C9: =B9/B$4 | D9: ='Edo de resultados'!D18 | E9: =D9/D$4 | F9: ='Edo de resultados'!F18 | G9: =F9/F$4 | H9: ='Edo de resultados'!H18 | I9: =H9/H$4 | J9: =+(H9/$K$2)*12 | K9: =J9/J$4 | M9: =+D9-B9 | N9: =M9/B9 | O9: =D9/B9 | Q9: =F9-D9 | R9: =Q9/D9 | S9: =F9/D9 | U9: =H9-F9 | V9: =U9/F9 | W9: =H9/F9
A10: OTROS GASTOS/PRODUCTOS | B10: ='Edo de resultados'!B20+'Edo de resultados'!B21 | C10: =B10/B$4 | D10: ='Edo de resultados'!D20+'Edo de resultados'!D21 | E10: =D10/D$4 | F10: ='Edo de resultados'!F20+'Edo de resultados'!F21 | G10: =F10/F$4 | H10: ='Edo de resultados'!H20+'Edo de resultados'!H21 | J10: =+(H10/$K$2)*12
A11: Utilidad antes de impuestos | B11: ='Edo de resultados'!B22 | C11: =B11/B$4 | D11: ='Edo de resultados'!D22 | E11: =D11/D$4 | F11: ='Edo de resultados'!F22 | G11: =F11/F$4 | H11: ='Edo de resultados'!H22 | I11: =H11/H$4 | J11: =+J8+J9 | K11: =J11/J$4 | M11: =+D11-B11 | N11: =M11/B11 | O11: =D11/B11 | Q11: =F11-D11 | R11: =Q11/D11 | S11: =F11/D11 | U11: =H11-F11 | V11: =U11/F11 | W11: =H11/F11
A12: IMPUESTOS | B12: ='Edo de resultados'!B24 | C12: =B12/B$4 | D12: ='Edo de resultados'!D24 | E12: =D12/D$4 | F12: ='Edo de resultados'!F24 | G12: =F12/F$4 | H12: ='Edo de resultados'!H24 | I12: =H12/H$4 | K12: =J12/J$4 | M12: =+D12-B12 | N12: =M12/B12 | O12: =D12/B12 | Q12: =F12-D12 | R12: =Q12/D12 | S12: =F12/D12 | U12: =H12-F12 | V12: =U12/F12 | W12: =H12/F12
A13: Utilidad Neta | B13: ='Edo de resultados'!B25 | C13: =B13/B$4 | D13: ='Edo de resultados'!D25 | E13: =D13/D$4 | F13: ='Edo de resultados'!F25 | G13: =F13/F$4 | H13: ='Edo de resultados'!H25 | I13: =H13/H$4 | J13: =+J11+J12 | K13: =J13/J$4 | M13: =+D13-B13 | N13: =M13/B13 | O13: =D13/B13 | Q13: =F13-D13 | R13: =Q13/D13 | S13: =F13/D13 | U13: =H13-F13 | V13: =U13/F13 | W13: =H13/F13
N18: ACTIVO | R18: ACTIVO | V18: ACTIVO
A19: ACTIVO | M19: AÑO 1 VS AÑO 2 | Q19: AÑO 2 VS AÑO 3 | T19: CIRCULANTE | U19: AÑO 3 VS AÑO 4
A20: ACTIVO- CIRCULANTE | B20: Analisis vertical | D20: Analisis vertical | F20: Analisis vertical | H20: Analisis vertical | M20: ANALISIS HORIZONTAL | Q20: ANALISIS HORIZONTAL | U20: ANALISIS HORIZONTAL
B21: Importe | C21: % | D21: Importe | E21: % | F21: Importe | G21: % | H21: Importe | I21: % | M21: VARIACION $ | N21: VARIACION % | O21: INDICES | Q21: VARIACION $ | R21: VARIACION % | S21: INDICES | U21: VARIACION $ | V21: VARIACION % | W21: INDICES
A22: CAJA | B22: =Balance!B9 | C22: =B22/$B$56 | D22: =Balance!D9 | E22: =D22/$D$56 | F22: =Balance!F9 | G22: =F22/$F$56 | H22: =Balance!H9 | I22: =H22/$H$56 | M22: =D22-B22 | N22: =M22/B22 | O22: =D22/B22 | Q22: =F22-D22 | R22: =Q22/D22 | S22: =F22/D22 | U22: =H22-F22 | V22: =U22/F22 | W22: =H22/F22
A23: BANCOS | B23: =Balance!B10 | C23: =B23/$B$56 | D23: =Balance!D10 | E23: =D23/$D$56 | F23: =Balance!F10 | G23: =F23/$F$56 | H23: =Balance!H10 | I23: =H23/$H$56 | M23: =D23-B23 | N23: =M23/B23 | O23: =D23/B23 | Q23: =F23-D23 | R23: =Q23/D23 | S23: =F23/D23 | U23: =H23-F23 | V23: =U23/F23 | W23: =H23/F23
A24: CLIENTES | B24: =Balance!B11 | C24: =B24/$B$56 | D24: =Balance!D11 | E24: =D24/$D$56 | F24: =Balance!F11 | G24: =F24/$F$56 | H24: =Balance!H11 | I24: =H24/$H$56 | M24: =D24-B24 | N24: =M24/B24 | O24: =D24/B24 | Q24: =F24-D24 | R24: =Q24/D24 | S24: =F24/D24 | U24: =H24-F24 | V24: =U24/F24 | W24: =H24/F24
A25: INVENTARIO | B25: =Balance!B16 | C25: =B25/$B$56 | D25: =Balance!D16 | E25: =D25/$D$56 | F25: =Balance!F16 | G25: =F25/$F$56 | H25: =Balance!H16 | I25: =H25/$H$56 | M25: =D25-B25 | N25: =M25/B25 | O25: =D25/B25 | Q25: =F25-D25 | R25: =Q25/D25 | S25: =F25/D25 | U25: =H25-F25 | V25: =U25/F25 | W25: =H25/F25
A26: DEUDORES DIVERSOS | B26: =Balance!B13 | C26: =B26/$B$56 | D26: =Balance!D13 | E26: =D26/$D$56 | F26: =Balance!F13 | G26: =F26/$F$56 | H26: =Balance!H13 | I26: =H26/$H$56 | M26: =D26-B26 | N26: =M26/B26 | O26: =D26/B26 | Q26: =F26-D26 | R26: =Q26/D26 | S26: =F26/D26 | U26: =H26-F26 | V26: =U26/F26 | W26: =H26/F26
A27: OTRAS CUENTAS POR COBRAR | B27: =+Balance!B14+Balance!B12 | C27: =B27/$B$56 | D27: =+Balance!D14+Balance!D12 | E27: =D27/$D$56 | F27: =+Balance!F14+Balance!F12 | G27: =F27/$F$56 | H27: =+Balance!H14+Balance!H12 | I27: =H27/$H$56 | M27: =D27-B27 | N27: =M27/B27 | O27: =D27/B27 | Q27: =F27-D27 | R27: =Q27/D27 | S27: =F27/D27 | U27: =H27-F27 | V27: =U27/F27 | W27: =H27/F27
A28: IVA POR RECUPERAR | B28: =Balance!B15 | C28: =B28/$B$56 | D28: =Balance!D15 | E28: =D28/$D$56 | F28: =Balance!F15 | G28: =F28/$F$56 | H28: =Balance!H15 | I28: =H28/$H$56 | M28: =D28-B28 | N28: =M28/B28 | O28: =D28/B28 | Q28: =F28-D28 | R28: =Q28/D28 | S28: =F28/D28 | U28: =H28-F28 | V28: =U28/F28 | W28: =H28/F28
A29: OTROS ACTIVOS | B29: =Balance!B17+Balance!B18 | C29: =B29/$B$56 | D29: =Balance!D17+Balance!D18 | E29: =D29/$D$56 | F29: =Balance!F17+Balance!F18 | G29: =F29/$F$56 | H29: =Balance!H17+Balance!H18 | I29: =H29/$H$56 | M29: =D29-B29 | N29: =M29/B29 | O29: =D29/B29 | Q29: =F29-D29 | R29: =Q29/D29 | S29: =F29/D29 | U29: =H29-F29 | V29: =U29/F29 | W29: =H29/F29
A32: Total - CIRCULANTE | B32: =SUM(B22:B31) | C32: =B32/$B$56 | D32: =SUM(D22:D31) | E32: =D32/$D$56 | F32: =SUM(F22:F31) | G32: =F32/$F$56 | H32: =SUM(H22:H31) | I32: =H32/$H$56 | M32: =D32-B32 | N32: =M32/B32 | O32: =D32/B32 | Q32: =F32-D32 | R32: =Q32/D32 | S32: =F32/D32 | U32: =H32-F32 | V32: =U32/F32 | W32: =H32/F32
B34: - - - - - - - - - - - - - | F34: - - - - - - - - - - - - - | H34: - - - - - - - - - - - - -
A36: ACTIVO- FIJO | N36: ACTIVO- FIJO | R36: ACTIVO- FIJO | V36: ACTIVO- FIJO
A37: EDIFICIOS | B37: =Balance!B24 | C37: =B37/$B$56 | D37: =Balance!D24 | E37: =D37/$D$56 | F37: =Balance!F24 | G37: =F37/$F$43 | H37: =+Balance!H24 | I37: =H37/$H$56 | M37: =D37-B37 | N37: =M37/B37 | O37: =D37/B37 | Q37: =F37-D37 | R37: =Q37/D37 | S37: =F37/D37 | U37: =H37-F37 | V37: =U37/F37 | W37: =H37/F37
A38: MAQ, Y EQU. TRANSPORTE | B38: =Balance!B25 | C38: =B38/$B$56 | D38: =Balance!D25 | E38: =D38/$D$56 | F38: =Balance!F25 | G38: =F38/$F$43 | H38: =+Balance!H25 | I38: =H38/$H$56 | M38: =D38-B38 | N38: =M38/B38 | O38: =D38/B38 | Q38: =F38-D38 | R38: =Q38/D38 | S38: =F38/D38 | U38: =H38-F38 | V38: =U38/F38 | W38: =H38/F38
A39: EQUIPO DE TRANSPORTE | B39: =Balance!B26 | C39: =B39/$B$56 | D39: =Balance!D26 | E39: =D39/$D$56 | F39: =Balance!F26 | G39: =F39/$F$43 | H39: =+Balance!H26 | I39: =H39/$H$56 | M39: =D39-B39 | N39: =M39/B39 | O39: =D39/B39 | Q39: =F39-D39 | R39: =Q39/D39 | S39: =F39/D39 | U39: =H39-F39 | V39: =U39/F39 | W39: =H39/F39
A40: EQUIPO DE OFICINA | B40: =Balance!B27 | C40: =B40/$B$56 | D40: =Balance!D27 | E40: =D40/$D$56 | F40: =Balance!F27 | G40: =F40/$F$43 | H40: =+Balance!H27 | I40: =H40/$H$56 | M40: =D40-B40 | N40: =M40/B40 | O40: =D40/B40 | Q40: =F40-D40 | R40: =Q40/D40 | S40: =F40/D40 | U40: =H40-F40 | V40: =U40/F40 | W40: =H40/F40
A41: EQUIPO DE COMPUTO | B41: =Balance!B28 | C41: =B41/$B$56 | D41: =Balance!D28 | E41: =D41/$D$56 | F41: =Balance!F28 | G41: =F41/$F$43 | H41: =+Balance!H28 | I41: =H41/$H$56 | M41: =D41-B41 | N41: =M41/B41 | O41: =D41/B41 | Q41: =F41-D41 | R41: =Q41/D41 | S41: =F41/D41 | U41: =H41-F41 | V41: =U41/F41 | W41: =H41/F41
A42: OTROS UTILES | B42: =Balance!B29 | C42: =B42/$B$56 | D42: =Balance!D29 | E42: =D42/$D$56 | F42: =Balance!F29 | G42: =F42/$F$43 | H42: =+Balance!H29 | I42: =H42/$H$56 | M42: =D42-B42 | N42: =M42/B42 | O42: =D42/B42 | Q42: =F42-D42 | R42: =Q42/D42 | S42: =F42/D42 | U42: =H42-F42 | V42: =U42/F42 | W42: =H42/F42
B43: =Balance!B30 | C43: =B43/$B$56 | D43: =Balance!D30 | E43: =D43/$D$56 | F43: =Balance!F30 | G43: =F43/$F$43 | H43: =+Balance!H30 | I43: =H43/$H$56 | M43: =D43-B43 | N43: =M43/B43 | O43: =D43/B43 | Q43: =F43-D43 | R43: =Q43/D43 | S43: =F43/D43 | U43: =H43-F43 | V43: =U43/F43 | W43: =H43/F43
A44: DEPRECIACION ACUMULADA(MENOS) | B44: =Balance!B31 | C44: =B44/$B$56 | D44: =Balance!D31 | E44: =D44/$D$56 | F44: =Balance!F31 | G44: =F44/$F$43 | H44: =Balance!H31 | I44: =H44/$H$56 | M44: =D44-B44 | N44: =M44/B44 | O44: =D44/B44 | Q44: =F44-D44 | R44: =Q44/D44 | S44: =F44/D44 | U44: =H44-F44 | V44: =U44/F44 | W44: =H44/F44
A46: Total- FIJO | B46: =SUM(B37:B44) | C46: =B46/$B$56 | D46: =SUM(D37:D44) | E46: =D46/$D$56 | F46: =SUM(F37:F44) | G46: =F46/$F$56 | H46: =SUM(H37:H44) | I46: =H46/$H$56 | M46: =D46-B46 | N46: =M46/B46 | O46: =D46/B46 | Q46: =F46-D46 | R46: =Q46/D46 | S46: =F46/D46 | U46: =H46-F46 | V46: =U46/F46 | W46: =H46/F46
B47: - - - - - - - - - - - - - | F47: - - - - - - - - - - - - - | H47: - - - - - - - - - - - - -
A49: ACTIVO- DIFERIDO | N49: DIFERIDO | R49: DIFERIDO | V49: DIFERIDO
A50: PAGOS ANTICIPADOS | B50: =Balance!B37 | C50: =B50/$B$56 | D50: =Balance!D37 | E50: =D50/$D$56 | F50: =Balance!F37 | G50: =F50/$F$43 | H50: =Balance!H37 | I50: =H50/$H$43 | M50: =D50-B50 | N50: =M50/B50 | O50: =D50/B50 | Q50: =F50-D50 | R50: =Q50/D50 | S50: =F50/D50 | U50: =H50-F50 | V50: =U50/F50 | W50: =H50/F50
A51: OTROS ACTIVOS NO CIRCULANTES | B51: =Balance!B38+Balance!B39 | C51: =B51/$B$56 | D51: =Balance!D38+Balance!D39 | E51: =D51/$D$56 | F51: =Balance!F38+Balance!F39 | G51: =F51/$F$43 | H51: =Balance!H38+Balance!H39 | I51: =H51/$H$56 | M51: =D51-B51 | N51: =M51/B51 | O51: =D51/B51 | Q51: =F51-D51 | R51: =Q51/D51 | S51: =F51/D51 | U51: =H51-F51 | V51: =U51/F51 | W51: =H51/F51
A53: Total- DIFERIDO | B53: =B50+B51 | C53: =B53/$B$56 | D53: =D50+D51 | E53: =D53/$D$56 | F53: =F50+F51 | G53: =F53/$F$56 | H53: =H50+H51 | I53: =H53/$H$56 | M53: =D53-B53 | N53: =M53/B53 | O53: =D53/B53 | Q53: =F53-D53 | R53: =Q53/D53 | S53: =F53/D53 | U53: =H53-F53 | V53: =U53/F53 | W53: =H53/F53
B54: - - - - - - - - - - - - - | F54: - - - - - - - - - - - - - | H54: - - - - - - - - - - - - -
A56: TOTAL ACTIVOS | B56: =B53+B32+B46 | C56: =B56/$B$56 | D56: =D53+D32+D46 | E56: =D56/$D$56 | F56: =F53+F32+F46 | G56: =F56/$F$56 | H56: =H53+H32+H46 | I56: =H56/$H$56 | M56: =D56-B56 | N56: =M56/B56 | O56: =D56/B56 | Q56: =F56-D56 | R56: =Q56/D56 | S56: =F56/D56 | U56: =H56-F56 | V56: =U56/F56 | W56: =H56/F56
A59: PASIVO | M59: PASIVO | Q59: PASIVO | U59: PASIVO
A60: Pasivos | B60: Importe | C60: % | F60: Importe | G60: % | H60: Importe | I60: % | M60: AÑO 1 VS AÑO 2 | Q60: AÑO 2 VS AÑO 3 | U60: AÑO 3 VS AÑO 4
A62: PASIVO- CIRCULANTE
A64: PROVEEDORES | B64: =Balance!B52 | C64: =B64/$B$82 | D64: =Balance!D52 | E64: =D64/$D$82 | F64: =Balance!F52 | G64: =F64/$F$82 | H64: =Balance!H52 | I64: =H64/$H$84 | M64: =D64-B64 | N64: =M64/B64 | O64: =D64/B64 | Q64: =F64-D64 | R64: =Q64/D64 | S64: =F64/D64 | U64: =H64-F64 | V64: =U64/F64 | W64: =H64/F64
A65: PRESTAMOS BANCARIOS A CP | B65: =Balance!B53 | C65: =B65/$B$82 | D65: =Balance!D53 | E65: =D65/$D$82 | F65: =Balance!F53 | G65: =F65/$F$82 | H65: =Balance!H53 | I65: =H65/$H$84 | M65: =D65-B65 | N65: =M65/B65 | O65: =D65/B65 | Q65: =F65-D65 | R65: =Q65/D65 | S65: =F65/D65 | U65: =H65-F65 | V65: =U65/F65 | W65: =H65/F65
A66: PORCION CIRCULANTE PRESTAMOS LARGO PLAZO | B66: =Balance!B54 | C66: =B66/$B$82 | D66: =Balance!D54 | E66: =D66/$D$82 | F66: =Balance!F54 | G66: =F66/$F$82 | H66: =Balance!H54 | I66: =H66/$H$84 | M66: =D66-B66 | N66: =M66/B66 | O66: =D66/B66 | Q66: =F66-D66 | R66: =Q66/D66 | S66: =F66/D66 | U66: =H66-F66 | V66: =U66/F66 | W66: =H66/F66
A67: ACREEDORES DIVERSOS | B67: =Balance!B55 | C67: =B67/$B$82 | D67: =Balance!D55 | E67: =D67/$D$82 | F67: =Balance!F55 | G67: =F67/$F$82 | H67: =Balance!H55 | I67: =H67/$H$84 | M67: =D67-B67 | N67: =M67/B67 | O67: =D67/B67 | Q67: =F67-D67 | R67: =Q67/D67 | S67: =F67/D67 | U67: =H67-F67 | V67: =U67/F67 | W67: =H67/F67
A68: IMPUESTOS POR PAGAR | B68: =Balance!B56 | C68: =B68/$B$82 | D68: =Balance!D56 | E68: =D68/$D$82 | F68: =Balance!F56 | G68: =F68/$F$82 | H68: =Balance!H56 | I68: =H68/$H$84 | M68: =D68-B68 | N68: =M68/B68 | O68: =D68/B68 | Q68: =F68-D68 | R68: =Q68/D68 | S68: =F68/D68 | U68: =H68-F68 | V68: =U68/F68 | W68: =H68/F68
A69: GASTOS ACUMULADOS POR PAGAR | B69: =Balance!B57 | C69: =B69/$B$82 | D69: =Balance!D57 | E69: =D69/$D$82 | F69: =Balance!F57 | G69: =F69/$F$82 | H69: =Balance!H57 | I69: =H69/$H$84 | M69: =D69-B69 | N69: =M69/B69 | O69: =D69/B69 | Q69: =F69-D69 | R69: =Q69/D69 | S69: =F69/D69 | U69: =H69-F69 | V69: =U69/F69 | W69: =H69/F69
A73: Total CIRCULANTE | B73: =SUM(B64:B71) | C73: =B73/$B$82 | D73: =SUM(D64:D71) | E73: =D73/$D$82 | F73: =SUM(F64:F71) | G73: =F73/$F$82 | H73: =SUM(H64:H71) | I73: =H73/$H$82 | M73: =D73-B73 | N73: =M73/B73 | O73: =D73/B73 | Q73: =F73-D73 | R73: =Q73/D73 | S73: =F73/D73 | U73: =H73-F73 | V73: =U73/F73 | W73: =H73/F73
B74: - - - - - - - - - - - - - | D74: - - - - - - - - - - - - - | F74: - - - - - - - - - - - - - | H74: - - - - - - - - - - - - -
A75: PASIVO A LARGO PLAZO
A76: PRESTAMOS BANCARIOS A LARGO PLAZO | B76: =Balance!B64 | C76: =B76/$B$82 | D76: =Balance!D64 | E76: =D76/$D$82 | F76: =Balance!F64 | G76: =F76/$F$82 | H76: =Balance!H64 | I76: =H76/$H$84 | M76: =D76-B76 | N76: =M76/B76 | O76: =D76/B76 | Q76: =F76-D76 | R76: =Q76/D76 | S76: =F76/D76 | U76: =H76-F76 | V76: =U76/F76 | W76: =H76/F76
A77: OTROS PASIVOS A LARGO PLAZO | B77: =Balance!B65 | C77: =B77/$B$82 | D77: =Balance!D65 | E77: =D77/$D$82 | F77: =Balance!F65 | G77: =F77/$F$82 | H77: =Balance!H65 | I77: =H77/$H$84 | M77: =D77-B77 | N77: =M77/B77 | O77: =D77/B77 | Q77: =F77-D77 | R77: =Q77/D77 | S77: =F77/D77 | U77: =H77-F77 | V77: =U77/F77 | W77: =H77/F77
A79: Total LARGO PLAZO | B79: =B76+B77 | C79: =B79/$B$82 | D79: =D76+D77 | E79: =D79/$D$82 | F79: =F76+F77 | G79: =F79/$F$82 | H79: =H76+H77 | I79: =H79/$H$82 | M79: =D79-B79 | N79: =M79/B79 | O79: =D79/B79 | Q79: =F79-D79 | R79: =Q79/D79 | S79: =F79/D79 | U79: =H79-F79 | V79: =U79/F79 | W79: =H79/F79
B80: - - - - - - - - - - - - - | D80: - - - - - - - - - - - - - | F80: - - - - - - - - - - - - - | H80: - - - - - - - - - - - - -
A82: TOTAL PASIVOS | B82: =SUM(B79+B73) | C82: =B82/$B$96 | D82: =SUM(D79+D73) | E82: =D82/$D$96 | F82: =SUM(F79+F73) | G82: =F82/$F$96 | H82: =SUM(H79+H73) | I82: =H82/$H$96 | M82: =D82-B82 | N82: =M82/B82 | O82: =D82/B82 | Q82: =F82-D82 | R82: =Q82/D82 | S82: =F82/D82 | U82: =H82-F82 | V82: =U82/F82 | W82: =H82/F82
A85: CAPITAL | M85: CAPITAL | Q85: CAPITAL | U85: CAPITAL
A86: CAPITAL SOCIAL | B86: =Balance!B74 | C86: =B86/$B$96 | D86: =Balance!D74 | E86: =D86/$D$96 | F86: =Balance!F74 | G86: =F86/$F$84 | H86: =Balance!H74 | I86: =H86/$H$84 | M86: =D86-B86 | N86: =M86/B86 | O86: =D86/B86 | Q86: =F86-D86 | R86: =Q86/D86 | S86: =F86/D86 | U86: =H86-F86 | V86: =U86/F86 | W86: =H86/F86
A87: RESERVA LEGAL | B87: =Balance!B75 | C87: =B87/$B$96 | D87: =Balance!D75 | E87: =D87/$D$96 | F87: =Balance!F75 | G87: =F87/$F$84 | H87: =Balance!H75 | I87: =H87/$H$84 | M87: =D87-B87 | N87: =M87/B87 | O87: =D87/B87 | Q87: =F87-D87 | R87: =Q87/D87 | S87: =F87/D87 | U87: =H87-F87 | V87: =U87/F87 | W87: =H87/F87
A88: OTROS | B88: =Balance!B76 | C88: =B88/$B$96 | D88: =Balance!D76 | E88: =D88/$D$96 | F88: =Balance!F76 | G88: =F88/$F$84 | H88: =Balance!H76 | I88: =H88/$H$84 | M88: =D88-B88 | N88: =M88/B88 | O88: =D88/B88 | Q88: =F88-D88 | R88: =Q88/D88 | S88: =F88/D88 | U88: =H88-F88 | V88: =U88/F88 | W88: =H88/F88
A89: UTILIDADES ACUMULADAS | B89: =Balance!B77 | C89: =B89/$B$96 | D89: =Balance!D77 | E89: =D89/$D$96 | F89: =Balance!F77 | G89: =F89/$F$84 | H89: =Balance!H77 | I89: =H89/$H$84 | M89: =D89-B89 | N89: =M89/B89 | O89: =D89/B89 | Q89: =F89-D89 | R89: =Q89/D89 | S89: =F89/D89 | U89: =H89-F89 | V89: =U89/F89 | W89: =H89/F89
A90: UTILIDAD DEL EJERCICIO | B90: =Balance!B78 | C90: =B90/$B$96 | D90: =Balance!D78 | E90: =D90/$D$96 | F90: =Balance!F78 | G90: =F90/$F$84 | H90: =Balance!H78 | I90: =H90/$H$84 | M90: =D90-B90 | N90: =M90/B90 | O90: =D90/B90 | Q90: =F90-D90 | R90: =Q90/D90 | S90: =F90/D90 | U90: =H90-F90 | V90: =U90/F90 | W90: =H90/F90
B91: - - - - - - - - - - - - - | D91: - - - - - - - - - - - - - | F91: - - - - - - - - - - - - - | H91: - - - - - - - - - - - - -
A92: Sumas | B92: =SUM(B86:B90) | C92: =B92/$B$94 | D92: =SUM(D86:D90) | E92: =D92/$D$94 | F92: =SUM(F86:F90) | G92: =F92/$F$94 | H92: =SUM(H86:H90) | I92: =H92/$H$94 | M92: =D92-B92 | N92: =M92/B92 | O92: =D92/B92 | Q92: =F92-D92 | R92: =Q92/D92 | S92: =F92/D92 | U92: =H92-F92 | V92: =U92/F92 | W92: =H92/F92
A94: TOTAL CAPITAL CONTABLE | B94: =B92 | C94: =B94/$B$96 | D94: =D92 | E94: =D94/$D$96 | F94: =F92 | G94: =F94/$F$96 | H94: =H92 | I94: =H94/$H$96 | M94: =D94-B94 | N94: =M94/B94 | O94: =D94/B94 | Q94: =F94-D94 | R94: =Q94/D94 | S94: =F94/D94 | U94: =H94-F94 | V94: =U94/F94 | W94: =H94/F94
A96: PASIVO MAS CAPITAL | B96: =B94+B82 | C96: =B96/$B$96 | D96: =D94+D82 | E96: =D96/$D$96 | F96: =F94+F82 | G96: =F96/$F$96 | H96: =H94+H82 | I96: =H96/$H$96 | M96: =D96-B96 | N96: =M96/B96 | O96: =D96/B96 | Q96: =F96-D96 | R96: =Q96/D96 | S96: =F96/D96 | U96: =H96-F96 | V96: =U96/F96 | W96: =H96/F96
B97: ============= | D97: ============= | F97: ============= | H97: =============
A100: ECUACION DE EQUILIBIO | B100: =(B56-B96) | D100: =(D56-D96) | F100: =(F56-F96) | H100: =(H56-H96) | M100: =(M56-M96) | N100: =(N56-N96) | O100: =(O56-O96) | Q100: =(Q56-Q96) | R100: =(R56-R96) | S100: =(S56-S96) | U100: =(U56-U96) | V100: =(V56-V96) | W100: =(W56-W96)

Sheet input
B2: =Balance!F3 | C2: =Balance!H3
A3: TOTAL ACTIVOS CIRCULANTES | B3: =Balance!F19 | C3: =Balance!H19
A4: TOTAL ACTIVOS FIJOS | B4: =Balance!F33 | C4: =Balance!H33
A5: TOTAL ACTIVOS DIFERIDOS | B5: =Balance!F40 | C5: =Balance!H40
A6: TOTAL PASIVO NO FINANCIERO | B6: =Balance!F61-Balance!F53 | C6: =Balance!H61-Balance!H53
A7: TOTAL PASIVO FINANCIERO | B7: =Balance!F53+Balance!F65 | C7: =Balance!H53+Balance!H65
A8: TOTAL PASIVO DIFERIDO | B8: =Balance!F67-Balance!F65 | C8: =Balance!H67-Balance!H65
A9: CXP Proveedores | B9: =Balance!F52 | C9: =Balance!H52
A10: CAPITAL CONTABLE TOTAL | B10: =Balance!F82 | C10: =Balance!H82
A12: VENTAS | B12: ='Edo de resultados'!F7 | C12: ='Edo de resultados'!H7
A13: UTILIDAD DE OPERACIÓN (Antes de impuestos y gastos financieros | B13: ='Edo de resultados'!F14 | C13: ='Edo de resultados'!H14
A14: DEPRECIACIÓN (edo. de resúltados) | B14: ='Edo de resultados'!F29 | C14: ='Edo de resultados'!H29

Sheet 2025
A1: Cuenta Extraída | B1: Monto Extraído | C1: Página | D1: Evidencia Visual | E1: Input / Ajuste | G1: Concepto | H1: Importe (Input)
G2: ── BALANCE ──
G3: ACTIVO CIRCULANTE
G4: Caja
G5: Bancos
G6: Clientes
G7: Cuentas Por Cobrar
G8: Deudores Diversos
G9: Isr Diferido
G10: Impuestos A Favor
G11: Inventarios
G12: Pagos Anticipados
G13: Anticipo Proveedores
... G61: Depreciacion
