Workbook
Name \0: #REF!
Name \C: #REF!
Name __xlnm._FilterDatabase: sectores!$D$1:$H$1069
Name AA: #REF!
Name AÑO: #REF!
Name AS2DocOpenMode: "AS2DocumentEdit"
Name BB: #REF!
Name CAPTURA: #REF!
Name CC: #REF!
Name DD: #REF!
Name depreciacion_last_partial_anualizado: DATOS!$U$11
Name depreciacion_PL_full_year: DATOS!$O$11
Name depreciacion_PL_last_partial: DATOS!$S$11
Name DOCXPAG: #N/A
Name EE: #REF!
Name EMP: #REF!
Name Excel_BuiltIn_Print_Area_5_1: CALIF!$A$1:$K$79
Name Excel_BuiltIn_Print_Area_5_1_3: Hoja10!$A$1:$K$79
Name FF: #REF!
Name IMPRESION: #REF!
Name INDICES: #REF!
Name INTACUMUL: #N/A
Name MENU: #REF!
Name MES: #REF!
Name nuevosca: #REF!
Name pagos_arrendamiento_mensual_full_year: DATOS!$O$13
Name PERDCAMBIOS: #N/A
Name rating_buro: DATOS!$Q$29
Name S.DEP: #REF!
Name SHARED_FORMULA_0: #N/A
Name SHARED_FORMULA_1: #N/A
Name SHARED_FORMULA_10: #N/A
Name SHARED_FORMULA_11: #N/A
Name SHARED_FORMULA_12: #N/A
Name SHARED_FORMULA_13: #N/A
Name SHARED_FORMULA_14: #N/A
Name SHARED_FORMULA_15: #N/A
Name SHARED_FORMULA_16: #N/A
Name SHARED_FORMULA_17: #N/A
Name SHARED_FORMULA_18: #N/A
Name SHARED_FORMULA_19: #N/A
Name SHARED_FORMULA_2: #N/A
Name SHARED_FORMULA_20: #N/A
Name SHARED_FORMULA_21: #N/A
Name SHARED_FORMULA_22: #N/A
Name SHARED_FORMULA_23: #N/A
Name SHARED_FORMULA_24: #N/A
Name SHARED_FORMULA_25: #N/A
Name SHARED_FORMULA_26: #N/A
Name SHARED_FORMULA_27: #N/A
Name SHARED_FORMULA_28: #N/A
Name SHARED_FORMULA_29: #N/A
Name SHARED_FORMULA_3: #N/A
Name SHARED_FORMULA_30: #N/A
Name SHARED_FORMULA_31: #N/A
Name SHARED_FORMULA_32: #N/A
Name SHARED_FORMULA_33: #N/A
Name SHARED_FORMULA_34: #N/A
Name SHARED_FORMULA_35: #N/A
Name SHARED_FORMULA_36: #N/A

Sheet Bal
E6: 2007 | F6: % | G6: 2008 | H6: % | I6: Jun - | J6: 2009 | K6: %
B8: BALANCE GENERAL
B9: ACTIVO CIRCULANTE
B11: Caja y Bancos | E11: 61506 | G11: 0.02 | H11: 271489 | I11: 0.05 | J11: 152319 | K11: 0.03
B12: Cuentas por Cobrar | E12: 805016 | G12: 0.21 | H12: 696737 | I12: 0.13 | J12: 590149 | K12: 0.11
B13: Deudores Diversos | E13: 696040 | G13: 0.18 | H13: 2303156 | I13: 0.41 | J13: 2475063 | K13: 0.45
B14: Inventarios | E14: 121292 | G14: 0.03 | H14: 199339 | I14: 0.04 | J14: 290010 | K14: 0.05
E15: 1683854 | G15: 0.44 | H15: 3470721 | I15: 0.63 | J15: 3507541 | K15: 0.64
B16: ACTIVO FIJO
B18: Terrenos y Edificios | E18: 287684 | G18: 0.07 | H18: 287684 | I18: 0.05 | J18: 287685 | K18: 0.05
B19: Maquinaria y Equipo | E19: 1960982 | G19: 0.5 | H19: 2362142 | I19: 0.42 | J19: 2425191 | K19: 0.44
B20: Muebles y Enseres | E20: 287942 | G20: 0.07 | H20: 398840 | I20: 0.07 | J20: 430042 | K20: 0.08
B21: Equipo de Transporte | E21: 44065 | G21: 0.01 | H21: 47054 | I21: 0.01 | J21: 54529 | K21: 0.01
B22: Depreciacion Acumulada | E22: -1014568 | G22: -0.26 | H22: -1181927 | I22: -0.21 | J22: -1274663 | K22: -0.23
E23: 1566105 | G23: 0.39 | H23: 1913793 | I23: 0.34 | J23: 1922784 | K23: 0.35
B24: ACTIVO DIFERIDO
B26: Pagos Anticipados | E26: 20318 | G26: 0.01 | H26: 41904 | I26: 0.01 | K26: 0
B27: Cargos Diferidos | E27: 630957 | G27: 0.16 | H27: 144259 | I27: 0.03 | J27: 34134 | K27: 0.01
B28: Inversiones en Valores | E28: 500 | G28: 0 | H28: 500 | I28: 0 | K28: 0
E29: 651775 | G29: 0.17 | H29: 186663 | I29: 0.04 | J29: 34134 | K29: 0.01
B30: TOTAL DE ACTIVO | E30: 3901734 | G30: 1 | H30: 5571177 | I30: 1 | J30: 5464459 | K30: 1
B31: PASIVO CIRCULANTE
B33: Proveedores | E33: 44762 | G33: 0.01 | H33: 30461 | I33: 0.01 | J33: 25632 | K33: 0
B34: Creditos a Corto Plazo | E34: 1035327 | G34: 0.27 | H34: 1588080 | I34: 0.29 | J34: 1000179 | K34: 0.18
B35: Impuestos a Pagar | E35: 85415 | G35: 0.02 | H35: 116008 | I35: 0.02 | J35: 52581 | K35: 0.01
B36: Acreedores Diversos | E36: 34072 | G36: 0.01 | H36: 720635 | I36: 0.13 | J36: 902103 | K36: 0.17
E37: 1199576 | G37: 0.31 | H37: 2455184 | I37: 0.45 | J37: 1980495 | K37: 0.36
B38: PASIVO A LARGO PLAZO
B40: Creditos a Largo Plazo | E40: 777045 | G40: 0.2 | H40: 659414 | I40: 0.12 | J40: 649505 | K40: 0.12
E41: 777045 | G41: 0.2 | H41: 659414 | I41: 0.12 | J41: 649505 | K41: 0.12
B44: TOTAL DE PASIVO | E44: 1976621 | G44: 0.51 | H44: 3114598 | I44: 0.57 | J44: 2630000 | K44: 0.48
B45: CAPITAL CONTABLE
B47: Capital Social | E47: 800000 | G47: 0.21 | H47: 800000 | I47: 0.14 | J47: 800000 | K47: 0.15
B48: Reservas | E48: 33328 | G48: 0.01 | H48: 54296 | I48: 0.01 | J48: 80869 | K48: 0.01
B49: Utilidad Acumulada | E49: 618232 | G49: 0.16 | H49: 1016623 | I49: 0.18 | J49: 1521517 | K49: 0.28
B50: Superavit por Reevaluacion | E50: 54194 | G50: 0.01 | H50: 54194 | I50: 0.01 | J50: 54194 | K50: 0.01
B51: Utilidad del Ejercicio | E51: 419359 | G51: 0.11 | H51: 531466 | I51: 0.1 | J51: 377879 | K51: 0.07
E52: 1925113 | G52: 0.5 | H52: 2456579 | I52: 0.44 | J52: 2834459 | K52: 0.52
B53: TOTAL DE CAPITAL CONTABLE | E53: 1925113 | G53: 0.5 | H53: 2456579 | I53: 0.44 | J53: 2834459 | K53: 0.52
B54: TOTAL DE PASIVO + CAPITAL | E54: 3901734 | G54: 1 | H54: 5571177 | I54: 1 | J54: 5464459 | K54: 1
B55: TOTAL DE ACTIVO | E55: 3901734 | G55: 1 | H55: 5571177 | I55: 1 | J55: 5464459 | K55: 1
B56: ESTADO DE RESULTADOS
B57: UTILIDAD BRUTA
B59: Ventas | E59: 2178748 | G59: 1 | H59: 2406741 | I59: 1 | J59: 1228870 | K59: 1
B60: Costo de Ventas | E60: 1239161 | G60: 0.57 | H60: 1102291 | I60: 0.46 | J60: 575660 | K60: 0.47
E61: 939587 | G61: 0.43 | H61: 1304450 | I61: 0.54 | J61: 653210 | K61: 0.53
B62: UTILIDAD DE OPERACION
B64: Gastos de Venta | E64: 191143 | G64: 0.09 | H64: 217833 | I64: 0.09 | J64: 125992 | K64: 0.1
E65: 748444 | G65: 0.34 | H65: 1086617 | I65: 0.45 | J65: 527218 | K65: 0.43
B66: UTILIDAD NETA
B68: Gastos Financieros | E68: 73064 | G68: 0.03 | H68: 335152 | I68: 0.14 | J68: 60760 | K68: 0.05
B69: Otros Ingresos (-) | E69: -1005 | G69: 0 | H69: -105738 | I69: -0.04 | J69: -58374 | K69: -0.05
B70: Impuestos | E70: 257026 | G70: 0.12 | H70: 325737 | I70: 0.14 | J70: 146953 | K70: 0.12
E71: 419359 | G71: 0.19 | H71: 531466 | I71: 0.21 | J71: 377879 | K71: 0.31
B72: CONCILIACION
B74: Inv. o Vta. Activos Fijos | G74: 0 | H74: 515047 | I74: 0 | J74: 101726 | K74: 0
B75: Depreciacion del Ejercicio | G75: 0 | H75: 167359 | I75: 0 | J75: 92736 | K75: 0
E76: 0 | G76: 0 | H76: 682406 | I76: 0 | J76: 194462 | K76: 0
B78: CIFRA DE UTILIDADES EN EL BALANCE
B79: NOTA: Las cifras entre paréntesis se suman al Estado de Resultados.
B80: 0 | C80: 0 | K80: 4294967295 of 1

Sheet resumen ejecutivo
B2: Banregio Grupo Financiero
B3: SOLICITANTE | F3: =#N/A -> #N/A
B5: ACTIVIDAD | D5: AÑOS EN SU ACTIVIDAD | F5: 40 AÑOS
D7: ACTIVIDAD / PRODUCTOS / MARCA | F7: FABRICACIÓN DE GALLETAS DULCES Y DERIVADOS DE LAS MARCA MARIAN. SUS PRINCIPALES PRODUCTOS SON LAS GALLETAS DE TIPO SURTIDO MARIAN CLASICO Y SURTIDO MARIAN TRADICIONAL.
D9: PRINCIPALES CLIENTES | F9: NUEVA WAL MART (22%), COSTCO DE MÉXICO (12%), TIENDAS SORIANA (11%)
B12: EXPERIENCIA CON BGF | D12: CLIENTE DE CREDITO DESDE | F12: =#N/A -> #N/A | H12: CALIFICACION DE CARTERA | I12: N.A. | J12: PRE CALIFICACION DE CARTERA | L12: =#N/A -> #N/A
D14: FUERZAS / OPORTUNIDADES | I14: DEBILIDADES / AMENAZAS
G17: ( UNIDADES ) | K17: (MILES DE PESOS)
G18: N° DE CONTRATOS ARRENDADOS | K18: RTAS X DEV. | L18: SALDO
G19: VIGENTES | H19: TERMINADOS | I19: TOTAL
E20: ($501- ) | G20: 0 | I20: =+G20+H20 -> 0 | K20: 0
E21: ($201 - $500) | G21: 0 | I21: =+G21+H21 -> 0 | K21: 0
E22: ($0 - $200) | G22: 1 | I22: =+G22+H22 -> 1 | K22: 137
D24: SINIESTRO | H24: 8 | I24: =+G24+H24 -> 8
D25: CANCELACIÓN ANTICIPADA | H25: 0 | I25: =+G25+H25 -> 0
D26: TRANSPASO/ CESIÓN | H26: 0 | I26: =+G26+H26 -> 0
D27: TERMINACIÓN NORMAL | H27: 174 | I27: =+G27+H27 -> 174
D28: SALDOS VENCIDOS | K28: 3
D30: TOTALES | G30: =SUM(G20:G29) -> 1 | H30: =SUM(H20:H29) -> 182 | I30: =SUM(I20:I29) -> 183 | K30: =SUM(K20:K29) -> 140
D31: % | G31: =+IF(I30=0,0,G30/I30) -> 0.0054644809 | H31: =+IF(J30=0,0,H30/J30) -> 0 | I31: =+IF(K30=0,0,I30/K30) -> 1.3071429
D33: RENTAS DEVENGADAS | G33: 25
D35: PAGO DE RENTA MENSUAL ACTUAL | G35: 3.5 | I35: INTERES MORATORIO COBRADO DESDE | L35: 0
I36: EL ORIGEN DE LA CUENTA | L36: =IF((K30+G33)=0,0,+L35/(K30+G33)) -> 0
D37: RENTA PROMEDIO X UNIDAD | G37: =IF(G30=0,0,G35/G30) -> 3.5
B40: COMP. DE PAGO EN BC | D40: FECHA DE CONSULTA DE BC | F40: =#N/A -> #N/A | G40: CALIFICACION BURO DE CRÉDITO | I40: 1 B1 , 1 A2
D44: INSTITUCIÓN | E44: TIPO DE CRÉDITO | F44: N° DE | G44: ULTIMO | H44: HIST. 12 MESES | I44: FECHA DE | J44: SALDO
F45: CRÉDITOS | G45: MOP | I45: ACTUALIZACIÓN | J45: ORIGINAL | K45: VIGENTE | L45: VENCIDO
D47: ARRENDAMIENTO PURO (MASTERLEASE) | F47: 1 | G47: 1 | H47: 1 | I47: DICIEMBRE 09 | J47: 113 | K47: 106 | L47: 0
D48: OTRAS FINANCIERAS (ARREND PURO) | F48: 4 | G48: 2 | H48: 4 | I48: DICIEMBRE 09 | J48: 768 | K48: 202 | L48: 3
D49: CRÉDITO FISCAL | F49: 3 | G49: 5 | H49: 5 | I49: DICIEMBRE 09 | J49: =0.8+0.8+2 -> 3.6 | K49: 0 | L49: =+J49 -> 3.6
D50: BANCO (DESCUENTOS) | F50: 1 | G50: 1 | H50: 1 | I50: ENERO 10 | J50: 4858 | K50: 4038 | L50: 0
D51: LINEAS DE CRÉDITO (OTRAS FINANCIERAS) | F51: 5 | G51: 1 | H51: 1 | I51: DICIEMBRE 09 | J51: =2+0.6+0.7+3+20 -> 26.3 | K51: 0
D52: BANCO (SIMPLE) | F52: 3 | G52: 2 | H52: 2 | I52: ENERO 10 | J52: =2000+2250+8500 -> 12750 | K52: =1680+1064+8500 -> 11244 | L52: 0
D53: BANCO (TARJETA DE SERVICIO) | F53: 4 | G53: 1 | H53: 3 | I53: DICIEMBRE 09 | J53: 0 | K53: =50+54+39 -> 143 | L53: 0
E56: TOTAL | F56: =SUM(F48:F55) -> 20 | J56: =SUM(J47:J55) -> 18518.9 | K56: =SUM(K47:K55) -> 15733 | L56: =SUM(L48:L55) -> 6.6
D60: Notas:
D61: EL IMPORTE VENCIDO QUE REPORTAN LAS OTRAS FINANCIERAS ES UN SALDO DE $ 3,
D62: LOS SALDOS CON EL SAT (CREDITOS FISCALES) PRESENTAN UNA CLAVE DE OBSERVACION PC = CUENTA EN COBRANZA
D66: FUERZAS / OPORTUNIDADES | I66: DEBILIDADES / AMENAZAS
D67: -LOS SALDOS VENCIDOS NO SON REPRESENTATIVOS DE LOS SALDOS VIGIENTES Y CONSIDERANDO LAS CALIFICACIONES DE BURÓ DE CRÉDITO DE B1 Y A2 SE CONSIDERA SU HISTORIAL EN BURÓ DE CRÉDITO COMO REGULAR.
B71: CAPACIDAD DE PAGO | D71: FECHA | F71: =#N/A -> #N/A | I71: =#N/A -> #N/A
D72: INDICE DE LIQUIDEZ | F72: =#N/A -> #N/A | I72: =#N/A -> #N/A
D73: DS CXC | F73: =#N/A -> #N/A | I73: =#N/A -> #N/A
D74: DS CICLO FINANCIERO | F74: =#N/A -> #N/A | I74: =#N/A -> #N/A
D75: UTILIDAD NETA | F75: =#N/A -> #N/A | I75: =#N/A -> #N/A
D76: UAFIR/FINANCIEROS | F76: =#N/A -> #N/A | I76: =#N/A -> #N/A
D77: CRECIMIENTO EN VENTAS | F77: =#N/A -> #N/A | I77: =#N/A -> #N/A
D78: FUERZAS / OPORTUNIDADES | I78: DEBILIDADES / AMENAZAS
D79: -PRESENTA INDICES DE LIQUIDEZ FAVORABLES SOPORTADOS PRINCIPALMENTE POR CUENTAS POR COBRAR E INVENTARIOS. | I79: -EL CICLO FINANCIERO INCREMENTO SU PERIODO DERIVADO DEL CRECIMIENTO DE CUENTAS POR COBRAR E INVENTARIOS AUNADO A UN PRONTO PAGO DE PROVEEDORES.
D80: -PRESENTA CRECIMIENTO DE VENTAS CONSTANTES. | I80: - LA CAPACIDAD DE PAGO DE FLUJO DE EFECTIVO SE VIO AFECTADA POR LA GENERACIÓN DE FLUJO OPERATIVA ( INCREMENTO DE CxC, INVENTARIOS)
D81: - EL MARGEN DE UTILIDAD NETA ES EL MÁS ALTO DE LOS TRES EJERCICIOS REVISADOS.
B83: CAPACIDAD DE ENDEUDAMIENTO | D83: FECHA | F83: =+F71 -> #N/A | I83: =+I71 -> #N/A
D84: PASIVO TOTAL | F84: =#N/A -> #N/A | I84: =#N/A -> #N/A
D85: CAPITAL CONTABLE | F85: =#N/A -> #N/A | I85: =#N/A -> #N/A
D86: PASIVO FINANCIERO/PASIVO TOTAL | F86: =+#REF! -> #REF! | I86: =+#REF! -> #REF!
D87: APALANCAMIENTO (PT/CC) | F87: =#N/A -> #N/A | I87: =#N/A -> #N/A
D88: PASIVO FIN C.P. | F88: 8081 | I88: 10299
D89: PASIVO FIN L.P. (BANESTO ESPAÑA EN USD) IMPORTE YA CONVERTIDO A M.N. | F89: 23659 | I89: 23356
D90: PROVEEDORES | F90: 23852 | I90: 16789
D91: FUERZAS / OPORTUNIDADES | I91: DEBILIDADES / AMENAZAS
I92: - SU CAPITAL CONTABLE SE ENCUENTRA SOPORTADO PRINCIPALMENTE POR ACTUALIZACIONES.
B96: COLATERAL GARANTÍA | D96: FUERZAS / OPORTUNIDADES | I96: DEBILIDADES / AMENAZAS
D97: -AVAL DE INMOBILIARIA LA MATA, S.A. DE C.V. (PROPIETARIA DEL INMUEBLE DONDE SE UBICA GALLETAS DE CALIDAD), QUIEN REPORTA ACTIVOS TOTALES POR $ 32´000, EN DONDE LOS TERRENOS Y EDIFICIOS SUMAN $ 25,099,. NO REPORTA PASIVOS. EN SU BURO DE CREDITO NO REPORTA FINANCIAMIENTO ALGUNO.
B103: CONDICIONES OPERATIVAS | D103: FUERZAS / OPORTUNIDADES | I103: DEBILIDADES / AMENAZAS
B108: OTROS ASPECTOS RELEV. | D108: FUERZAS / OPORTUNIDADES | I108: DEBILIDADES / AMENAZAS
B115: RECOMENDACIÓN | D115: SE RECOMIENDA LA RATIFICACIÓN E INCREMENTO DE SU LÍNEA DE CRÉDITO EN BASE A: EXPERIENCIA DE PAGO FAVORABLE CON MASTERLEASE, CAPITAL DE TRABAJO SUFICIENTE PARA CUMPLIR CON SUS COMPROMISOS Y EXPERIENCIA EN EL GIRO AL QUE SE DEDICA POR MAS DE 40 AÑOS. POR OTRA PARTE, YA LE HEMOS ARRENDADO 183 CONTRATOS, DONDE ACTUALMENTE TIENE UN CONTRATO VIGENTE.
I117: OPINION | J117: FAVORABLE
D124: ELABORÓ
D127: ALBERTO SALINAS GUERRA

Sheet RIESGO ACTUAL
B5: =#REF! -> #REF!
B7: =#N/A -> #N/A
L8: =#N/A -> #N/A
D10: CLIENTE DESDE | E10: =#N/A -> #N/A
C12: NEGOCIO / CONVENIENCIA | G12: =+B7 -> #N/A
G14: ( UNIDADES ) | K14: (MILES DE PESOS)
G15: N° DE CONTRATOS ARRENDADOS | K15: RIESGO ACTUAL
G16: VIGENTES | H16: TERMINADOS | I16: TOTAL
D17: EJECUTIVOS | E17: ($501- ) | G17: 0 | I17: =+G17+H17 -> 0 | K17: 0
D18: EMPLEADOS | E18: ($201 - $500) | G18: 0 | I18: =+G18+H18 -> 0 | K18: 0
D19: UTILITARIOS | E19: ($0 - $200) | G19: 48 | I19: =+G19+H19 -> 48 | K19: 3689
D21: SINIESTRO | H21: 11 | I21: =+G21+H21 -> 11
D22: CANCELACIÓN ANTICIPADA | H22: 4 | I22: =+G22+H22 -> 4
D23: TRANSPASO/ CESIÓN | H23: 27 | I23: =+G23+H23 -> 27
D24: TERMINACIÓN NORMAL | H24: 219 | I24: =+G24+H24 -> 219
D26: TOTALES | G26: =SUM(G17:G25) -> 48 | H26: =SUM(H17:H25) -> 261 | I26: =SUM(I17:I25) -> 309 | K26: =SUM(K17:K25) -> 3689
D27: % | G27: =+G26/I26 -> 0.15533981 | H27: =+H26/I26 -> 0.84466019 | I27: =+I26/I26 -> 1
D32: NUMERO DE UNIDADES ARRENDADAS ACTUALES
D34: EJECUTIVOS | E34: ($501- ) | G34: 0
D35: EMPLEADOS | E35: ($201 - $500) | G35: 22
D36: UTILITARIOS | E36: ($0 - $200) | G36: 90
D38: TOTAL | G38: =SUM(G34:G36) -> 112
D41: TOTAL DE CONTRATOS OPERADOS (HISTORICO Y ACTUAL) | G41: =+G38+G49 -> 200
D44: SINIESTRO | G44: 10
D45: CANCELACIÓN ANTICIPADA | G45: 0
D46: TRANSPASO/ CESIÓN | G46: 0
D47: TERMINACIÓN NORMAL | G47: 78
D49: TOTAL DE CONTRATOS TERMINADOS | G49: =SUM(G44:G48) -> 88
D50: % | G50: =+G49/G41 -> 0.44
D53: RIESGO A LA FECHA | J53: (MILES DE PESOS)
G54: RIESGO ACTUAL
D56: EJECUTIVOS | E56: ($501- ) | G56: 0
D57: EMPLEADOS | E57: ($201 - $500) | G57: 10128
D58: UTILITARIOS | E58: ($0 - $200) | G58: 6486
D61: TOTAL | G61: =SUM(G56:G58) -> 16614
D64: PAGO DE RENTA MENSUAL ACTUAL | G64: 159.6
D66: RENTA PROMEDIO X UNIDAD | G66: =+G64/G26 -> 3.325
I67: CALIFICACION DE CONVENIENCIA | J67: BUENA
C71: COMPORTAMIENTO DE PAGO | D71: EXPERIENCIA INTERNA DE MASTERLEASE
D72: INTERES MORATORIO COBRADO DESDE
D73: EL ORIGEN DE LA CUENTA | G73: 44.262
D74: % | G74: =+G73/K26 -> 0.011998374
D77: EXPERIENCIA EXTERNA BURÓ DE CRÉDITO
D79: FECHA DE CONSULTA DE BURO DE CRÉDITO | F79: =#N/A -> #N/A
D81: NO PRESENTA ANTECEDENTES CREDITICIOS
D82: INSTITUCIÓN | E82: TIPO DE CRÉDITO | F82: N° DE | G82: ULTIMO | H82: HISTORICO 12 MESES | I82: FECHA DE | J82: SALDO | K82: SALDO | L82: SALDO
F83: CRÉDITOS | G83: MOP | H83: MOP | I83: ACTUALIZACIÓN | J83: ORIGINAL | K83: VIGENTE | L83: VENCIDO
D85: ARRENDAMIENTOS PUROS | F85: 59 | G85: 1 | H85: 1 | I85: JUNIO 09 | J85: =181135-173730 -> 7405 | K85: =89031-85483 -> 3548 | L85: 0
D86: BANCOS (TARJETAS DE SERVICIO) | F86: 6 | G86: 1 | H86: 6 | I86: OCTUBRE 09 | J86: 0 | K86: 0 | L86: 24
D87: OTRAS FINANCIERAS (REFACCIONARIO) | F87: 16 | G87: 1 | H87: 1 | I87: OCTUBRE 09 | J87: =585+585+604+604+604+1529+1545+1545+1545+2507+2507+2507+1656+1119+5432+5486 -> 30360 | K87: =3670+3622+564+833+1079+1016+1016+626+626+626+620+231+231+231+224+224 -> 15439 | L87: 0
D88: BANCOS (GTIA INMOBILIARIA) | F88: 1 | G88: 1 | H88: 1 | I88: NOVIEMBRE 09 | J88: 123370 | K88: 70034 | L88: 0
D89: BANCOS (SIMPLE) | F89: 1 | G89: 1 | H89: 1 | I89: OCTUBRE 09 | J89: 20000 | K89: 10 | L89: 0
E92: TOTAL | F92: =SUM(F85:F91) -> 83 | J92: =SUM(J85:J91) -> 181135 | K92: =SUM(K85:K91) -> 89031 | L92: =SUM(L85:L91) -> 24
D94: CALIFICACION BURO DE CRÉDITO | F94: 1 - C2
I98: CALIFICACION DE CONDUCTA INTERNA | J98: BUENA
I99: CALIFICACION DE CONDUCTA EXTERNA | J99: REGULAR
B103: CAPACIDAD DE PAGO
D105: NO CUENTA CON CAPACIDAD DE PAGO DE RENTAS CON SUS MARGENES DE OPERACIÓN AL 2009, SIN EMGARGO SI SE CONSIDERA EL 2008 CUENTA CON CAPACIDAD DE PAGO.
D107: CUENTA CON CAPACIDAD DE FLUJO DE EFECTIVO LIMITADA AL PARCIAL DEL 2009, PRINCIPALMENTE POR LA RELACIÓN INTER-FILIALES, SIN EMBARGO PARA EL CIERRE DEL 2008 PRESENTA CAPACIDAD DE PAGO DE SU FLUJO DE EFECTIVO Y DE SU MARGEN DE OPERACIÓN.
I110: CALIFICACION DE CAPACIDAD DE PAGO | J110: SUFICIENTE / LIMITADA
B114: CAPACIDAD DE ENDEUDAMIENTO
D116: SU NIVEL DE APALANCAMIENTO ES DE | F116: =#N/A -> #N/A
D118: =+#REF! -> #REF! | F118: =+#REF! -> #REF!
D120: LA RENTA MENSUAL ACTUAL ES DE | F120: =+G64 -> 159.6
D122: LA UTILIDAD DE OPERACIÓN MENSUAL ES | F122: =+#REF!/#REF! -> #REF!
E124: LA RENTA MENSUAL REPRESENTA EL | F124: =+F120/F122 -> #REF! | G124: DE LA UTILIDAD DE OPEARCIÓN
I127: CALIFICACION DE CAPACIDAD DE ENDEUDAMIENTO | J127: INSUFICIENTE
B131: COLATERAL GARANTÍA
D132: NO SE CUENTA CON FUENTE SECUNDARIA DE PAGO
I139: CALIFICACION DE GARANTÍA | J139: INSUFICIENTE
B143: OPINIÓN
D145: SE RECOMIENDA EN BASE A:
D146: SE RECOMIENDA APOYAR LA PROPUESTA EN BASE A LA TRAYECTORIA FAVORABLE DE PAGO EN MASTERLEASE Y A LA EXPERIENCIA EN EL GIRO DEL GRUPO DE EMPRESAS A LAS CUALES PERTENECE LA SOLICITANTE.
I153: OPINION | J153: FAVORABLE / LIMITADA

Sheet TERRENOS
C9: =#N/A -> #N/A
C11: RELACIONES ANALÍTICAS
C13: =#REF! -> #REF!
C15: TERRENOS
C17: DESCRIPCIÓN | D17: UBICACIÓN | E17: SUP. MTS² | F17: VALOR DE ADQUISICIÓN | G17: REVALUACIÓN | H17: VALOR TOTAL
C19: TERRENO | D19: LOTE 21 Y 44 DE FRACC CD. INDUSTRIAL, CELAYA, GTO | E19: 2115.5 | F19: 846 | G19: 998.2 | H19: =+F19+G19 -> 1844.2
C21: TERRENO | D21: LOTE 32 Y 33 DE FRACC ARBOLEDAS, UNIDAD PARQUES RESIDENCIALES DE QUERETARO, QRO. | E21: 3900 | F21: 3962.7 | G21: 4644.2 | H21: =+F21+G21 -> 8606.9
C23: EDIFICIO | D23: LOTE 32 Y 33 DE FRACC ARBOLEDAS, UNIDAD PARQUES RESIDENCIALES DE QUERETARO, QRO. | F23: 7291 | G23: 6252.5 | H23: =+F23+G23 -> 13543.5
C25: TERRENO | D25: LOTE EN FRACC LA TABLA DE LA VIRGEN, LEON, GTO. | E25: 2004.9 | F25: 1816.5 | G25: 1679.9 | H25: =+F25+G25 -> 3496.4
C27: EDIFICIO | D27: LOTE EN FRACC LA TABLA DE LA VIRGEN, LEON, GTO. | F27: 2461.5 | G27: 212.5 | H27: =+F27+G27 -> 2674
C29: TERRENO | D29: LOTE EN MIGUEL ALEMAN KM 14.8 APODACA, N.L. | E29: 4918 | F29: 4864.7 | G29: 2188.8 | H29: =+F29+G29 -> 7053.5
C31: EDIFICIO | D31: LOTE EN MIGUEL ALEMAN KM 14.8 APODACA, N.L. | F31: 1372.5 | G31: 0 | H31: =+F31+G31 -> 1372.5
C33: TERRENO | D33: LOTE EN MANZANA 5, DISTRITO 1-81 FRACC CUAUTITLÁN IZCALLI | E33: 4927296 | F33: 2082 | G33: 2456.6 | H33: =+F33+G33 -> 4538.6
C35: EDIFICIO | D35: LOTE EN MANZANA 5, DISTRITO 1-81 FRACC CUAUTITLÁN IZCALLI | F35: 15526.7 | G35: 10406.7 | H35: =+F35+G35 -> 25933.4
C37: TERRENO | D37: LOTE EN MANZANA 12, NUMERO 319 DE CALLE 21, UBICADO EN MERIDA, CD. INDUSTRIAL | F37: 497.5 | G37: 54.725 | H37: =+F37+G37 -> 552.225
C39: EDIFICIO | D39: LOTE EN MANZANA 12, NUMERO 319 DE CALLE 21, UBICADO EN MERIDA, CD. INDUSTRIAL | F39: 3009.9 | G39: 121.9 | H39: =+F39+G39 -> 3131.8
C41: EDIFICIO | D41: CONSTRUCCIÓN EN TEPOZTLAN, EDO MÉXICO, SOBRE TERRENO PROPIEDAD DE BIENES DEL CENTRO | F41: 63524.88 | G41: 966 | H41: =+F41+G41 -> 64490.88
D45: TOTAL | F45: =SUM(F19:F41) -> 107255.88 | G45: =SUM(G19:G41) -> 29982.025 | H45: =SUM(H19:H41) -> 137237.9

Sheet ANEXO1
B5: =#REF! -> #REF!
B7: =#N/A -> #N/A
B8: ANEXO 1
C10: AVAL 1: | D10: RAMIRO GONZALEZ GONZALEZ
D11: RFC | F11: GOGR 741111 EN8
D12: ESTADO CIVIL | F12: SOLTERO
D13: EDAD | F13: 35 AÑOS
C15: BALANCE GENERAL
C16: AL 31 DE ENERO DEL 2009
D18: ACTIVO CIRCULANTE | H18: 0
D20: ACTIVO FIJO
E21: TERRENOS Y EDIFICIOS | G21: 42000
D23: TOTAL ACTIVO FIJO | H23: =G21 -> 42000
D25: TOTAL ACTIVO | H25: =+H23+H18 -> 42000
D27: PASIVO CIRCULANTE | H27: 0
D29: PASIVO LARGO PLAZO | H29: 0
D31: PASIVO TOTAL | H31: =H29+H27 -> 0
D33: PATRIMONIO | H33: =H25-H31 -> 42000
D35: ESTADO DE RESULTADOS
D37: NO DISPONIBLE
C39: INMUEBLES REPORTADOS
C40: DESCRIPCIÓN | E40: MTS² | F40: MTS² | G40: VALOR | H40: PROPIETARIO | I40: VERIF | J40: FECHA
E41: TERRENO | F41: COSNTR.
B42: 1.- | C42: TERRENO URBANO INDUSTRIAL, UBICADO EN LOTE N° 2 MANZANA N° 37, DISTRITO INDUSTRIAL MARITIMO DE ALTAMIRA, TAMPS. | E42: 42282 | F42: N.D. | G42: 39000 | H42: =D10 -> RAMIRO GONZALEZ GONZALEZ | I42: LIBRE DE GRAVAMEN | J42: 39987
C43: REG: 3803, VOL: 33, LIB 6-077, FECHA: 06-03-2003, TAMPS.
B44: 2.- | C44: DEPARTAMENTO UBICADO EN AVE. LOS ARCANGELES N° 1001, FRACC. LOS ARCANGELES, SAN PEDRO GRAZA GARCÍA, N.L. | E44: 230 | F44: N.D. | G44: 3000 | H44: =H42 -> RAMIRO GONZALEZ GONZALEZ | I44: LIBRE DE GRAVAMEN | J44: 39989
C45: REG: 860, VOL: 98, LIB 36, FECHA: 06-06-2006
C47: TOTAL | E47: =SUM(E42:E44) -> 42512 | G47: =SUM(G42:G44) -> 42000
D49: B.R. LIBRES | F49: 2 | G49: 42000
D50: B.R. GRAVADOS
D51: B.R. TERCEROS
D52: B.R. PENDIENTES
D54: TOTAL BIENES RAICES | F54: =SUM(F49:F53) -> 2 | G54: =SUM(G49:G52) -> 42000
C55: BURÓ DE CRÉDITO
C57: FECHA DE CONSULTA | E57: 40049 | G57: CANTIDAD DE CUENTAS ABIERTAS | J57: 6
C58: SALDO VIGENTE | E58: 342 | G58: CANTIDAD DE CUENTAS CERRADAS | J58: 4
C59: SALDO VENCIDO | E59: 0 | G59: NUMERO DE CONSULTAS | J59: 36
C60: MOP MAXIMO ULTIMO AÑO | E60: 1
C62: CALIFICACIÓN BURÓ | E62: 1A1 | G62: INTERPRETACIÓN | I62: BUEN HISTORIAL
C63: BC SCORE | E63: 701
B67: =B5 -> #REF!
B69: =B7 -> #N/A
B70: ANEXO 1
C72: AVAL 2: | D72: RAMIRO GONZALEZ GARCIA
D73: RFC | F73: GOGR 490204 CM2
D74: ESTADO CIVIL | F74: NO DISPONIBLE
D75: EDAD | F75: 60 AÑOS
C77: BALANCE GENERAL
D79: NO DISPONIBLE
D81: ESTADO DE RESULTADOS
D83: NO DISPONIBLE
C85: BURÓ DE CRÉDITO (NO DISPONIBLE)
C87: FECHA DE CONSULTA | G87: CANTIDAD DE CUENTAS ABIERTAS
C88: SALDO VIGENTE | G88: CANTIDAD DE CUENTAS CERRADAS
C89: SALDO VENCIDO | G89: NUMERO DE CONSULTAS
C90: MOP MAXIMO ULTIMO AÑO
C92: CALIFICACIÓN BURÓ | G92: INTERPRETACIÓN
C93: BC SCORE

Sheet CALIF
A2: =#REF! -> #REF! | U2: Sectores de Actividad Económica | Z2: Calificación de Riesgo Trim I 2009
U3: Agropecuario, Silvicultura y Pesca | Z3: B-3
A4: RAZONES FINANCIERAS HISTÓRICAS PARA CALIFICACIÓN DE LA CARTERA | U4: Minería | Z4: D
F5: =#REF! -> #REF! | H5: =#REF! -> #REF! | J5: =#REF! -> #REF! | U5: Electricidad, Gas y Agua | Z5: C-1
A6: FLUJO DE EFECTIVO | U6: Construcción | Z6: C-1
A7: Flujo Operativo / Total Financiamiento Externo | D7: Base | F7: 0 | H7: =#REF!/(#REF!+#REF!) -> #REF! | J7: =#REF!/(#REF!+#REF!) -> #REF! | U7: Industria Manufacturera | Z7: C-1
A8: Flujo Operativo / Pasivo Corto Plazo | D8: Base | F8: 0 | H8: =#REF!/#REF! -> #REF! | J8: =#REF!/#REF! -> #REF! | U8: Carnes y Lácteos | Z8: B-3
A9: Flujo Operativo / Pasivo Total | D9: Base | F9: 0 | H9: =#REF!/#REF! -> #REF! | J9: =#REF!/#REF! -> #REF! | U9: Textiles, Prendas de Vestir e Industria del Cuero | Z9: D
A10: EBITDA / Intereses | D10: Base | F10: =#REF! -> #REF! | H10: =#REF! -> #REF! | J10: =#REF! -> #REF! | M10: Actividad o giro | N10: =#N/A -> #N/A | U10: Imprentas y Editoriales | Z10: C-2
A11: EBITDA / Pasivo con Costo Financiero | D11: Base | F11: =#REF! -> #REF! | H11: =#REF! -> #REF! | J11: =#REF! -> #REF! | N11: B-3 | U11: Artículos de Plástico | Z11: C-1
U12: Productos a base de minerales no metálicos | Z12: C-1
A13: LIQUIDEZ | U13: Vidrio y Productos de Vidrio | Z13: B-3
A14: Indice de Liquidez | D14: 0 | F14: =#REF! -> #REF! | H14: =#REF! -> #REF! | J14: =#REF! -> #REF! | U14: Industrias Básicas de Hierro y Acero | Z14: C-1
A15: Liquidez Inmediata | D15: 0 | F15: =#REF! -> #REF! | H15: =#REF! -> #REF! | J15: =#REF! -> #REF! | U15: Productos Metálicos, Maquinaria y Equipo | Z15: C-1
A16: Capital de Trabajo Neto ($) | D16: 0 | F16: =#REF! -> #REF! | H16: =#REF! -> #REF! | J16: =#REF! -> #REF! | U16: Comercio, Restaurantes y Hoteles | Z16: C-1
U17: Comercio | Z17: C-1
A18: APALANCAMIENTO | U18: Transporte, Almacenaje y Comunicaciones | Z18: B-3
A19: Pasivo Total / Activo Total | D19: 0 | F19: =#REF! -> #REF! | H19: =#REF! -> #REF! | J19: =#REF! -> #REF! | U19: Transporte | Z19: C-1
A20: Pasivo Total / Capital Contable | D20: 0 | F20: =#REF! -> #REF! | H20: =#REF! -> #REF! | J20: =#REF! -> #REF! | U20: Servicios Financieros, Seguros, Actividades Inmobiliarias y de Alquiler | Z20: C-1
A21: Instituciones Financieras / Pasivo Total | D21: 0 | F21: =#REF! -> #REF! | H21: =#REF! -> #REF! | J21: =#REF! -> #REF! | U21: Servicios Comunales, Sociales y Personales | Z21: C-1
U22: Servicios Profesionales | Z22: C-2
A23: RENTABILIDAD Y EFICIENCIA | U23: Servicios Médicos | Z23: B-3
A24: Utilidad Neta / Activo Total | D24: 0 | F24: =#REF! -> #REF! | H24: =#REF! -> #REF! | J24: =#REF! -> #REF! | U24: Agrupaciones mercantiles, profesionales, cívicas, políticas, laborales y religiosas | Z24: B-3
A25: Utilidad Neta / Capital Contable | D25: 0 | F25: =#REF! -> #REF! | H25: =#REF! -> #REF! | J25: =#REF! -> #REF! | U25: Gobierno | Z25: B-3
A26: Utilidad Neta / Ventas Netas | D26: 0 | F26: =#REF! -> #REF! | H26: =#REF! -> #REF! | J26: =#REF! -> #REF! | U26: Empleados, profesionistas independientes y similares | Z26: C-2
A27: Utilidad Oper. / Ints. Pagados | D27: 0 | F27: =IF(#REF!=0,0,#REF!/#REF!) -> #REF! | H27: =IF(#REF!=0,0,#REF!/#REF!) -> #REF! | J27: =IF(#REF!=0,0,#REF!/#REF!) -> #REF!
A28: Días Cartera | D28: 0 | F28: =#REF! -> #REF! | H28: =#REF! -> #REF! | J28: =#REF! -> #REF!
A29: Días Inventarios | D29: 0 | F29: =#REF! -> #REF! | H29: =#REF! -> #REF! | J29: =#REF! -> #REF!
A30: Ciclo Financiero | D30: 0 | F30: =F28+F29 -> #REF! | H30: =H28+H29 -> #REF! | J30: =J28+J29 -> #REF!
A31: Días Proveedores | D31: 0 | F31: =#REF! -> #REF! | H31: =#REF! -> #REF! | J31: =#REF! -> #REF!
B32: C A L I F I C A C I O N E S | E32: Calificación | F32: Calificación | G32: Calificación | H32: Reservas
B33: Riesgo | C33: Riesgo | D33: Riesgo | E33: Experiencia | F33: Acumulada | G33: A1 = 1 | H33: 0.005
B34: País | C34: Financiero | D34: Industria | E34: de Pago B.C. | F34: del Deudor | G34: A2 = 2 | H34: 0.0099
B35: 0 | C35: =K80 -> #REF! | D35: =VLOOKUP(D36,$O$41:$P$49,2) -> 5 | E35: =VLOOKUP(E36,$O$41:$P$49,2) -> 7 | F35: =HLOOKUP(E35,C49:K58,C35+1) -> #REF! | G35: B1 = 3 | H35: 0.0499
C36: =VLOOKUP(C35,$P$85:$Q$93,2) -> #REF! | D36: B3 | E36: =VLOOKUP(Pre_calif!K46,M41:O49,3) -> C2 | F36: =VLOOKUP(F35,$P$85:$Q$93,2) -> #REF! | G36: B2 = 4 | H36: 0.0999
F37: =(VLOOKUP(F35,$P$85:$R$93,3)) -> #REF! | G37: B3 = 5 | H37: 0.1999
G38: C1 = 6 | H38: 0.3999
G39: C2 = 7 | H39: 0.5999
G40: D = 8 | H40: 0.8999
G41: E = 9 | H41: 1 | M41: 0 | N41: 0 | O41: A1 | P41: 1
C42: CALIFICACIÓN DE LA EXPERIENCIA DE PAGO EN EL BURÓ DE CRÉDITO | M42: 1 | N42: 14 | O42: A2 | P42: 2
C43: A1 = 1 | D43: A2 = 2 | E43: B1 = 3 | F43: B2 = 4 | G43: B3 = 5 | H43: C1 = 6 | I43: C2 = 7 | J43: D = 8 | K43: E = 9 | M43: 15 | N43: 29 | O43: B1 | P43: 3
B44: Días Atraso | C44: 0 | D44: 1 a 14 | E44: 15 a 29 | F44: 30 a 44 | G44: 45 a 59 | H44: 60 a 89 | I44: 90 a 179 | J44: 180 a 365 | K44: > 365 | M44: 30 | N44: 44 | O44: B2 | P44: 4
M45: 45 | N45: 59 | O45: B3 | P45: 5
B46: CALIFICACIÓN ACUMULADA DEL DEUDOR | M46: 60 | N46: 89 | O46: C1 | P46: 6
B47: Calificación | C47: Calificación de la Experiencia de Pago | M47: 90 | N47: 179 | O47: C2 | P47: 7
B48: Acumulada | C48: A1 = 1 | D48: A2 = 2 | E48: B1 = 3 | F48: B2 = 4 | G48: B3 = 5 | H48: C1 = 6 | I48: C2 = 7 | J48: D = 8 | K48: E = 9 | M48: 180 | N48: 365 | O48: D | P48: 8
C49: 1 | D49: 2 | E49: 3 | F49: 4 | G49: 5 | H49: 6 | I49: 7 | J49: 8 | K49: 9 | M49: 366 | N49: 10000000 | O49: E | P49: 9
A50: 1 | B50: A1 = 1 | C50: 1 | D50: 1 | E50: 2 | F50: 3 | G50: 4 | H50: 5 | I50: 7 | J50: 8 | K50: 9
A51: 2 | B51: A2 = 2 | C51: 1 | D51: 2 | E51: 2 | F51: 3 | G51: 4 | H51: 5 | I51: 7 | J51: 8 | K51: 9
A52: 3 | B52: B1 = 3 | C52: 2 | D52: 3 | E52: 3 | F52: 3 | G52: 4 | H52: 5 | I52: 7 | J52: 8 | K52: 9
A53: 4 | B53: B2 = 4 | C53: 3 | D53: 4 | E53: 4 | F53: 4 | G53: 4 | H53: 5 | I53: 7 | J53: 8 | K53: 9
A54: 5 | B54: B3 = 5 | C54: 4 | D54: 5 | E54: 5 | F54: 5 | G54: 5 | H54: 5 | I54: 7 | J54: 8 | K54: 9
A55: 6 | B55: C1 = 6 | C55: 5 | D55: 6 | E55: 6 | F55: 6 | G55: 6 | H55: 6 | I55: 7 | J55: 8 | K55: 9
A56: 7 | B56: C2 = 7 | C56: 7 | D56: 7 | E56: 7 | F56: 7 | G56: 7 | H56: 7 | I56: 7 | J56: 8 | K56: 9
A57: 8 | B57: D = 8 | C57: 8 | D57: 8 | E57: 8 | F57: 8 | G57: 8 | H57: 8 | I57: 8 | J57: 8 | K57: 9
A58: 9 | B58: E = 9 | C58: 9 | D58: 9 | E58: 9 | F58: 9 | G58: 9 | H58: 9 | I58: 9 | J58: 9 | K58: 9
A63: =A2 -> #REF!
C64: A1 | D64: A2 | E64: B1 | F64: B2 | G64: B3 | H64: C1 | I64: C2 | J64: D | K64: E
A65: Calificación Riesgo Fin. | C65: 1 a 4.99 | D65: 5 a 5.99 | E65: 6 a 6.33 | F65: 6.34 a 6.66 | G65: 6.67 a 6.99 | H65: 7 a 7.99 | I65: 8 a 8.99 | J65: 9 | K65: 9
L66: RAZON | O66: PESO
E67: =D5 -> 0 | G67: =F5 -> #REF! | I67: =H5 -> #REF! | K67: =J5 -> #REF! | L67: TIPO | M67: DEFINICION | O67: ESPECIF.
A68: Cobertura de Intereses: | E68: =HLOOKUP(D68,$P68:$AE$75,8) -> 7 | F68: =(#REF!+#REF!)/#REF! -> #REF! | G68: =HLOOKUP(F68,$P68:$AE$75,8) -> #REF! | H68: =(#REF!+#REF!)/#REF! -> #REF! | I68: =HLOOKUP(H68,$P68:$AE$75,8) -> #REF! | J68: =IF(#REF!=0,0,(#REF!+#REF!)/#REF!)-1 -> #REF! | K68: =HLOOKUP(J68,$P68:$AE$75,8) -> #REF! | L68: 1 | M68: Cobertura de Intereses: | O68: 0.2 | P68: -2000 | Q68: -1 | R68: =(Q68+S68)/2 -> -0.53 | S68: -0.06 | T68: =(S68+U68)/2 -> 0.355 | U68: 0.77 | V68: =(U68+W68)/2 -> 1.04 | W68: 1.31 | X68: =(W68+Y68)/2 -> 1.805 | Y68: 2.3 | Z68: =(Y68+AA68)/2 -> 3.355 | AA68: 4.41 | AB68: =(AA68+AC68)/2 -> 6.86 | AC68: 9.31 | AD68: =(AC68+AE68)/2 -> 13.005 | AE68: 16.7
A69: Cob.Ints.Respecto a Flujo Fondos: | E69: =HLOOKUP(D69,$P69:$AE$75,7) -> 7.5 | F69: =(+#REF!+#REF!+#REF!)/#REF! -> #REF! | G69: =HLOOKUP(F69,$P69:$AE$75,7) -> #REF! | H69: =(+#REF!+#REF!+#REF!)/#REF! -> #REF! | I69: =HLOOKUP(H69,$P69:$AE$75,7) -> #REF! | J69: =IF(#REF!=0,0,(+#REF!+#REF!+#REF!)/#REF!)-1 -> #REF! | K69: =HLOOKUP(J69,$P69:$AE$75,7) -> #REF! | L69: =+L68+1 -> 2 | M69: Cob.Ints.Respecto a Flujo Fondos: | O69: 0.2 | P69: -2000 | Q69: -0.57 | R69: =(Q69+S69)/2 -> 0 | S69: 0.57 | T69: =(S69+U69)/2 -> 1.04 | U69: 1.51 | V69: =(U69+W69)/2 -> 1.935 | W69: 2.36 | X69: =(W69+Y69)/2 -> 3.19 | Y69: 4.02 | Z69: =(Y69+AA69)/2 -> 5.22 | AA69: 6.42 | AB69: =(AA69+AC69)/2 -> 9.545 | AC69: 12.67 | AD69: =(AC69+AE69)/2 -> 16.395 | AE69: 20.12
A70: Cobertura de la Deuda: | E70: =HLOOKUP(D70,$P70:$AE$75,6) -> 7.5 | F70: =IF((#REF!+#REF!+#REF!+#REF!)>0,((#REF!+#REF!)/(#REF!+#REF!+#REF!+#REF!))*100,((#REF!+#REF!)/(#REF!*0.05))*100) -> #REF! | G70: =HLOOKUP(F70,$P70:$AE$75,6) -> #REF! | H70: =IF((#REF!+#REF!+#REF!+#REF!)>0,((#REF!+#REF!)/(#REF!+#REF!+#REF!+#REF!))*100,((#REF!+#REF!)/(#REF!*0.05))*100) -> #REF! | I70: =HLOOKUP(H70,$P70:$AE$75,6) -> #REF! | J70: =IF((#REF!+#REF!+#REF!+#REF!)>0,((#REF!+#REF!)/(#REF!+#REF!+#REF!+#REF!))*100,((#REF!+#REF!)/(#REF!*0.05))*100) -> #REF! | K70: =HLOOKUP(J70,$P70:$AE$75,6) -> #REF! | L70: =+L69+1 -> 3 | M70: Cobertura de la Deuda: | O70: 0.1333 | P70: -2000 | Q70: -4.8 | R70: =(Q70+S70)/2 -> 0 | S70: 4.8 | T70: =(S70+U70)/2 -> 7 | U70: 9.2 | V70: =(U70+W70)/2 -> 12.65 | W70: 16.1 | X70: =(W70+Y70)/2 -> 21.9 | Y70: 27.7 | Z70: =(Y70+AA70)/2 -> 35.4 | AA70: 43.1 | AB70: =(AA70+AC70)/2 -> 57.9 | AC70: 72.7 | AD70: =(AC70+AE70)/2 -> 100.6 | AE70: 128.5
A71: Cobertura Neta de la Deuda: | E71: =HLOOKUP(D71,$P71:$AE$75,5) -> 5 | F71: Nd | G71: =HLOOKUP(F71,$P71:$AE$75,5) -> #N/A | H71: =IF((#REF!+#REF!+#REF!+#REF!)>0,((#REF!-#REF!)/(#REF!+#REF!+#REF!+#REF!))*100,((#REF!-#REF!)/(#REF!*0.05))*100) -> #REF! | I71: =HLOOKUP(H71,$P71:$AE$75,5) -> #REF! | J71: =IF((#REF!+#REF!+#REF!+#REF!)>0,((#REF!-#REF!)/(#REF!+#REF!+#REF!+#REF!))*100,((#REF!-#REF!)/(#REF!*0.05))*100) -> #REF! | K71: =HLOOKUP(J71,$P71:$AE$75,5) -> #REF! | L71: =+L70+1 -> 4 | M71: Cobertura neta de la Deuda: | O71: 0.1333 | P71: -5000 | Q71: -3.9 | R71: =(Q71+S71)/2 -> -3.3 | S71: -2.7 | T71: =(S71+U71)/2 -> -2.3 | U71: -1.9 | V71: =(U71+W71)/2 -> -0.3 | W71: 1.3 | X71: =(W71+Y71)/2 -> 2.7 | Y71: 4.1 | Z71: =(Y71+AA71)/2 -> 8.7 | AA71: 13.3 | AB71: =(AA71+AC71)/2 -> 21.95 | AC71: 30.6 | AD71: =(AC71+AE71)/2 -> 32.7 | AE71: 34.8
A72: Rendimiento del Capital: | E72: =HLOOKUP(D72,$P72:$AE$75,4) -> 7 | F72: =((#REF!+#REF!)/(#REF!+#REF!+#REF!+#REF!+#REF!))*100 -> #REF! | G72: =HLOOKUP(F72,$P72:$AE$75,4) -> #REF! | H72: =((#REF!+#REF!)/((#REF!+#REF!+#REF!+#REF!+#REF!+#REF!+#REF!+#REF!+#REF!+#REF!)/2))*100 -> #REF! | I72: =HLOOKUP(H72,$P72:$AE$75,4) -> #REF! | J72: =((#REF!+#REF!)/((#REF!+#REF!+#REF!+#REF!+#REF!+#REF!+#REF!+#REF!+#REF!+#REF!)/2))*100 -> #REF! | K72: =HLOOKUP(J72,$P72:$AE$75,4) -> #REF! | L72: =+L71+1 -> 5 | M72: Rendimiento del Capital: | O72: 0.0667 | P72: -2000 | Q72: -4 | R72: =(Q72+S72)/2 -> -2.2 | S72: -0.4 | T72: =(S72+U72)/2 -> 2.85 | U72: 6.1 | V72: =(U72+W72)/2 -> 7.95 | W72: 9.8 | X72: =(W72+Y72)/2 -> 9.9 | Y72: 10 | Z72: =(Y72+AA72)/2 -> 12.45 | AA72: 14.9 | AB72: =(AA72+AC72)/2 -> 17.05 | AC72: 19.2 | AD72: =(AC72+AE72)/2 -> 23.7 | AE72: 28.2
A73: Margen de Operación: | E73: =HLOOKUP(D73,$P73:$AE$75,3) -> 9 | F73: =#REF! -> #REF! | G73: =HLOOKUP(F73,$P73:$AE$75,3) -> #REF! | H73: =#REF! -> #REF! | I73: =HLOOKUP(H73,$P73:$AE$75,3) -> #REF! | J73: =#REF! -> #REF! | K73: =HLOOKUP(J73,$P73:$AE$75,3) -> #REF! | L73: =+L72+1 -> 6 | M73: Margen de Operación: | O73: 0.0667 | P73: -21 | Q73: 0.07 | R73: =(Q73+S73)/2 -> 0.08 | S73: 0.09 | T73: =(S73+U73)/2 -> 0.0935 | U73: 0.097 | V73: =(U73+W73)/2 -> 0.1 | W73: 0.103 | X73: =(W73+Y73)/2 -> 0.113 | Y73: 0.123 | Z73: =(Y73+AA73)/2 -> 0.131 | AA73: 0.139 | AB73: =(AA73+AC73)/2 -> 0.1495 | AC73: 0.16 | AD73: =(AC73+AE73)/2 -> 0.188 | AE73: 0.216
P74: D | Q74: D | R74: =S74 -> CCC | S74: CCC | T74: =U74 -> B | U74: B | V74: =W74 -> BB | W74: BB | X74: =Y74 -> BBB | Y74: BBB | Z74: =AA74 -> A | AA74: A | AB74: =AC74 -> AA | AC74: AA | AD74: =AE74 -> AAA | AE74: AAA
P75: 9 | Q75: 8 | R75: 7.5 | S75: 7 | T75: =U75 -> 6 | U75: 6 | V75: =W75 -> 5 | W75: 5 | X75: =Y75 -> 4 | Y75: 4 | Z75: =AA75 -> 3 | AA75: 3 | AB75: =AC75 -> 2 | AC75: 2 | AD75: =AE75 -> 1 | AE75: 1
E76: =D5 -> 0 | G76: =F5 -> #REF! | I76: =H5 -> #REF! | K76: =J5 -> #REF!
A77: Pas.c/Costo Fin. LP a Cap. Cont.: | E77: =HLOOKUP(D77,$R77:$AH$80,4) -> 1 | F77: =+((#REF!+#REF!)/(#REF!+#REF!+#REF!))*100 -> #REF! | G77: =HLOOKUP(F77,$R77:$AH$80,4) -> #REF! | H77: =+((#REF!+#REF!)/(#REF!+#REF!+#REF!))*100 -> #REF! | I77: =HLOOKUP(H77,$R77:$AH$80,4) -> #REF! | J77: =+((#REF!+#REF!)/(#REF!+#REF!+#REF!))*100 -> #REF! | K77: =HLOOKUP(J77,$R77:$AH$80,4) -> #REF! | L77: 8 | M77: Pas.c/Costo Fin. LP a Cap. Cont.: | O77: 0.0667 | R77: -52000 | S77: 11.1 | T77: =(S77+U77)/2 -> 14.05 | U77: 17 | V77: =(U77+W77)/2 -> 23.35 | W77: 29.7 | X77: =(W77+Y77)/2 -> 35.05 | Y77: 40.4 | Z77: =(Y77+AA77)/2 -> 46.7 | AA77: 53 | AB77: =(AA77+AC77)/2 -> 54.9 | AC77: 56.8 | AD77: =(AC77+AE77)/2 -> 65.8 | AE77: 74.8 | AF77: =(AE77+AG77)/2 -> 87.4 | AG77: 100 | AH77: 150
A78: Pas.c/Costo Fin.Total a Cap. Cont.: | E78: =HLOOKUP(D78,$R78:$AH$80,3) -> 1 | F78: =+((#REF!+#REF!+#REF!+#REF!)/(#REF!+#REF!+#REF!+#REF!+#REF!))*100 -> #REF! | G78: =HLOOKUP(F78,$R78:$AH$80,3) -> #REF! | H78: =+((#REF!+#REF!+#REF!+#REF!)/(#REF!+#REF!+#REF!+#REF!+#REF!))*100 -> #REF! | I78: =HLOOKUP(H78,$R78:$AH$80,3) -> #REF! | J78: =+((#REF!+#REF!+#REF!+#REF!)/(#REF!+#REF!+#REF!+#REF!+#REF!))*100 -> #REF! | K78: =HLOOKUP(J78,$R78:$AH$80,3) -> #REF! | L78: 7 | M78: Pas.c/Costo Fin.Total a Cap. Cont.: | O78: 0.1333 | R78: -52000 | S78: 21.9 | T78: =(S78+U78)/2 -> 24.15 | U78: 26.4 | V78: =(U78+W78)/2 -> 31.8 | W78: 37.2 | X78: =(W78+Y78)/2 -> 41.85 | Y78: 46.5 | Z78: =(Y78+AA78)/2 -> 53.1 | AA78: 59.7 | AB78: =(AA78+AC78)/2 -> 62.8 | AC78: 65.9 | AD78: =(AC78+AE78)/2 -> 75.25 | AE78: 84.6 | AF78: =(AE78+AG78)/2 -> 92.3 | AG78: 100 | AH78: 180
A79: CALIFICACION RIESGO FINANCIERO: | E79: =SUMPRODUCT(E68:E78,$O$68:$O$78) -> 5.83345 | G79: =SUMPRODUCT(G68:G78,$O$68:$O$78) -> #REF! | I79: =SUMPRODUCT(I68:I78,$O$68:$O$78) -> #REF! | K79: =SUMPRODUCT(K68:K78,$O$68:$O$78) -> #REF! | N79: TOTAL | O79: =SUM(O68:O78) -> 1 | R79: =S79 -> AAA | S79: AAA | T79: =U79 -> AA | U79: AA | V79: =W79 -> A | W79: A | X79: =Y79 -> BBB | Y79: BBB | Z79: =AA79 -> BB | AA79: BB | AB79: =AC79 -> B | AC79: B | AD79: =AE79 -> CCC | AE79: CCC | AF79: D | AG79: D | AH79: E
E80: =VLOOKUP(E$79,$N$85:$Q$93,3) -> 2 | G80: =VLOOKUP(G$79,$N$85:$Q$93,3) -> #REF! | I80: =VLOOKUP(I$79,$N$85:$Q$93,3) -> #REF! | K80: =VLOOKUP(K$79,$N$85:$Q$93,3) -> #REF! | R80: =S80 -> 1 | S80: 1 | T80: =U80 -> 2 | U80: 2 | V80: =W80 -> 3 | W80: 3 | X80: =Y80 -> 4 | Y80: 4 | Z80: =AA80 -> 5 | AA80: 5 | AB80: =AC80 -> 6 | AC80: 6 | AD80: =AE80 -> 7 | AE80: 7 | AF80: 8 | AG80: 8.5 | AH80: 9
N85: 1 | O85: 4.99 | P85: 1 | Q85: A1 | R85: 0.005
N86: 5 | O86: 5.99 | P86: 2 | Q86: A2 | R86: 0.0099
N87: 6 | O87: 6.33 | P87: 3 | Q87: B1 | R87: 0.0499
N88: 6.34 | O88: 6.66 | P88: 4 | Q88: B2 | R88: 0.0999
N89: 6.67 | O89: 6.99 | P89: 5 | Q89: B3 | R89: 0.1999
N90: 7 | O90: 7.99 | P90: 6 | Q90: C1 | R90: 0.3999
N91: 8 | O91: 8.99 | P91: 7 | Q91: C2 | R91: 0.5999
N92: 9 | O92: 9 | P92: 8 | Q92: D | R92: 0.8999
N93: 9 | O93: 9 | P93: 9 | Q93: E | R93: 1

Sheet Pre_calif
D10: Pre – Calificación del Deudor
E13: Nombre del Cliente: | G13: =+#REF! -> #REF!
E14: Fecha de la Pre Calificación | G14: =#N/A -> #N/A
E15: Analista | G15: =#N/A -> #N/A
E17: Calificación del Deudor | G17: =L27 -> #REF!
E19: Sector | G19: =+sectores!L13 -> INDUSTRIA MANUFACTURERA
E20: Giro | G20: =+CALIF!N10 -> #N/A
D24: Riesgo | E24: Riesgo | I24: Riesgo | J24: Experiencia | L24: Calificación
D25: País | E25: Financiero | I25: Industria | J25: de Pago B.C. | L25: del Deudor
D27: N.A. | E27: =CALIF!C36 -> #REF! | I27: =VLOOKUP(G19,sectores!L7:M17,2) -> C1 | J27: =CALIF!E36 -> C2 | L27: =CALIF!F36 -> #REF!
E33: Pond. | F33: Razones Financieras | J33: Solicitante
J34: Fecha Buró | K34: =#N/A -> #N/A
E35: =CALIF!O68 -> 0.2 | F35: Cobertura de Intereses: | G35: =CALIF!J68 -> #REF! | H35: =CALIF!K68*CALIF!O68 -> #REF! | J35: Días de atraso buró | K35: 120
E36: =CALIF!O69 -> 0.2 | F36: Cob.Ints.Respecto a Flujo Fondos: | G36: =CALIF!J69 -> #REF! | H36: =CALIF!K69*CALIF!O69 -> #REF! | J36: Días de atraso Banregio | K36: 0
E37: =CALIF!O70 -> 0.1333 | F37: Cobertura de la Deuda: | G37: =CALIF!J70 -> #REF! | H37: =CALIF!K70*CALIF!O70 -> #REF! | J37: Días de atraso AF Banregio | K37: 0
E38: =CALIF!O71 -> 0.1333 | F38: Cobertura neta de la Deuda: | G38: =CALIF!J71 -> #REF! | H38: =CALIF!K71*CALIF!O71 -> #REF!
E39: =CALIF!O72 -> 0.0667 | F39: Rendimiento del Capital: | G39: =CALIF!J72 -> #REF! | H39: =CALIF!K72*CALIF!O72 -> #REF! | J39: Aval
E40: =CALIF!O73 -> 0.0667 | F40: Margen de Operación: | G40: =CALIF!J73 -> #REF! | H40: =CALIF!K73*CALIF!O73 -> #REF! | J40: Fecha Buró | K40: 0
E41: =CALIF!O77 -> 0.0667 | F41: Pas.c/Costo Fin. LP a Cap. Cont.: | G41: =CALIF!J77 -> #REF! | H41: =CALIF!K77*CALIF!O77 -> #REF! | J41: Días de atraso buró | K41: 0
E42: =CALIF!O78 -> 0.1333 | F42: Pas.c/Costo Fin.Total a Cap. Cont.: | G42: =CALIF!J78 -> #REF! | H42: =CALIF!K78*CALIF!O78 -> #REF! | J42: Días de atraso Banregio | K42: 0
J43: Días de atraso AF Banregio | K43: 0
E44: =SUM(E32:E43) -> 1 | F44: Resultado | H44: =SUM(H32:H43) -> #REF!
F46: A1 | G46: 1 a 4.99 | J46: Mayor atraso | K46: =MAX(K35,K36,K37,K41,K42,K43) -> 120
F47: A2 | G47: 5 a 5.99
F48: B1 | G48: 6 a 6.33
F49: B2 | G49: 6.34 a 6.66
F50: B3 | G50: 6.67 a 6.99
F51: C1 | G51: 7 a 7.99
F52: C2 | G52: 8 a 8.99
F53: D | G53: 9
F54: E | G54: 9

Sheet sectores
D1: ACTIVIDAD DE CATALOGO | E1: SECTOR | F1: SUBSECTOR | G1: RAMA | H1: ACTIVIDAD ESPECÍFICA
D2: ACABADO DE HILOS | E2: INDUSTRIA MANUFACTURERA | F2: TEXTILES, PRENDAS DE VESTIR E INDUSTRIA DEL CUERO | G2: HILADO Y TEJIDO DE FIBRAS BLANDAS | H2: 220-ACABADO DE HILOS
D3: ACABADO DE TELAS | E3: INDUSTRIA MANUFACTURERA | F3: TEXTILES, PRENDAS DE VESTIR E INDUSTRIA DEL CUERO | G3: HILADO Y TEJIDO DE FIBRAS BLANDAS | H3: 228-ACABADO DE TELAS
D4: ACTIVIDADES DE CLUBES DEPORTIVOS PROFESIONALES | E4: SERVICIOS COMUNALES, SOCIALES Y PERSONALES | F4: SERVICIOS PROFESIONALES, DE EDUCACIÓN, MÉDICOS Y DE ESPARCIMIENTO | G4: SERVICIOS DE ESPARCIMIENTO | H4: 935-ACTIVIDADES DE CLUBES DEPORTIVOS PROFESIONALES
D5: ADMINISTRACION DE CAMINOS PUENTES Y SERVICIOS AUXILIARES | E5: TRANSPORTE, ALMACENAMIENTO Y COMUNICACIONES | F5: TRANSPORTE Y ALMACENAMIENTO | G5: TRANSPORTE | H5: 830-ADMINISTRACION DE CAMINOS PUENTES Y SERVICIOS AUXILIARES | L5: Calificación de Riesgo Primer Trimestre del 2009
D6: ADMINISTRACION DE CAMINOS PUENTES Y SERVICIOS AUXILIARES (GOBIERNO) | E6: GOBIERNO, AGRUPACIONES Y ORGANIZACIONES INTERNACIONALES | F6: GOBIERNO | G6: OTROS SERVICIOS Y ACTIVIDADES DE ADMINISTRACION PUBLICA | H6: 1035-ADMINISTRACION DE CAMINOS PUENTES Y SERVICIOS AUXILIARES (GOBIERNO)
D7: ADMINISTRACION DE CENTRALES CAMIONERAS Y SERVICIOS AUXILIARES | E7: TRANSPORTE, ALMACENAMIENTO Y COMUNICACIONES | F7: TRANSPORTE Y ALMACENAMIENTO | G7: TRANSPORTE | H7: 833-ADMINISTRACION DE CENTRALES CAMIONERAS Y SERVICIOS AUXILIARES | K7: 1 | L7: AGROPECUARIO,SILVICULTURA, CAZA Y PESCA | M7: B3
D8: ADMINISTRACION DE CENTRALES CAMIONERAS Y SERVICIOS AUXILIARES (GOBIERNO) | E8: GOBIERNO, AGRUPACIONES Y ORGANIZACIONES INTERNACIONALES | F8: GOBIERNO | G8: OTROS SERVICIOS Y ACTIVIDADES DE ADMINISTRACION PUBLICA | H8: 1038-ADMINISTRACION DE CENTRALES CAMIONERAS Y SERVICIOS AUXILIARES (GOBIERNO) | K8: 2 | L8: COMERCIO, RESTAURANTES Y HOTELES | M8: C1
D9: ADMINISTRACION DE INMUEBLES | E9: SERVICIOS FINANCIEROS, SEGUROS Y BIENES INMUEBLES | F9: BIENES INMUEBLES | G9: ALQUILER DE INMUEBLES | H9: 885-ADMINISTRACION DE INMUEBLES | K9: 3 | L9: CONSTRUCCION | M9: C1
D10: ADMINISTRACION DE PUERTOS MARITIMOS LACUSTRES Y FLUVIALES | E10: TRANSPORTE, ALMACENAMIENTO Y COMUNICACIONES | F10: TRANSPORTE Y ALMACENAMIENTO | G10: TRANSPORTE | H10: 832-ADMINISTRACION DE PUERTOS MARITIMOS LACUSTRES Y FLUVIALES | K10: 4 | L10: ELECTRICIDAD, GAS Y AGUA | M10: C1
D11: ADMINISTRACION DE PUERTOS MARITIMOS LACUSTRES Y FLUVIALES (GOBIERNO) | E11: GOBIERNO, AGRUPACIONES Y ORGANIZACIONES INTERNACIONALES | F11: GOBIERNO | G11: OTROS SERVICIOS Y ACTIVIDADES DE ADMINISTRACION PUBLICA | H11: 1037-ADMINISTRACION DE PUERTOS MARITIMOS LACUSTRES Y FLUVIALES (GOBIERNO) | K11: 5 | L11: EMPLEADOS, PROFESIONISTAS INDEPENDIENTES Y SIMILARES | M11: B3
D12: AEROPUERTO CIVIL | E12: TRANSPORTE, ALMACENAMIENTO Y COMUNICACIONES | F12: TRANSPORTE Y ALMACENAMIENTO | G12: TRANSPORTE | H12: 831-AEROPUERTO CIVIL | K12: 6 | L12: GOBIERNO, AGRUPACIONES Y ORGANIZACIONES INTERNACIONALES | M12: B3
D13: AEROPUERTO CIVIL (GOBIERNO) | E13: GOBIERNO, AGRUPACIONES Y ORGANIZACIONES INTERNACIONALES | F13: GOBIERNO | G13: OTROS SERVICIOS Y ACTIVIDADES DE ADMINISTRACION PUBLICA | H13: 1036-AEROPUERTO CIVIL (GOBIERNO) | K13: 7 | L13: INDUSTRIA MANUFACTURERA | M13: C1
D14: AGENCIA ADUANAL | E14: TRANSPORTE, ALMACENAMIENTO Y COMUNICACIONES | F14: TRANSPORTE Y ALMACENAMIENTO | G14: TRANSPORTE | H14: 836-AGENCIA ADUANAL | K14: 8 | L14: MINERÍA | M14: D
D15: AGENCIA ADUANAL (GOBIERNO) | E15: GOBIERNO, AGRUPACIONES Y ORGANIZACIONES INTERNACIONALES | F15: GOBIERNO | G15: OTROS SERVICIOS Y ACTIVIDADES DE ADMINISTRACION PUBLICA | H15: 1041-AGENCIA ADUANAL (GOBIERNO) | K15: 9 | L15: SERVICIOS COMUNALES, SOCIALES Y PERSONALES | M15: C1
D16: AGENCIA DE FERROCARRIL | E16: TRANSPORTE, ALMACENAMIENTO Y COMUNICACIONES | F16: TRANSPORTE Y ALMACENAMIENTO | G16: TRANSPORTE | H16: 838-AGENCIA DE FERROCARRIL | K16: 10 | L16: SERVICIOS FINANCIEROS, SEGUROS Y BIENES INMUEBLES | M16: C1
D17: AGENCIA DE FERROCARRIL (GOBIERNO) | E17: GOBIERNO, AGRUPACIONES Y ORGANIZACIONES INTERNACIONALES | F17: GOBIERNO | G17: OTROS SERVICIOS Y ACTIVIDADES DE ADMINISTRACION PUBLICA | H17: 1043-AGENCIA DE FERROCARRIL (GOBIERNO) | K17: 11 | L17: TRANSPORTE, ALMACENAMIENTO Y COMUNICACIONES | M17: B3
D18: AGENCIA DE INHUMACIONES | E18: SERVICIOS COMUNALES, SOCIALES Y PERSONALES | F18: OTROS SERVICIOS | G18: OTROS SERVICIOS | H18: 980-AGENCIA DE INHUMACIONES
D19: AGENCIA DE MUDANZAS | E19: TRANSPORTE, ALMACENAMIENTO Y COMUNICACIONES | F19: TRANSPORTE Y ALMACENAMIENTO | G19: TRANSPORTE | H19: 817-AGENCIA DE MUDANZAS
D20: AGENCIA DE MUDANZAS (GOBIERNO) | E20: GOBIERNO, AGRUPACIONES Y ORGANIZACIONES INTERNACIONALES | F20: GOBIERNO | G20: OTROS SERVICIOS Y ACTIVIDADES DE ADMINISTRACION PUBLICA | H20: 1022-AGENCIA DE MUDANZAS (GOBIERNO)
D21: AGENCIA DE PUBLICIDAD | E21: SERVICIOS COMUNALES, SOCIALES Y PERSONALES | F21: SERVICIOS PROFESIONALES, DE EDUCACIÓN, MÉDICOS Y DE ESPARCIMIENTO | G21: SERVICIOS PROFESIONALES | H21: 893-AGENCIA DE PUBLICIDAD
D22: AGENCIA DE TURISMO | E22: TRANSPORTE, ALMACENAMIENTO Y COMUNICACIONES | F22: TRANSPORTE Y ALMACENAMIENTO | G22: TRANSPORTE | H22: 835-AGENCIA DE TURISMO
D23: AGENCIA DE TURISMO (GOBIERNO) | E23: GOBIERNO, AGRUPACIONES Y ORGANIZACIONES INTERNACIONALES | F23: GOBIERNO | G23: OTROS SERVICIOS Y ACTIVIDADES DE ADMINISTRACION PUBLICA | H23: 1040-AGENCIA DE TURISMO (GOBIERNO)
D24: AGENCIA DE VAPORES Y BUQUES | E24: TRANSPORTE, ALMACENAMIENTO Y COMUNICACIONES | F24: TRANSPORTE Y ALMACENAMIENTO | G24: TRANSPORTE | H24: 824-AGENCIA DE VAPORES Y BUQUES
D25: AGENCIA DE VAPORES Y BUQUES (GOBIERNO) | E25: GOBIERNO, AGRUPACIONES Y ORGANIZACIONES INTERNACIONALES | F25: GOBIERNO | G25: OTROS SERVICIOS Y ACTIVIDADES DE ADMINISTRACION PUBLICA | H25: 1029-AGENCIA DE VAPORES Y BUQUES (GOBIERNO)
D26: AGENCIA NOTICIOSA | E26: SERVICIOS COMUNALES, SOCIALES Y PERSONALES | F26: SERVICIOS PROFESIONALES, DE EDUCACIÓN, MÉDICOS Y DE ESPARCIMIENTO | G26: SERVICIOS PROFESIONALES | H26: 894-AGENCIA NOTICIOSA
D27: AGENCIAS DE RIFAS Y SORTEOS (QUINIELAS Y LOTERIA) | E27: COMERCIO, RESTAURANTES Y HOTELES | F27: ARTICULOS DIVERSOS | G27: COMERCIO | H27: 789-AGENCIAS DE RIFAS Y SORTEOS (QUINIELAS Y LOTERIA)
D28: AGENTE DE BOLSA | E28: SERVICIOS FINANCIEROS, SEGUROS Y BIENES INMUEBLES | F28: SERVICIOS FINANCIEROS Y SEGUROS | G28: SERVICIOS FINANCIEROS | H28: 856-AGENTE DE BOLSA
D29: AGENTE DE BOLSA (GOBIERNO) | E29: SERVICIOS FINANCIEROS, SEGUROS Y BIENES INMUEBLES | F29: SERVICIOS FINANCIEROS Y SEGUROS | G29: SERVICIOS FINANCIEROS | H29: 874-AGENTE DE BOLSA (GOBIERNO)
... D1069: VULCANIZACION DE LLANTAS Y CAMARAS | E1069: INDUSTRIA MANUFACTURERA | F1069: SUSTANCIAS QUIMICAS, DERIVADOS DEL PETROLEO, CAUCHO Y PLASTICOS | G1069: PRODUCTOS DE HULE | H1069: 391-VULCANIZACION DE LLANTAS Y CAMARAS

Sheet Hoja10

Sheet Base
A1: =IF(#REF!="","",#REF!) -> #REF! | B1: =IF(#REF!="","",#REF!) -> #REF! | C1: =IF(#REF!="","",#REF!) -> #REF! | D1: =IF(#REF!="","",#REF!) -> #REF! | E1: =IF(#REF!="","",#REF!) -> #REF! | F1: =IF(#REF!="","",#REF!) -> #REF! | G1: =IF(#REF!="","",#REF!) -> #REF! | H1: =IF(#REF!="","",#REF!) -> #REF! | ... S1: =IF(#REF!="","",#REF!) -> #REF!
A2: =IF(#REF!="","",#REF!) -> #REF! | B2: =IF(#REF!="","",#REF!) -> #REF! | C2: =IF(#REF!="","",#REF!) -> #REF! | D2: =IF(#REF!="","",#REF!) -> #REF! | E2: =IF(#REF!="","",#REF!) -> #REF! | F2: =IF(#REF!="","",#REF!) -> #REF! | G2: =IF(#REF!="","",#REF!) -> #REF! | H2: =IF(#REF!="","",#REF!) -> #REF! | ... S2: =IF(#REF!="","",#REF!) -> #REF!
A3: =IF(#REF!="","",#REF!) -> #REF! | B3: =IF(#REF!="","",#REF!) -> #REF! | C3: =IF(#REF!="","",#REF!) -> #REF! | D3: =IF(#REF!="","",#REF!) -> #REF! | E3: =IF(#REF!="","",#REF!) -> #REF! | F3: =IF(#REF!="","",#REF!) -> #REF! | G3: =IF(#REF!="","",#REF!) -> #REF! | H3: =IF(#REF!="","",#REF!) -> #REF! | ... S3: =IF(#REF!="","",#REF!) -> #REF!
A4: =IF(#REF!="","",#REF!) -> #REF! | B4: =IF(#REF!="","",#REF!) -> #REF! | C4: =IF(#REF!="","",#REF!) -> #REF! | D4: =IF(#REF!="","",#REF!) -> #REF! | E4: =IF(#REF!="","",#REF!) -> #REF! | F4: =IF(#REF!="","",#REF!) -> #REF! | G4: =IF(#REF!="","",#REF!) -> #REF! | H4: =IF(#REF!="","",#REF!) -> #REF! | ... S4: =IF(#REF!="","",#REF!) -> #REF!
A5: =IF(#REF!="","",#REF!) -> #REF! | B5: =IF(#REF!="","",#REF!) -> #REF! | C5: =IF(#REF!="","",#REF!) -> #REF! | D5: =IF(#REF!="","",#REF!) -> #REF! | E5: =IF(#REF!="","",#REF!) -> #REF! | F5: =IF(#REF!="","",#REF!) -> #REF! | G5: =IF(#REF!="","",#REF!) -> #REF! | H5: =IF(#REF!="","",#REF!) -> #REF! | ... S5: =IF(#REF!="","",#REF!) -> #REF!
A6: =IF(#REF!="","",#REF!) -> #REF! | B6: =IF(#REF!="","",#REF!) -> #REF! | C6: =IF(#REF!="","",#REF!) -> #REF! | D6: =IF(#REF!="","",#REF!) -> #REF! | E6: =IF(#REF!="","",#REF!) -> #REF! | F6: =IF(#REF!="","",#REF!) -> #REF! | G6: =IF(#REF!="","",#REF!) -> #REF! | H6: =IF(#REF!="","",#REF!) -> #REF! | ... S6: =IF(#REF!="","",#REF!) -> #REF!
A7: =IF(#REF!="","",#REF!) -> #REF! | B7: =IF(#REF!="","",#REF!) -> #REF! | C7: =IF(#REF!="","",#REF!) -> #REF! | D7: =IF(#REF!="","",#REF!) -> #REF! | E7: =IF(#REF!="","",#REF!) -> #REF! | F7: =IF(#REF!="","",#REF!) -> #REF! | G7: =IF(#REF!="","",#REF!) -> #REF! | H7: =IF(#REF!="","",#REF!) -> #REF! | ... S7: =IF(#REF!="","",#REF!) -> #REF!
A8: =IF(#REF!="","",#REF!) -> #REF! | B8: =IF(#REF!="","",#REF!) -> #REF! | C8: =IF(#REF!="","",#REF!) -> #REF! | D8: =IF(#REF!="","",#REF!) -> #REF! | E8: =IF(#REF!="","",#REF!) -> #REF! | F8: =IF(#REF!="","",#REF!) -> #REF! | G8: =IF(#REF!="","",#REF!) -> #REF! | H8: =IF(#REF!="","",#REF!) -> #REF! | ... S8: =IF(#REF!="","",#REF!) -> #REF!
A9: =IF(#REF!="","",#REF!) -> #REF! | B9: =IF(#REF!="","",#REF!) -> #REF! | C9: =IF(#REF!="","",#REF!) -> #REF! | D9: =IF(#REF!="","",#REF!) -> #REF! | E9: =IF(#REF!="","",#REF!) -> #REF! | F9: =IF(#REF!="","",#REF!) -> #REF! | G9: =IF(#REF!="","",#REF!) -> #REF! | H9: =IF(#REF!="","",#REF!) -> #REF! | ... S9: =IF(#REF!="","",#REF!) -> #REF!
A10: =IF(#REF!="","",#REF!) -> #REF! | B10: =IF(#REF!="","",#REF!) -> #REF! | C10: =IF(#REF!="","",#REF!) -> #REF! | D10: =IF(#REF!="","",#REF!) -> #REF! | E10: =IF(#REF!="","",#REF!) -> #REF! | F10: =IF(#REF!="","",#REF!) -> #REF! | G10: =IF(#REF!="","",#REF!) -> #REF! | H10: =IF(#REF!="","",#REF!) -> #REF! | ... S10: =IF(#REF!="","",#REF!) -> #REF!
A11: =IF(#REF!="","",#REF!) -> #REF! | B11: =IF(#REF!="","",#REF!) -> #REF! | C11: =IF(#REF!="","",#REF!) -> #REF! | D11: =IF(#REF!="","",#REF!) -> #REF! | E11: =IF(#REF!="","",#REF!) -> #REF! | F11: =IF(#REF!="","",#REF!) -> #REF! | G11: =IF(#REF!="","",#REF!) -> #REF! | H11: =IF(#REF!="","",#REF!) -> #REF! | ... S11: =IF(#REF!="","",#REF!) -> #REF!
A12: =IF(#REF!="","",#REF!) -> #REF! | B12: =IF(#REF!="","",#REF!) -> #REF! | C12: =IF(#REF!="","",#REF!) -> #REF! | D12: =IF(#REF!="","",#REF!) -> #REF! | E12: =IF(#REF!="","",#REF!) -> #REF! | F12: =IF(#REF!="","",#REF!) -> #REF! | G12: =IF(#REF!="","",#REF!) -> #REF! | H12: =IF(#REF!="","",#REF!) -> #REF! | ... S12: =IF(#REF!="","",#REF!) -> #REF!
... A172: =IF(#REF!="","",#REF!) -> #REF! | B172: =IF(#REF!="","",#REF!) -> #REF! | C172: =IF(#REF!="","",#REF!) -> #REF! | D172: =IF(#REF!="","",#REF!) -> #REF! | E172: =IF(#REF!="","",#REF!) -> #REF! | F172: =IF(#REF!="","",#REF!) -> #REF! | G172: =IF(#REF!="","",#REF!) -> #REF! | H172: =IF(#REF!="","",#REF!) -> #REF! | ... S172: =IF(#REF!="","",#REF!) -> #REF!

Sheet Bal2
S3: Caja y Bancos | T3: Cuentas por Cobrar | U3: IVA por Acreditar | V3: Deudores Diversos | W3: Inventarios | X3: Reclamaciones por Garantia | Y3: Cuentas por Cobrar Filiales | Z3: Otros Activos Circulantes | AF3: Terrenos y Edificios | AG3: Maquinaria y Equipo | AH3: Muebles y Enseres | AI3: Equipo de Transporte | AJ3: Depreciacion Acumulada | AK3: Revaluacion de Activos | AL3: Mejoras al Local Arrendado | AR3: Pagos Anticipados | AS3: Cargos Diferidos | AT3: Inversiones en Valores | AU3: Credito al Salario | BC3: Proveedores | BD3: Creditos a Corto Plazo | BE3: Arrendadora a Corto Plazo | BF3: Impuestos a Pagar | BG3: Acreedores Diversos | BH3: Documentos por Pagar | BI3: Cuentas por Pagar Filiales | BJ3: Anticipos de Clientes | BK3: Porcion Circ. Deuda L.P. | BQ3: Creditos a Largo Plazo | BR3: Arrendadora a Largo Plazo | BS3: Documentos x Pagar a Largo Pla | BY3: Creditos Diferidos | BZ3: Estimacion Prima de Antiguedad | CH3: Capital Social | CI3: Reservas | CJ3: Aportaciones Futuros Aument | CK3: Actualizacion de Capital | CL3: Superavit por Reevaluacion | CM3: Utilidad Acumulada | CN3: Utilidad del Ejercicio | CO3: Otras Partidas | CP3: Patrimonio | DJ3: Ventas | DK3: Costo de Ventas | DL3: Sueldos | DM3: Ingresos Varios | DQ3: Gastos de Administracion | DR3: Gastos de Venta | DS3: Gastos Familiares | DY3: Productos Financieros (-) | DZ3: Gastos Financieros | EA3: Fluctuacion Cambiaria | EB3: REPOMO | EE3: Otros Ingresos (-) | EF3: Otras Partidas | EG3: Particip. en Result. de Subsid | EH3: Partidas Extraordinarias | EI3: Pago Creditos | EJ3: Gastos Varios | EN3: Impuestos
S4: 1 | T4: 2 | U4: 3 | V4: 4 | W4: 5 | X4: 6 | Y4: 7 | Z4: 8 | AF4: 9 | AG4: 10 | AH4: 11 | AI4: 12 | AJ4: 13 | AK4: 14 | AL4: 15 | AR4: 16 | AS4: 17 | AT4: 18 | AU4: 19 | BC4: 20 | BD4: 21 | BE4: 22 | BF4: 23 | BG4: 24 | BH4: 25 | BI4: 26 | BJ4: 27 | BK4: 28 | BL4: 29 | BQ4: 29 | BR4: 30 | BS4: 31 | BY4: 32 | BZ4: 33 | CH4: 34 | CI4: 35 | CJ4: 36 | CK4: 37 | CL4: 38 | CM4: 39 | CN4: 40 | CO4: 41 | CP4: 42 | DJ4: 43 | DK4: 44 | DL4: 45 | DM4: 46 | DQ4: 47 | DR4: 48 | DS4: 49 | DY4: 50 | DZ4: 51 | EA4: 52 | EB4: 53 | EE4: 54 | EF4: 55 | EG4: 56 | EH4: 57 | EI4: 58 | EJ4: 59 | EN4: 60
E6: =Bal!B6 -> 0 | F6: =Bal!C6 -> 0 | G6: =Bal!D6 -> 0 | H6: =Bal!E6 -> 2007 | I6: =Bal!F6 -> % | J6: =Bal!G6 -> 2008 | K6: =Bal!H6 -> % | L6: =Bal!I6 -> Jun - | ... N6: =Bal!K6 -> %
E7: =Bal!B7 -> 0 | F7: =Bal!C7 -> 0 | G7: =Bal!D7 -> 0 | H7: =Bal!E7 -> 0 | I7: =Bal!F7 -> 0 | J7: =Bal!G7 -> 0 | K7: =Bal!H7 -> 0 | L7: =Bal!I7 -> 0 | ... N7: =Bal!K7 -> 0
E8: =Bal!B8 -> BALANCE GENERAL | F8: =Bal!C8 -> 0 | G8: =Bal!D8 -> 0 | H8: =Bal!E8 -> 0 | I8: =Bal!F8 -> 0 | J8: =Bal!G8 -> 0 | K8: =Bal!H8 -> 0 | L8: =Bal!I8 -> 0 | ... N8: =Bal!K8 -> 0
E9: =Bal!B9 -> ACTIVO CIRCULANTE | F9: =Bal!C9 -> 0 | G9: =Bal!D9 -> 0 | H9: =Bal!E9 -> 0 | I9: =Bal!F9 -> 0 | J9: =Bal!G9 -> 0 | K9: =Bal!H9 -> 0 | L9: =Bal!I9 -> 0 | ... N9: =Bal!K9 -> 0
E10: =Bal!B10 -> 0 | F10: =Bal!C10 -> 0 | G10: =Bal!D10 -> 0 | H10: =Bal!E10 -> 0 | I10: =Bal!F10 -> 0 | J10: =Bal!G10 -> 0 | K10: =Bal!H10 -> 0 | L10: =Bal!I10 -> 0 | ... N10: =Bal!K10 -> 0
D11: =HLOOKUP(E11,$S$3:$EN$4,2,0) -> 1 | E11: =Bal!B11 -> Caja y Bancos | F11: =Bal!C11 -> 0 | G11: =Bal!D11 -> 0 | H11: =Bal!E11 -> 61506 | I11: =Bal!F11 -> 0 | J11: =Bal!G11 -> 0.02 | K11: =Bal!H11 -> 271489 | L11: =Bal!I11 -> 0.05 | ... N11: =Bal!K11 -> 0.03
D12: =HLOOKUP(E12,$S$3:$EN$4,2,0) -> 2 | E12: =Bal!B12 -> Cuentas por Cobrar | F12: =Bal!C12 -> 0 | G12: =Bal!D12 -> 0 | H12: =Bal!E12 -> 805016 | I12: =Bal!F12 -> 0 | J12: =Bal!G12 -> 0.21 | K12: =Bal!H12 -> 696737 | L12: =Bal!I12 -> 0.13 | ... N12: =Bal!K12 -> 0.11
D13: =HLOOKUP(E13,$S$3:$EN$4,2,0) -> 4 | E13: =Bal!B13 -> Deudores Diversos | F13: =Bal!C13 -> 0 | G13: =Bal!D13 -> 0 | H13: =Bal!E13 -> 696040 | I13: =Bal!F13 -> 0 | J13: =Bal!G13 -> 0.18 | K13: =Bal!H13 -> 2303156 | L13: =Bal!I13 -> 0.41 | ... N13: =Bal!K13 -> 0.45
D14: =HLOOKUP(E14,$S$3:$EN$4,2,0) -> 5 | E14: =Bal!B14 -> Inventarios | F14: =Bal!C14 -> 0 | G14: =Bal!D14 -> 0 | H14: =Bal!E14 -> 121292 | I14: =Bal!F14 -> 0 | J14: =Bal!G14 -> 0.03 | K14: =Bal!H14 -> 199339 | L14: =Bal!I14 -> 0.04 | ... N14: =Bal!K14 -> 0.05
B15: Caja y Bancos | C15: 1 | D15: =HLOOKUP(E15,$S$3:$EN$4,2,0) -> #N/A | E15: =Bal!B15 -> 0 | F15: =Bal!C15 -> 0 | G15: =Bal!D15 -> 0 | H15: =Bal!E15 -> 1683854 | I15: =Bal!F15 -> 0 | J15: =Bal!G15 -> 0.44 | K15: =Bal!H15 -> 3470721 | L15: =Bal!I15 -> 0.63 | ... N15: =Bal!K15 -> 0.64
B16: Cuentas por Cobrar | C16: 2 | D16: =HLOOKUP(E16,$S$3:$EN$4,2,0) -> #N/A | E16: =Bal!B16 -> ACTIVO FIJO | F16: =Bal!C16 -> 0 | G16: =Bal!D16 -> 0 | H16: =Bal!E16 -> 0 | I16: =Bal!F16 -> 0 | J16: =Bal!G16 -> 0 | K16: =Bal!H16 -> 0 | L16: =Bal!I16 -> 0 | ... N16: =Bal!K16 -> 0
B17: IVA por Acreditar | C17: 3 | D17: =HLOOKUP(E17,$S$3:$EN$4,2,0) -> #N/A | E17: =Bal!B17 -> 0 | F17: =Bal!C17 -> 0 | G17: =Bal!D17 -> 0 | H17: =Bal!E17 -> 0 | I17: =Bal!F17 -> 0 | J17: =Bal!G17 -> 0 | K17: =Bal!H17 -> 0 | L17: =Bal!I17 -> 0 | ... N17: =Bal!K17 -> 0
B18: Deudores Diversos | C18: 4 | D18: =HLOOKUP(E18,$S$3:$EN$4,2,0) -> 9 | E18: =Bal!B18 -> Terrenos y Edificios | F18: =Bal!C18 -> 0 | G18: =Bal!D18 -> 0 | H18: =Bal!E18 -> 287684 | I18: =Bal!F18 -> 0 | J18: =Bal!G18 -> 0.07 | K18: =Bal!H18 -> 287684 | L18: =Bal!I18 -> 0.05 | ... N18: =Bal!K18 -> 0.05
B19: Inventarios | C19: 5 | D19: =HLOOKUP(E19,$S$3:$EN$4,2,0) -> 10 | E19: =Bal!B19 -> Maquinaria y Equipo | F19: =Bal!C19 -> 0 | G19: =Bal!D19 -> 0 | H19: =Bal!E19 -> 1960982 | I19: =Bal!F19 -> 0 | J19: =Bal!G19 -> 0.5 | K19: =Bal!H19 -> 2362142 | L19: =Bal!I19 -> 0.42 | ... N19: =Bal!K19 -> 0.44
B20: Reclamaciones por Garantia | C20: 6 | D20: =HLOOKUP(E20,$S$3:$EN$4,2,0) -> 11 | E20: =Bal!B20 -> Muebles y Enseres | F20: =Bal!C20 -> 0 | G20: =Bal!D20 -> 0 | H20: =Bal!E20 -> 287942 | I20: =Bal!F20 -> 0 | J20: =Bal!G20 -> 0.07 | K20: =Bal!H20 -> 398840 | L20: =Bal!I20 -> 0.07 | ... N20: =Bal!K20 -> 0.08
B21: Cuentas por Cobrar Filiales | C21: 7 | D21: =HLOOKUP(E21,$S$3:$EN$4,2,0) -> 12 | E21: =Bal!B21 -> Equipo de Transporte | F21: =Bal!C21 -> 0 | G21: =Bal!D21 -> 0 | H21: =Bal!E21 -> 44065 | I21: =Bal!F21 -> 0 | J21: =Bal!G21 -> 0.01 | K21: =Bal!H21 -> 47054 | L21: =Bal!I21 -> 0.01 | ... N21: =Bal!K21 -> 0.01
B22: Otros Activos Circulantes | C22: 8 | D22: =HLOOKUP(E22,$S$3:$EN$4,2,0) -> 13 | E22: =Bal!B22 -> Depreciacion Acumulada | F22: =Bal!C22 -> 0 | G22: =Bal!D22 -> 0 | H22: =Bal!E22 -> -1014568 | I22: =Bal!F22 -> 0 | J22: =Bal!G22 -> -0.26 | K22: =Bal!H22 -> -1181927 | L22: =Bal!I22 -> -0.21 | ... N22: =Bal!K22 -> -0.23
D23: =HLOOKUP(E23,$S$3:$EN$4,2,0) -> #N/A | E23: =Bal!B23 -> 0 | F23: =Bal!C23 -> 0 | G23: =Bal!D23 -> 0 | H23: =Bal!E23 -> 1566105 | I23: =Bal!F23 -> 0 | J23: =Bal!G23 -> 0.39 | K23: =Bal!H23 -> 1913793 | L23: =Bal!I23 -> 0.34 | ... N23: =Bal!K23 -> 0.35
D24: =HLOOKUP(E24,$S$3:$EN$4,2,0) -> #N/A | E24: =Bal!B24 -> ACTIVO DIFERIDO | F24: =Bal!C24 -> 0 | G24: =Bal!D24 -> 0 | H24: =Bal!E24 -> 0 | I24: =Bal!F24 -> 0 | J24: =Bal!G24 -> 0 | K24: =Bal!H24 -> 0 | L24: =Bal!I24 -> 0 | ... N24: =Bal!K24 -> 0
D25: =HLOOKUP(E25,$S$3:$EN$4,2,0) -> #N/A | E25: =Bal!B25 -> 0 | F25: =Bal!C25 -> 0 | G25: =Bal!D25 -> 0 | H25: =Bal!E25 -> 0 | I25: =Bal!F25 -> 0 | J25: =Bal!G25 -> 0 | K25: =Bal!H25 -> 0 | L25: =Bal!I25 -> 0 | ... N25: =Bal!K25 -> 0
D26: =HLOOKUP(E26,$S$3:$EN$4,2,0) -> 16 | E26: =Bal!B26 -> Pagos Anticipados | F26: =Bal!C26 -> 0 | G26: =Bal!D26 -> 0 | H26: =Bal!E26 -> 20318 | I26: =Bal!F26 -> 0 | J26: =Bal!G26 -> 0.01 | K26: =Bal!H26 -> 41904 | L26: =Bal!I26 -> 0.01 | ... N26: =Bal!K26 -> 0
D27: =HLOOKUP(E27,$S$3:$EN$4,2,0) -> 17 | E27: =Bal!B27 -> Cargos Diferidos | F27: =Bal!C27 -> 0 | G27: =Bal!D27 -> 0 | H27: =Bal!E27 -> 630957 | I27: =Bal!F27 -> 0 | J27: =Bal!G27 -> 0.16 | K27: =Bal!H27 -> 144259 | L27: =Bal!I27 -> 0.03 | ... N27: =Bal!K27 -> 0.01
B28: Terrenos y Edificios | C28: 9 | D28: =HLOOKUP(E28,$S$3:$EN$4,2,0) -> 18 | E28: =Bal!B28 -> Inversiones en Valores | F28: =Bal!C28 -> 0 | G28: =Bal!D28 -> 0 | H28: =Bal!E28 -> 500 | I28: =Bal!F28 -> 0 | J28: =Bal!G28 -> 0 | K28: =Bal!H28 -> 500 | L28: =Bal!I28 -> 0 | ... N28: =Bal!K28 -> 0
B29: Maquinaria y Equipo | C29: 10 | D29: =HLOOKUP(E29,$S$3:$EN$4,2,0) -> #N/A | E29: =Bal!B29 -> 0 | F29: =Bal!C29 -> 0 | G29: =Bal!D29 -> 0 | H29: =Bal!E29 -> 651775 | I29: =Bal!F29 -> 0 | J29: =Bal!G29 -> 0.17 | K29: =Bal!H29 -> 186663 | L29: =Bal!I29 -> 0.04 | ... N29: =Bal!K29 -> 0.01
B30: Muebles y Enseres | C30: 11 | D30: =HLOOKUP(E30,$S$3:$EN$4,2,0) -> #N/A | E30: =Bal!B30 -> TOTAL DE ACTIVO | F30: =Bal!C30 -> 0 | G30: =Bal!D30 -> 0 | H30: =Bal!E30 -> 3901734 | I30: =Bal!F30 -> 0 | J30: =Bal!G30 -> 1 | K30: =Bal!H30 -> 5571177 | L30: =Bal!I30 -> 1 | ... N30: =Bal!K30 -> 1
B31: Equipo de Transporte | C31: 12 | D31: =HLOOKUP(E31,$S$3:$EN$4,2,0) -> #N/A | E31: =Bal!B31 -> PASIVO CIRCULANTE | F31: =Bal!C31 -> 0 | G31: =Bal!D31 -> 0 | H31: =Bal!E31 -> 0 | I31: =Bal!F31 -> 0 | J31: =Bal!G31 -> 0 | K31: =Bal!H31 -> 0 | L31: =Bal!I31 -> 0 | ... N31: =Bal!K31 -> 0
B32: Depreciacion Acumulada | C32: 13 | D32: =HLOOKUP(E32,$S$3:$EN$4,2,0) -> #N/A | E32: =Bal!B32 -> 0 | F32: =Bal!C32 -> 0 | G32: =Bal!D32 -> 0 | H32: =Bal!E32 -> 0 | I32: =Bal!F32 -> 0 | J32: =Bal!G32 -> 0 | K32: =Bal!H32 -> 0 | L32: =Bal!I32 -> 0 | ... N32: =Bal!K32 -> 0
B33: Revaluacion de Activos | C33: 14 | D33: =HLOOKUP(E33,$S$3:$EN$4,2,0) -> 20 | E33: =Bal!B33 -> Proveedores | F33: =Bal!C33 -> 0 | G33: =Bal!D33 -> 0 | H33: =Bal!E33 -> 44762 | I33: =Bal!F33 -> 0 | J33: =Bal!G33 -> 0.01 | K33: =Bal!H33 -> 30461 | L33: =Bal!I33 -> 0.01 | ... N33: =Bal!K33 -> 0
B34: Mejoras al Local Arrendado | C34: 15 | D34: =HLOOKUP(E34,$S$3:$EN$4,2,0) -> 21 | E34: =Bal!B34 -> Creditos a Corto Plazo | F34: =Bal!C34 -> 0 | G34: =Bal!D34 -> 0 | H34: =Bal!E34 -> 1035327 | I34: =Bal!F34 -> 0 | J34: =Bal!G34 -> 0.27 | K34: =Bal!H34 -> 1588080 | L34: =Bal!I34 -> 0.29 | ... N34: =Bal!K34 -> 0.18
D35: =HLOOKUP(E35,$S$3:$EN$4,2,0) -> 23 | E35: =Bal!B35 -> Impuestos a Pagar | F35: =Bal!C35 -> 0 | G35: =Bal!D35 -> 0 | H35: =Bal!E35 -> 85415 | I35: =Bal!F35 -> 0 | J35: =Bal!G35 -> 0.02 | K35: =Bal!H35 -> 116008 | L35: =Bal!I35 -> 0.02 | ... N35: =Bal!K35 -> 0.01
D36: =HLOOKUP(E36,$S$3:$EN$4,2,0) -> 24 | E36: =Bal!B36 -> Acreedores Diversos | F36: =Bal!C36 -> 0 | G36: =Bal!D36 -> 0 | H36: =Bal!E36 -> 34072 | I36: =Bal!F36 -> 0 | J36: =Bal!G36 -> 0.01 | K36: =Bal!H36 -> 720635 | L36: =Bal!I36 -> 0.13 | ... N36: =Bal!K36 -> 0.17
D37: =HLOOKUP(E37,$S$3:$EN$4,2,0) -> #N/A | E37: =Bal!B37 -> 0 | F37: =Bal!C37 -> 0 | G37: =Bal!D37 -> 0 | H37: =Bal!E37 -> 1199576 | I37: =Bal!F37 -> 0 | J37: =Bal!G37 -> 0.31 | K37: =Bal!H37 -> 2455184 | L37: =Bal!I37 -> 0.45 | ... N37: =Bal!K37 -> 0.36
D38: =HLOOKUP(E38,$S$3:$EN$4,2,0) -> #N/A | E38: =Bal!B38 -> PASIVO A LARGO PLAZO | F38: =Bal!C38 -> 0 | G38: =Bal!D38 -> 0 | H38: =Bal!E38 -> 0 | I38: =Bal!F38 -> 0 | J38: =Bal!G38 -> 0 | K38: =Bal!H38 -> 0 | L38: =Bal!I38 -> 0 | ... N38: =Bal!K38 -> 0
D39: =HLOOKUP(E39,$S$3:$EN$4,2,0) -> #N/A | E39: =Bal!B39 -> 0 | F39: =Bal!C39 -> 0 | G39: =Bal!D39 -> 0 | H39: =Bal!E39 -> 0 | I39: =Bal!F39 -> 0 | J39: =Bal!G39 -> 0 | K39: =Bal!H39 -> 0 | L39: =Bal!I39 -> 0 | ... N39: =Bal!K39 -> 0
B40: Pagos Anticipados | C40: 16 | D40: =HLOOKUP(E40,$S$3:$EN$4,2,0) -> 29 | E40: =Bal!B40 -> Creditos a Largo Plazo | F40: =Bal!C40 -> 0 | G40: =Bal!D40 -> 0 | H40: =Bal!E40 -> 777045 | I40: =Bal!F40 -> 0 | J40: =Bal!G40 -> 0.2 | K40: =Bal!H40 -> 659414 | L40: =Bal!I40 -> 0.12 | ... N40: =Bal!K40 -> 0.12
B41: Cargos Diferidos | C41: 17 | D41: =HLOOKUP(E41,$S$3:$EN$4,2,0) -> #N/A | E41: =Bal!B41 -> 0 | F41: =Bal!C41 -> 0 | G41: =Bal!D41 -> 0 | H41: =Bal!E41 -> 777045 | I41: =Bal!F41 -> 0 | J41: =Bal!G41 -> 0.2 | K41: =Bal!H41 -> 659414 | L41: =Bal!I41 -> 0.12 | ... N41: =Bal!K41 -> 0.12
B42: Inversiones en Valores | C42: 18 | D42: =HLOOKUP(E42,$S$3:$EN$4,2,0) -> #N/A | E42: =Bal!B42 -> 0 | F42: =Bal!C42 -> 0 | G42: =Bal!D42 -> 0 | H42: =Bal!E42 -> 0 | I42: =Bal!F42 -> 0 | J42: =Bal!G42 -> 0 | K42: =Bal!H42 -> 0 | L42: =Bal!I42 -> 0 | ... N42: =Bal!K42 -> 0
B43: Credito al Salario | C43: 19 | D43: =HLOOKUP(E43,$S$3:$EN$4,2,0) -> #N/A | E43: =Bal!B43 -> 0 | F43: =Bal!C43 -> 0 | G43: =Bal!D43 -> 0 | H43: =Bal!E43 -> 0 | I43: =Bal!F43 -> 0 | J43: =Bal!G43 -> 0 | K43: =Bal!H43 -> 0 | L43: =Bal!I43 -> 0 | ... N43: =Bal!K43 -> 0
D44: =HLOOKUP(E44,$S$3:$EN$4,2,0) -> #N/A | E44: =Bal!B44 -> TOTAL DE PASIVO | F44: =Bal!C44 -> 0 | G44: =Bal!D44 -> 0 | H44: =Bal!E44 -> 1976621 | I44: =Bal!F44 -> 0 | J44: =Bal!G44 -> 0.51 | K44: =Bal!H44 -> 3114598 | L44: =Bal!I44 -> 0.57 | ... N44: =Bal!K44 -> 0.48
D45: =HLOOKUP(E45,$S$3:$EN$4,2,0) -> #N/A | E45: =Bal!B45 -> CAPITAL CONTABLE | F45: =Bal!C45 -> 0 | G45: =Bal!D45 -> 0 | H45: =Bal!E45 -> 0 | I45: =Bal!F45 -> 0 | J45: =Bal!G45 -> 0 | K45: =Bal!H45 -> 0 | L45: =Bal!I45 -> 0 | ... N45: =Bal!K45 -> 0
D46: =HLOOKUP(E46,$S$3:$EN$4,2,0) -> #N/A | E46: =Bal!B46 -> 0 | F46: =Bal!C46 -> 0 | G46: =Bal!D46 -> 0 | H46: =Bal!E46 -> 0 | I46: =Bal!F46 -> 0 | J46: =Bal!G46 -> 0 | K46: =Bal!H46 -> 0 | L46: =Bal!I46 -> 0 | ... N46: =Bal!K46 -> 0
D47: =HLOOKUP(E47,$S$3:$EN$4,2,0) -> 34 | E47: =Bal!B47 -> Capital Social | F47: =Bal!C47 -> 0 | G47: =Bal!D47 -> 0 | H47: =Bal!E47 -> 800000 | I47: =Bal!F47 -> 0 | J47: =Bal!G47 -> 0.21 | K47: =Bal!H47 -> 800000 | L47: =Bal!I47 -> 0.14 | ... N47: =Bal!K47 -> 0.15
D48: =HLOOKUP(E48,$S$3:$EN$4,2,0) -> 35 | E48: =Bal!B48 -> Reservas | F48: =Bal!C48 -> 0 | G48: =Bal!D48 -> 0 | H48: =Bal!E48 -> 33328 | I48: =Bal!F48 -> 0 | J48: =Bal!G48 -> 0.01 | K48: =Bal!H48 -> 54296 | L48: =Bal!I48 -> 0.01 | ... N48: =Bal!K48 -> 0.01
D49: =HLOOKUP(E49,$S$3:$EN$4,2,0) -> 39 | E49: =Bal!B49 -> Utilidad Acumulada | F49: =Bal!C49 -> 0 | G49: =Bal!D49 -> 0 | H49: =Bal!E49 -> 618232 | I49: =Bal!F49 -> 0 | J49: =Bal!G49 -> 0.16 | K49: =Bal!H49 -> 1016623 | L49: =Bal!I49 -> 0.18 | ... N49: =Bal!K49 -> 0.28
D50: =HLOOKUP(E50,$S$3:$EN$4,2,0) -> 38 | E50: =Bal!B50 -> Superavit por Reevaluacion | F50: =Bal!C50 -> 0 | G50: =Bal!D50 -> 0 | H50: =Bal!E50 -> 54194 | I50: =Bal!F50 -> 0 | J50: =Bal!G50 -> 0.01 | K50: =Bal!H50 -> 54194 | L50: =Bal!I50 -> 0.01 | ... N50: =Bal!K50 -> 0.01
B51: Proveedores | C51: 20 | D51: =HLOOKUP(E51,$S$3:$EN$4,2,0) -> 40 | E51: =Bal!B51 -> Utilidad del Ejercicio | F51: =Bal!C51 -> 0 | G51: =Bal!D51 -> 0 | H51: =Bal!E51 -> 419359 | I51: =Bal!F51 -> 0 | J51: =Bal!G51 -> 0.11 | K51: =Bal!H51 -> 531466 | L51: =Bal!I51 -> 0.1 | ... N51: =Bal!K51 -> 0.07
B52: Creditos a Corto Plazo | C52: 21 | D52: =HLOOKUP(E52,$S$3:$EN$4,2,0) -> #N/A | E52: =Bal!B52 -> 0 | F52: =Bal!C52 -> 0 | G52: =Bal!D52 -> 0 | H52: =Bal!E52 -> 1925113 | I52: =Bal!F52 -> 0 | J52: =Bal!G52 -> 0.5 | K52: =Bal!H52 -> 2456579 | L52: =Bal!I52 -> 0.44 | ... N52: =Bal!K52 -> 0.52
B53: Arrendadora a Corto Plazo | C53: 22 | D53: =HLOOKUP(E53,$S$3:$EN$4,2,0) -> #N/A | E53: =Bal!B53 -> TOTAL DE CAPITAL CONTABLE | F53: =Bal!C53 -> 0 | G53: =Bal!D53 -> 0 | H53: =Bal!E53 -> 1925113 | I53: =Bal!F53 -> 0 | J53: =Bal!G53 -> 0.5 | K53: =Bal!H53 -> 2456579 | L53: =Bal!I53 -> 0.44 | ... N53: =Bal!K53 -> 0.52
B54: Impuestos a Pagar | C54: 23 | D54: =HLOOKUP(E54,$S$3:$EN$4,2,0) -> #N/A | E54: =Bal!B54 -> TOTAL DE PASIVO + CAPITAL | F54: =Bal!C54 -> 0 | G54: =Bal!D54 -> 0 | H54: =Bal!E54 -> 3901734 | I54: =Bal!F54 -> 0 | J54: =Bal!G54 -> 1 | K54: =Bal!H54 -> 5571177 | L54: =Bal!I54 -> 1 | ... N54: =Bal!K54 -> 1
B55: Acreedores Diversos | C55: 24 | D55: =HLOOKUP(E55,$S$3:$EN$4,2,0) -> #N/A | E55: =Bal!B55 -> TOTAL DE ACTIVO | F55: =Bal!C55 -> 0 | G55: =Bal!D55 -> 0 | H55: =Bal!E55 -> 3901734 | I55: =Bal!F55 -> 0 | J55: =Bal!G55 -> 1 | K55: =Bal!H55 -> 5571177 | L55: =Bal!I55 -> 1 | ... N55: =Bal!K55 -> 1
B56: Documentos por Pagar | C56: 25 | D56: =HLOOKUP(E56,$S$3:$EN$4,2,0) -> #N/A | E56: =Bal!B56 -> ESTADO DE RESULTADOS | F56: =Bal!C56 -> 0 | G56: =Bal!D56 -> 0 | H56: =Bal!E56 -> 0 | I56: =Bal!F56 -> 0 | J56: =Bal!G56 -> 0 | K56: =Bal!H56 -> 0 | L56: =Bal!I56 -> 0 | ... N56: =Bal!K56 -> 0
B57: Cuentas por Pagar Filiales | C57: 26 | D57: =HLOOKUP(E57,$S$3:$EN$4,2,0) -> #N/A | E57: =Bal!B57 -> UTILIDAD BRUTA | F57: =Bal!C57 -> 0 | G57: =Bal!D57 -> 0 | H57: =Bal!E57 -> 0 | I57: =Bal!F57 -> 0 | J57: =Bal!G57 -> 0 | K57: =Bal!H57 -> 0 | L57: =Bal!I57 -> 0 | ... N57: =Bal!K57 -> 0
B58: Anticipos de Clientes | C58: 27 | D58: =HLOOKUP(E58,$S$3:$EN$4,2,0) -> #N/A | E58: =Bal!B58 -> 0 | F58: =Bal!C58 -> 0 | G58: =Bal!D58 -> 0 | H58: =Bal!E58 -> 0 | I58: =Bal!F58 -> 0 | J58: =Bal!G58 -> 0 | K58: =Bal!H58 -> 0 | L58: =Bal!I58 -> 0 | ... N58: =Bal!K58 -> 0
B59: Porcion Circ. Deuda L.P. | C59: 28 | D59: =HLOOKUP(E59,$S$3:$EN$4,2,0) -> 43 | E59: =Bal!B59 -> Ventas | F59: =Bal!C59 -> 0 | G59: =Bal!D59 -> 0 | H59: =Bal!E59 -> 2178748 | I59: =Bal!F59 -> 0 | J59: =Bal!G59 -> 1 | K59: =Bal!H59 -> 2406741 | L59: =Bal!I59 -> 1 | ... N59: =Bal!K59 -> 1
C60: 29 | D60: =HLOOKUP(E60,$S$3:$EN$4,2,0) -> 44 | E60: =Bal!B60 -> Costo de Ventas | F60: =Bal!C60 -> 0 | G60: =Bal!D60 -> 0 | H60: =Bal!E60 -> 1239161 | I60: =Bal!F60 -> 0 | J60: =Bal!G60 -> 0.57 | K60: =Bal!H60 -> 1102291 | L60: =Bal!I60 -> 0.46 | ... N60: =Bal!K60 -> 0.47
D61: =HLOOKUP(E61,$S$3:$EN$4,2,0) -> #N/A | E61: =Bal!B61 -> 0 | F61: =Bal!C61 -> 0 | G61: =Bal!D61 -> 0 | H61: =Bal!E61 -> 939587 | I61: =Bal!F61 -> 0 | J61: =Bal!G61 -> 0.43 | K61: =Bal!H61 -> 1304450 | L61: =Bal!I61 -> 0.54 | ... N61: =Bal!K61 -> 0.53
D62: =HLOOKUP(E62,$S$3:$EN$4,2,0) -> #N/A | E62: =Bal!B62 -> UTILIDAD DE OPERACION | F62: =Bal!C62 -> 0 | G62: =Bal!D62 -> 0 | H62: =Bal!E62 -> 0 | I62: =Bal!F62 -> 0 | J62: =Bal!G62 -> 0 | K62: =Bal!H62 -> 0 | L62: =Bal!I62 -> 0 | ... N62: =Bal!K62 -> 0
D63: =HLOOKUP(E63,$S$3:$EN$4,2,0) -> #N/A | E63: =Bal!B63 -> 0 | F63: =Bal!C63 -> 0 | G63: =Bal!D63 -> 0 | H63: =Bal!E63 -> 0 | I63: =Bal!F63 -> 0 | J63: =Bal!G63 -> 0 | K63: =Bal!H63 -> 0 | L63: =Bal!I63 -> 0 | ... N63: =Bal!K63 -> 0
D64: =HLOOKUP(E64,$S$3:$EN$4,2,0) -> 48 | E64: =Bal!B64 -> Gastos de Venta | F64: =Bal!C64 -> 0 | G64: =Bal!D64 -> 0 | H64: =Bal!E64 -> 191143 | I64: =Bal!F64 -> 0 | J64: =Bal!G64 -> 0.09 | K64: =Bal!H64 -> 217833 | L64: =Bal!I64 -> 0.09 | ... N64: =Bal!K64 -> 0.1
B65: Creditos a Largo Plazo | C65: 29 | D65: =HLOOKUP(E65,$S$3:$EN$4,2,0) -> #N/A | E65: =Bal!B65 -> 0 | F65: =Bal!C65 -> 0 | G65: =Bal!D65 -> 0 | H65: =Bal!E65 -> 748444 | I65: =Bal!F65 -> 0 | J65: =Bal!G65 -> 0.34 | K65: =Bal!H65 -> 1086617 | L65: =Bal!I65 -> 0.45 | ... N65: =Bal!K65 -> 0.43
B66: Arrendadora a Largo Plazo | C66: 30 | D66: =HLOOKUP(E66,$S$3:$EN$4,2,0) -> #N/A | E66: =Bal!B66 -> UTILIDAD NETA | F66: =Bal!C66 -> 0 | G66: =Bal!D66 -> 0 | H66: =Bal!E66 -> 0 | I66: =Bal!F66 -> 0 | J66: =Bal!G66 -> 0 | K66: =Bal!H66 -> 0 | L66: =Bal!I66 -> 0 | ... N66: =Bal!K66 -> 0
B67: Documentos x Pagar a Largo Pla | C67: 31 | D67: =HLOOKUP(E67,$S$3:$EN$4,2,0) -> #N/A | E67: =Bal!B67 -> 0 | F67: =Bal!C67 -> 0 | G67: =Bal!D67 -> 0 | H67: =Bal!E67 -> 0 | I67: =Bal!F67 -> 0 | J67: =Bal!G67 -> 0 | K67: =Bal!H67 -> 0 | L67: =Bal!I67 -> 0 | ... N67: =Bal!K67 -> 0
D68: =HLOOKUP(E68,$S$3:$EN$4,2,0) -> 51 | E68: =Bal!B68 -> Gastos Financieros | F68: =Bal!C68 -> 0 | G68: =Bal!D68 -> 0 | H68: =Bal!E68 -> 73064 | I68: =Bal!F68 -> 0 | J68: =Bal!G68 -> 0.03 | K68: =Bal!H68 -> 335152 | L68: =Bal!I68 -> 0.14 | ... N68: =Bal!K68 -> 0.05
D69: =HLOOKUP(E69,$S$3:$EN$4,2,0) -> 54 | E69: =Bal!B69 -> Otros Ingresos (-) | F69: =Bal!C69 -> 0 | G69: =Bal!D69 -> 0 | H69: =Bal!E69 -> -1005 | I69: =Bal!F69 -> 0 | J69: =Bal!G69 -> 0 | K69: =Bal!H69 -> -105738 | L69: =Bal!I69 -> -0.04 | ... N69: =Bal!K69 -> -0.05
D70: =HLOOKUP(E70,$S$3:$EN$4,2,0) -> 60 | E70: =Bal!B70 -> Impuestos | F70: =Bal!C70 -> 0 | G70: =Bal!D70 -> 0 | H70: =Bal!E70 -> 257026 | I70: =Bal!F70 -> 0 | J70: =Bal!G70 -> 0.12 | K70: =Bal!H70 -> 325737 | L70: =Bal!I70 -> 0.14 | ... N70: =Bal!K70 -> 0.12
D71: =HLOOKUP(E71,$S$3:$EN$4,2,0) -> #N/A | E71: =Bal!B71 -> 0 | F71: =Bal!C71 -> 0 | G71: =Bal!D71 -> 0 | H71: =Bal!E71 -> 419359 | I71: =Bal!F71 -> 0 | J71: =Bal!G71 -> 0.19 | K71: =Bal!H71 -> 531466 | L71: =Bal!I71 -> 0.21 | ... N71: =Bal!K71 -> 0.31
D72: =HLOOKUP(E72,$S$3:$EN$4,2,0) -> #N/A | E72: =Bal!B72 -> CONCILIACION | F72: =Bal!C72 -> 0 | G72: =Bal!D72 -> 0 | H72: =Bal!E72 -> 0 | I72: =Bal!F72 -> 0 | J72: =Bal!G72 -> 0 | K72: =Bal!H72 -> 0 | L72: =Bal!I72 -> 0 | ... N72: =Bal!K72 -> 0
B73: Creditos Diferidos | C73: 32 | D73: =HLOOKUP(E73,$S$3:$EN$4,2,0) -> #N/A | E73: =Bal!B73 -> 0 | F73: =Bal!C73 -> 0 | G73: =Bal!D73 -> 0 | H73: =Bal!E73 -> 0 | I73: =Bal!F73 -> 0 | J73: =Bal!G73 -> 0 | K73: =Bal!H73 -> 0 | L73: =Bal!I73 -> 0 | ... N73: =Bal!K73 -> 0
B74: Estimacion Prima de Antiguedad | C74: 33 | D74: =HLOOKUP(E74,$S$3:$EN$4,2,0) -> #N/A | E74: =Bal!B74 -> Inv. o Vta. Activos Fijos | F74: =Bal!C74 -> 0 | G74: =Bal!D74 -> 0 | H74: =Bal!E74 -> 0 | I74: =Bal!F74 -> 0 | J74: =Bal!G74 -> 0 | K74: =Bal!H74 -> 515047 | L74: =Bal!I74 -> 0 | ... N74: =Bal!K74 -> 0
D75: =HLOOKUP(E75,$S$3:$EN$4,2,0) -> #N/A | E75: =Bal!B75 -> Depreciacion del Ejercicio | F75: =Bal!C75 -> 0 | G75: =Bal!D75 -> 0 | H75: =Bal!E75 -> 0 | I75: =Bal!F75 -> 0 | J75: =Bal!G75 -> 0 | K75: =Bal!H75 -> 167359 | L75: =Bal!I75 -> 0 | ... N75: =Bal!K75 -> 0
D76: =HLOOKUP(E76,$S$3:$EN$4,2,0) -> #N/A | E76: =Bal!B76 -> 0 | F76: =Bal!C76 -> 0 | G76: =Bal!D76 -> 0 | H76: =Bal!E76 -> 0 | I76: =Bal!F76 -> 0 | J76: =Bal!G76 -> 0 | K76: =Bal!H76 -> 682406 | L76: =Bal!I76 -> 0 | ... N76: =Bal!K76 -> 0
D77: =HLOOKUP(E77,$S$3:$EN$4,2,0) -> #N/A | E77: =Bal!B77 -> 0 | F77: =Bal!C77 -> 0 | G77: =Bal!D77 -> 0 | H77: =Bal!E77 -> 0 | I77: =Bal!F77 -> 0 | J77: =Bal!G77 -> 0 | K77: =Bal!H77 -> 0 | L77: =Bal!I77 -> 0 | ... N77: =Bal!K77 -> 0
D78: =HLOOKUP(E78,$S$3:$EN$4,2,0) -> #N/A | E78: =Bal!B78 -> CIFRA DE UTILIDADES EN EL BALANCE | F78: =Bal!C78 -> 0 | G78: =Bal!D78 -> 0 | H78: =Bal!E78 -> 0 | I78: =Bal!F78 -> 0 | J78: =Bal!G78 -> 0 | K78: =Bal!H78 -> 0 | L78: =Bal!I78 -> 0 | ... N78: =Bal!K78 -> 0
D79: =HLOOKUP(E79,$S$3:$EN$4,2,0) -> #N/A | E79: =Bal!B79 -> NOTA: Las cifras entre paréntesis se suman al Estado de Resultados. | F79: =Bal!C79 -> 0 | G79: =Bal!D79 -> 0 | H79: =Bal!E79 -> 0 | I79: =Bal!F79 -> 0 | J79: =Bal!G79 -> 0 | K79: =Bal!H79 -> 0 | L79: =Bal!I79 -> 0 | ... N79: =Bal!K79 -> 0
D80: =HLOOKUP(E80,$S$3:$EN$4,2,0) -> #N/A | E80: =Bal!B80 -> 0 | F80: =Bal!C80 -> 0 | G80: =Bal!D80 -> 0 | H80: =Bal!E80 -> 0 | I80: =Bal!F80 -> 0 | J80: =Bal!G80 -> 0 | K80: =Bal!H80 -> 0 | L80: =Bal!I80 -> 0 | ... N80: =Bal!K80 -> 4294967295 of 1
D81: =HLOOKUP(E81,$S$3:$EN$4,2,0) -> #N/A | E81: =Bal!B81 -> 0 | F81: =Bal!C81 -> 0 | G81: =Bal!D81 -> 0 | H81: =Bal!E81 -> 0 | I81: =Bal!F81 -> 0 | J81: =Bal!G81 -> 0 | K81: =Bal!H81 -> 0 | L81: =Bal!I81 -> 0 | ... N81: =Bal!K81 -> 0
B82: Capital Social | C82: 34 | D82: =HLOOKUP(E82,$S$3:$EN$4,2,0) -> #N/A | E82: =Bal!B82 -> 0 | F82: =Bal!C82 -> 0 | G82: =Bal!D82 -> 0 | H82: 0 | I82: =Bal!F82 -> 0 | J82: =Bal!G82 -> 0 | K82: =Bal!H82 -> 0 | L82: =Bal!I82 -> 0 | M82: =Bal!J82 -> 0 | N82: =Bal!K82 -> 0
B83: Reservas | C83: 35 | D83: =HLOOKUP(E83,$S$3:$EN$4,2,0) -> #N/A | E83: =Bal!B83 -> 0 | F83: =Bal!C83 -> 0 | G83: =Bal!D83 -> 0 | H83: =Bal!E83 -> 0 | I83: =Bal!F83 -> 0 | J83: =Bal!G83 -> 0 | K83: =Bal!H83 -> 0 | L83: =Bal!I83 -> 0 | ... N83: =Bal!K83 -> 0
B84: Aportaciones Futuros Aument | C84: 36 | D84: =HLOOKUP(E84,$S$3:$EN$4,2,0) -> #N/A | E84: =Bal!B84 -> 0 | F84: =Bal!C84 -> 0 | G84: =Bal!D84 -> 0 | H84: =Bal!E84 -> 0 | I84: =Bal!F84 -> 0 | J84: =Bal!G84 -> 0 | K84: =Bal!H84 -> 0 | L84: =Bal!I84 -> 0 | ... N84: =Bal!K84 -> 0
B85: Actualizacion de Capital | C85: 37 | D85: =HLOOKUP(E85,$S$3:$EN$4,2,0) -> #N/A | E85: =Bal!B85 -> 0 | F85: =Bal!C85 -> 0 | G85: =Bal!D85 -> 0 | H85: =Bal!E85 -> 0 | I85: =Bal!F85 -> 0 | J85: =Bal!G85 -> 0 | K85: =Bal!H85 -> 0 | L85: =Bal!I85 -> 0 | ... N85: =Bal!K85 -> 0
B86: Superavit por Reevaluacion | C86: 38 | D86: =HLOOKUP(E86,$S$3:$EN$4,2,0) -> #N/A | E86: =Bal!B86 -> 0 | F86: =Bal!C86 -> 0 | G86: =Bal!D86 -> 0 | H86: =Bal!E86 -> 0 | I86: =Bal!F86 -> 0 | J86: =Bal!G86 -> 0 | K86: =Bal!H86 -> 0 | L86: =Bal!I86 -> 0 | ... N86: =Bal!K86 -> 0
B87: Utilidad Acumulada | C87: 39 | D87: =HLOOKUP(E87,$S$3:$EN$4,2,0) -> #N/A | E87: =Bal!B87 -> 0 | F87: =Bal!C87 -> 0 | G87: =Bal!D87 -> 0 | H87: =Bal!E87 -> 0 | I87: =Bal!F87 -> 0 | J87: =Bal!G87 -> 0 | K87: =Bal!H87 -> 0 | L87: =Bal!I87 -> 0 | ... N87: =Bal!K87 -> 0
B88: Utilidad del Ejercicio | C88: 40 | D88: =HLOOKUP(E88,$S$3:$EN$4,2,0) -> #N/A | E88: =Bal!B88 -> 0 | F88: =Bal!C88 -> 0 | G88: =Bal!D88 -> 0 | H88: =Bal!E88 -> 0 | I88: =Bal!F88 -> 0 | J88: =Bal!G88 -> 0 | K88: =Bal!H88 -> 0 | L88: =Bal!I88 -> 0 | ... N88: =Bal!K88 -> 0
B89: Otras Partidas | C89: 41 | D89: =HLOOKUP(E89,$S$3:$EN$4,2,0) -> #N/A | E89: =Bal!B89 -> 0 | F89: =Bal!C89 -> 0 | G89: =Bal!D89 -> 0 | H89: =Bal!E89 -> 0 | I89: =Bal!F89 -> 0 | J89: =Bal!G89 -> 0 | K89: =Bal!H89 -> 0 | L89: =Bal!I89 -> 0 | ... N89: =Bal!K89 -> 0
B90: Patrimonio | C90: 42 | D90: =HLOOKUP(E90,$S$3:$EN$4,2,0) -> #N/A | E90: =Bal!B90 -> 0 | F90: =Bal!C90 -> 0 | G90: =Bal!D90 -> 0 | H90: =Bal!E90 -> 0 | I90: =Bal!F90 -> 0 | J90: =Bal!G90 -> 0 | K90: =Bal!H90 -> 0 | L90: =Bal!I90 -> 0 | ... N90: =Bal!K90 -> 0
D91: =HLOOKUP(E91,$S$3:$EN$4,2,0) -> #N/A | E91: =Bal!B91 -> 0 | F91: =Bal!C91 -> 0 | G91: =Bal!D91 -> 0 | H91: =Bal!E91 -> 0 | I91: =Bal!F91 -> 0 | J91: =Bal!G91 -> 0 | K91: =Bal!H91 -> 0 | L91: =Bal!I91 -> 0 | ... N91: =Bal!K91 -> 0
D92: =HLOOKUP(E92,$S$3:$EN$4,2,0) -> #N/A | E92: =Bal!B92 -> 0 | F92: =Bal!C92 -> 0 | G92: =Bal!D92 -> 0 | H92: =Bal!E92 -> 0 | I92: =Bal!F92 -> 0 | J92: =Bal!G92 -> 0 | K92: =Bal!H92 -> 0 | L92: =Bal!I92 -> 0 | ... N92: =Bal!K92 -> 0
D93: =HLOOKUP(E93,$S$3:$EN$4,2,0) -> #N/A | E93: =Bal!B93 -> 0 | F93: =Bal!C93 -> 0 | G93: =Bal!D93 -> 0 | H93: =Bal!E93 -> 0 | I93: =Bal!F93 -> 0 | J93: =Bal!G93 -> 0 | K93: =Bal!H93 -> 0 | L93: =Bal!I93 -> 0 | ... N93: =Bal!K93 -> 0
D94: =HLOOKUP(E94,$S$3:$EN$4,2,0) -> #N/A | E94: =Bal!B94 -> 0 | F94: =Bal!C94 -> 0 | G94: =Bal!D94 -> 0 | H94: =Bal!E94 -> 0 | I94: =Bal!F94 -> 0 | J94: =Bal!G94 -> 0 | K94: =Bal!H94 -> 0 | L94: =Bal!I94 -> 0 | ... N94: =Bal!K94 -> 0
D95: =HLOOKUP(E95,$S$3:$EN$4,2,0) -> #N/A | E95: =Bal!B95 -> 0 | F95: =Bal!C95 -> 0 | G95: =Bal!D95 -> 0 | H95: =Bal!E95 -> 0 | I95: =Bal!F95 -> 0 | J95: =Bal!G95 -> 0 | K95: =Bal!H95 -> 0 | L95: =Bal!I95 -> 0 | ... N95: =Bal!K95 -> 0
D96: =HLOOKUP(E96,$S$3:$EN$4,2,0) -> #N/A | E96: =Bal!B96 -> 0 | F96: =Bal!C96 -> 0 | G96: =Bal!D96 -> 0 | H96: =Bal!E96 -> 0 | I96: =Bal!F96 -> 0 | J96: =Bal!G96 -> 0 | K96: =Bal!H96 -> 0 | L96: =Bal!I96 -> 0 | ... N96: =Bal!K96 -> 0
D97: =HLOOKUP(E97,$S$3:$EN$4,2,0) -> #N/A | E97: =Bal!B97 -> 0 | F97: =Bal!C97 -> 0 | G97: =Bal!D97 -> 0 | H97: =Bal!E97 -> 0 | I97: =Bal!F97 -> 0 | J97: =Bal!G97 -> 0 | K97: =Bal!H97 -> 0 | L97: =Bal!I97 -> 0 | ... N97: =Bal!K97 -> 0
D98: =HLOOKUP(E98,$S$3:$EN$4,2,0) -> #N/A | E98: =Bal!B98 -> 0 | F98: =Bal!C98 -> 0 | G98: =Bal!D98 -> 0 | H98: =Bal!E98 -> 0 | I98: =Bal!F98 -> 0 | J98: =Bal!G98 -> 0 | K98: =Bal!H98 -> 0 | L98: =Bal!I98 -> 0 | ... N98: =Bal!K98 -> 0
D99: =HLOOKUP(E99,$S$3:$EN$4,2,0) -> #N/A | E99: =Bal!B99 -> 0 | F99: =Bal!C99 -> 0 | G99: =Bal!D99 -> 0 | H99: =Bal!E99 -> 0 | I99: =Bal!F99 -> 0 | J99: =Bal!G99 -> 0 | K99: =Bal!H99 -> 0 | L99: =Bal!I99 -> 0 | ... N99: =Bal!K99 -> 0
D100: =HLOOKUP(E100,$S$3:$EN$4,2,0) -> #N/A | E100: =Bal!B100 -> 0 | F100: =Bal!C100 -> 0 | G100: =Bal!D100 -> 0 | H100: =Bal!E100 -> 0 | I100: =Bal!F100 -> 0 | J100: =Bal!G100 -> 0 | K100: =Bal!H100 -> 0 | L100: =Bal!I100 -> 0 | ... N100: =Bal!K100 -> 0
D101: =HLOOKUP(E101,$S$3:$EN$4,2,0) -> #N/A | E101: =Bal!B101 -> 0 | F101: =Bal!C101 -> 0 | G101: =Bal!D101 -> 0 | H101: =Bal!E101 -> 0 | I101: =Bal!F101 -> 0 | J101: =Bal!G101 -> 0 | K101: =Bal!H101 -> 0 | L101: =Bal!I101 -> 0 | ... N101: =Bal!K101 -> 0
D102: =HLOOKUP(E102,$S$3:$EN$4,2,0) -> #N/A | E102: =Bal!B102 -> 0 | F102: =Bal!C102 -> 0 | G102: =Bal!D102 -> 0 | H102: =Bal!E102 -> 0 | I102: =Bal!F102 -> 0 | J102: =Bal!G102 -> 0 | K102: =Bal!H102 -> 0 | L102: =Bal!I102 -> 0 | ... N102: =Bal!K102 -> 0
... D109: =HLOOKUP(E109,$S$3:$EN$4,2,0) -> #N/A | E109: =Bal!B109 -> 0 | F109: =Bal!C109 -> 0 | G109: =Bal!D109 -> 0 | H109: =Bal!E109 -> 0 | I109: =Bal!F109 -> 0 | J109: =Bal!G109 -> 0 | K109: =Bal!H109 -> 0 | L109: =Bal!I109 -> 0 | ... N109: =Bal!K109 -> 0
...

Sheet PROY CLIENTE
C5: =#REF! -> #REF!
C6: Proyección Cliente
E8: Real | F8: Estimado | G8: Proyección
E9: 2008 | F9: 2009 | G9: 2010 | H9: 2011 | I9: 2012
C11: Ingresos | E11: =#REF! -> #REF! | F11: 68184 | G11: 155186 | H11: 162946 | I11: 171093
C12: Costo de Venta | E12: =#REF!+#REF! -> #REF! | F12: 49774 | G12: 113286 | H12: 118950 | I12: 124897
C14: Utilidad Bruta | E14: =E11-E12 -> #REF! | F14: =F11-F12 -> 18410 | G14: =G11-G12 -> 41900 | H14: =H11-H12 -> 43996 | I14: =I11-I12 -> 46196
E15: =E14/E11 -> #REF! | F15: =F14/F11 -> 0.27000469 | G15: =G14/G11 -> 0.26999858 | H15: =H14/H11 -> 0.27000356 | I15: =I14/I11 -> 0.2700052
C17: Gastos de Admon y Vta | E17: =#REF! -> #REF! | F17: 15682 | G17: 35693 | H17: 37478 | I17: 39352
C19: Utilidad operativa | E19: =E14-E17 -> #REF! | F19: =F14-F17 -> 2728 | G19: =G14-G17 -> 6207 | H19: =H14-H17 -> 6518 | I19: =I14-I17 -> 6844
E20: =E19/E11 -> #REF! | F20: =F19/F11 -> 0.040009386 | G20: =G19/G11 -> 0.039997165 | H20: =H19/H11 -> 0.040000982 | I20: =I19/I11 -> 0.040001637
C22: Gastos Financieros | E22: =#REF! -> #REF! | F22: 651 | G22: 1617 | H22: 1107 | I22: 759
C24: Otros | E24: =#REF! -> #REF! | F24: 0 | G24: 0 | H24: 0 | I24: 0
C26: Impuestos | E26: =#REF! -> #REF! | F26: 312 | G26: 688 | H26: 812 | I26: 913
C28: Utilidad Neta | E28: =E19+E24-E22-E26 -> #REF! | F28: =F19+F24-F22-F26 -> 1765 | G28: =G19+G24-G22-G26 -> 3902 | H28: =H19+H24-H22-H26 -> 4599 | I28: =I19+I24-I22-I26 -> 5172
E29: =E28/E11 -> #REF! | F29: =F28/F11 -> 0.025885838 | G29: =G28/G11 -> 0.025144021 | H29: =H28/H11 -> 0.028224074 | I29: =I28/I11 -> 0.030229174
C33: Premisas de elaboración
C35: 1.- Ingresos para 2009 se consideran los mismos ingresos obtenidos para el primer semestre del año
C36: 2.- En 2010 se considera un aumento de un 13.8% derivado de nuestro ingreso a nivel nacional en cadena de autoservicios Costco y para los años subsecuentes se contemplo un incremento del 5%
C37: 3.- El costo se mantuvo en el mismo nivel (73% sobre ventas)
C38: 4.- Gastos de Distribución se mantuvieron en el mismo nivel (23% sobre ventas)
C39: 5.- Los Gastos Financieros fueron calculados de acuerdo a tablas de amortización individualmente por tipo de crédito.

Sheet PROYECCIONES
C5: =#REF! -> #REF!
C6: Proyección del Cliente
F8: Real | G8: Estimado | H8: Proyección
F9: 2008 | G9: 2009 | H9: 2010 | I9: 2011 | J9: 2012 | K9: 2013 | L9: 2014
C11: Ingresos | F11: =#REF! -> #REF! | G11: =138845+161898+10337 -> 311080 | H11: =138737+474028+11493 -> 624258 | I11: =141511+565143+11953 -> 718607 | J11: =144342+565143+12431 -> 721916 | K11: =147228+565143+12928 -> 725299 | L11: =150173+565143+13445 -> 728761
C12: Costo de Venta | F12: =#REF!+#REF! -> #REF! | G12: =91476+133009+8123 -> 232608 | H12: =91258+288879+9171 -> 389308 | I12: =93084+343687+9538 -> 446309 | J12: =94945+343687+9920 -> 448552 | K12: =96844+343687+10317 -> 450848 | L12: =98781+343687+10729 -> 453197
F13: =F12/F11 -> #REF! | G13: =G12/G11 -> 0.74774335 | H13: =H12/H11 -> 0.62363318 | I13: =I12/I11 -> 0.62107522 | J13: =J12/J11 -> 0.62133545 | K13: =K12/K11 -> 0.62160295 | L13: =L12/L11 -> 0.62187329
C15: Utilidad Bruta | F15: =F11-F12 -> #REF! | G15: =G11-G12 -> 78472 | H15: =H11-H12 -> 234950 | I15: =I11-I12 -> 272298 | J15: =J11-J12 -> 273364 | K15: =K11-K12 -> 274451 | L15: =L11-L12 -> 275564
F16: =F15/F11 -> #REF! | G16: =G15/G11 -> 0.25225665 | H16: =H15/H11 -> 0.37636682 | I16: =I15/I11 -> 0.37892478 | J16: =J15/J11 -> 0.37866455 | K16: =K15/K11 -> 0.37839705 | L16: =L15/L11 -> 0.37812671
C18: Gastos de Admon y Vta | F18: =#REF! -> #REF! | G18: =11636+8063+6801+3397 -> 29897 | H18: =12287+9543+3397 -> 25227 | I18: =12778+9925+3533 -> 26236 | J18: =13289+10322+3674 -> 27285 | K18: =13821+10735+3820 -> 28376 | L18: =14374+11165 -> 25539
C20: Utilidad operativa | F20: =F15-F18 -> #REF! | G20: =G15-G18 -> 48575 | H20: =H15-H18 -> 209723 | I20: =I15-I18 -> 246062 | J20: =J15-J18 -> 246079 | K20: =K15-K18 -> 246075 | L20: =L15-L18 -> 250025
F21: =F20/F11 -> #REF! | G21: =G20/G11 -> 0.15614954 | H21: =H20/H11 -> 0.33595565 | I21: =I20/I11 -> 0.34241526 | J21: =J20/J11 -> 0.3408693 | K21: =K20/K11 -> 0.33927387 | L21: =L20/L11 -> 0.3430823
C23: Gastos Financieros | F23: =#REF! -> #REF! | G23: 7209 | H23: 3257 | I23: 3387 | J23: 3522 | K23: 3663 | L23: 3810
C25: Otros | F25: =#REF! -> #REF! | G25: 1964 | H25: 2679 | I25: 2786 | J25: 0 | K25: 0 | L25: 0
C27: Impuestos | F27: =#REF! -> #REF! | G27: 0 | H27: 0 | I27: 0 | J27: 0 | K27: 0 | L27: 0
C29: Utilidad Neta | F29: =F20+F25-F23-F27 -> #REF! | G29: =G20+G25-G23-G27 -> 43330 | H29: =H20+H25-H23-H27 -> 209145 | I29: =I20+I25-I23-I27 -> 245461 | J29: =J20+J25-J23-J27 -> 242557 | K29: =K20+K25-K23-K27 -> 242412 | L29: =L20+L25-L23-L27 -> 246215
F30: =F29/F11 -> #REF! | G30: =G29/G11 -> 0.13928893 | H30: =H29/H11 -> 0.33502975 | I30: =I29/I11 -> 0.34157892 | J30: =J29/J11 -> 0.33599061 | K30: =K29/K11 -> 0.33422354 | L30: =L29/L11 -> 0.33785425
C32: Cuentas por Cobrar | D32: =#REF! -> #REF! | E32: =#REF! -> #REF! | F32: =F11/360*$E$32 -> #REF! | G32: =G11/360*$E$32 -> #REF! | H32: =H11/360*$E$32 -> #REF! | I32: =I11/360*$E$32 -> #REF! | J32: =J11/360*$E$32 -> #REF! | K32: =K11/360*$E$32 -> #REF! | L32: =L11/360*$E$32 -> #REF!
C33: Inventario | D33: =#REF! -> #REF! | E33: =#REF! -> #REF! | F33: =F12/360*$E$33 -> #REF! | G33: =G12/360*$E$33 -> #REF! | H33: =H12/360*$E$33 -> #REF! | I33: =I12/360*$E$33 -> #REF! | J33: =J12/360*$E$33 -> #REF! | K33: =K12/360*$E$33 -> #REF! | L33: =L12/360*$E$33 -> #REF!
C34: Proveedores | D34: =#REF! -> #REF! | E34: =#REF! -> #REF! | F34: =F12/360*$E$34 -> #REF! | G34: =G12/360*$E$34 -> #REF! | H34: =H12/360*$E$34 -> #REF! | I34: =I12/360*$E$34 -> #REF! | J34: =J12/360*$E$34 -> #REF! | K34: =K12/360*$E$34 -> #REF! | L34: =L12/360*$E$34 -> #REF!
C36: Gastos Financieros | H36: 2010 | I36: 2011 | J36: 2012 | K36: 2013 | L36: 2014
C37: HSBC | D37: 120 | H37: 0 | I37: 0 | J37: 0 | K37: 0 | L37: 0
C38: Frost Bank (ACCC) | D38: 12800 | H38: =1280-190 -> 1090 | I38: 1280 | J38: 1280 | K38: 1280 | L38: 1280
C39: SAT | D39: 4864 | H39: 486.4 | I39: 243.2
C40: Banregio ACCC | D40: 7000 | H40: 700 | I40: 700 | J40: 700
C41: Banregio ACS | D41: 8000 | H41: 726.66667 | I41: 566.66667 | J41: 406.66667 | K41: 246.66667 | L41: 86.666667
C42: Banregio AF | D42: 3000 | H42: 254.16667 | I42: 154.16667 | J42: 54.166667
C43: Otros | I43: 443 | J43: 1081 | K43: 2136 | L43: 2443
C47: Total | D47: =SUM(D37:D46) -> 35784 | H47: =SUM(H37:H46) -> 3257.2333 | I47: =SUM(I37:I46) -> 3387.0333 | J47: =SUM(J37:J46) -> 3521.8333 | K47: =SUM(K37:K46) -> 3662.6667 | L47: =SUM(L37:L46) -> 3809.6667
C49: Pago a Capital
C50: =C37 -> HSBC | D50: =D37 -> 120 | H50: 120
C51: =C38 -> Frost Bank (ACCC) | D51: =D38 -> 12800 | H51: 0
C52: =C39 -> SAT | D52: =D39 -> 4864 | H52: 4864 | I52: 0
C53: =C40 -> Banregio ACCC | D53: =D40 -> 7000 | H53: 0 | I53: 0 | J53: 0
C54: =C41 -> Banregio ACS | D54: =D41 -> 8000 | H54: 1600 | I54: 1600 | J54: 1600 | K54: 1600 | L54: 1600
C55: =C42 -> Banregio AF | D55: =D42 -> 3000 | H55: 1000 | I55: 1000 | J55: 1000
C56: otros ACCC
C60: Total | D60: =SUM(D50:D59) -> 35784 | H60: =SUM(H50:H59) -> 7584 | I60: =SUM(I50:I59) -> 2600 | J60: =SUM(J50:J59) -> 2600 | K60: =SUM(K50:K59) -> 1600 | L60: =SUM(L50:L59) -> 1600
C63: Premisas de elaboración
C65: 1.- Se consideran los ingresos proyectados por el cliente
C66: 2.- Se consideran los costos y gastos estimados por el cliente

Sheet Flujo
C3: =#REF! -> #REF!
C4: Flujo de Efectivo Proyectado del Cliente
F5: =+PROYECCIONES!H9 -> 2010 | G5: =+PROYECCIONES!I9 -> 2011 | H5: =+PROYECCIONES!J9 -> 2012 | I5: =+PROYECCIONES!K9 -> 2013 | J5: =+PROYECCIONES!L9 -> 2014
C7: UAFIR | F7: =PROYECCIONES!H20 -> 209723 | G7: =PROYECCIONES!I20 -> 246062 | H7: =PROYECCIONES!J20 -> 246079 | I7: =PROYECCIONES!K20 -> 246075 | J7: =PROYECCIONES!L20 -> 250025
D9: DEPRECIACIÓN DEL EJERCICIO | F9: 0 | G9: 0 | H9: 0 | I9: 0 | J9: 0
C11: UAFIRDA | F11: =+F7+F9 -> 209723 | G11: =+G7+G9 -> 246062 | H11: =+H7+H9 -> 246079 | I11: =+I7+I9 -> 246075 | J11: =+J7+J9 -> 250025
D13: CUENTAS POR COBRAR | F13: =PROYECCIONES!G32-PROYECCIONES!H32 -> #REF! | G13: =PROYECCIONES!H32-PROYECCIONES!I32 -> #REF! | H13: =PROYECCIONES!I32-PROYECCIONES!J32 -> #REF! | I13: =PROYECCIONES!J32-PROYECCIONES!K32 -> #REF! | J13: =PROYECCIONES!K32-PROYECCIONES!L32 -> #REF!
D14: INVENTARIOS | F14: =PROYECCIONES!G33-PROYECCIONES!H33 -> #REF! | G14: =PROYECCIONES!H33-PROYECCIONES!I33 -> #REF! | H14: =PROYECCIONES!I33-PROYECCIONES!J33 -> #REF! | I14: =PROYECCIONES!J33-PROYECCIONES!K33 -> #REF! | J14: =PROYECCIONES!K33-PROYECCIONES!L33 -> #REF!
D15: PROVEEDORES | F15: =PROYECCIONES!H34-PROYECCIONES!G34 -> #REF! | G15: =PROYECCIONES!I34-PROYECCIONES!H34 -> #REF! | H15: =PROYECCIONES!J34-PROYECCIONES!I34 -> #REF! | I15: =PROYECCIONES!K34-PROYECCIONES!J34 -> #REF! | J15: =PROYECCIONES!L34-PROYECCIONES!K34 -> #REF!
E16: SUBTOTAL OPERACIÓN | F16: =SUM(F13:F15) -> #REF! | G16: =SUM(G13:G15) -> #REF! | H16: =SUM(H13:H15) -> #REF! | I16: =SUM(I13:I15) -> #REF! | J16: =SUM(J13:J15) -> #REF!
C18: FLUJO DE OPERACIÓN | F18: =+F11+F16 -> #REF! | G18: =+G11+G16 -> #REF! | H18: =+H11+H16 -> #REF! | I18: =+I11+I16 -> #REF! | J18: =+J11+J16 -> #REF!
D20: GASTOS FINANCIEROS | F20: =PROYECCIONES!H23 -> 3257 | G20: =PROYECCIONES!I23 -> 3387 | H20: =PROYECCIONES!J23 -> 3522 | I20: =PROYECCIONES!K23 -> 3663 | J20: =PROYECCIONES!L23 -> 3810
C22: FLUJO ANTES DE IMPUESTOS | F22: =F18-F20 -> #REF! | G22: =G18-G20 -> #REF! | H22: =H18-H20 -> #REF! | I22: =I18-I20 -> #REF! | J22: =J18-J20 -> #REF!
D24: IMPUESTOS PAGADOS | F24: =PROYECCIONES!G27 -> 0 | G24: =PROYECCIONES!H27 -> 0 | H24: =PROYECCIONES!I27 -> 0 | I24: =PROYECCIONES!J27 -> 0 | J24: =PROYECCIONES!K27 -> 0
C26: FLUJO NETO | F26: =F22-F24 -> #REF! | G26: =G22-G24 -> #REF! | H26: =H22-H24 -> #REF! | I26: =I22-I24 -> #REF! | J26: =J22-J24 -> #REF!
C28: OTRAS ACTIVIDADES
D29: DEUDORES DIVERSOS | F29: 0 | G29: 0 | H29: 0 | I29: 0 | J29: 0
D30: OTROS ACTIVOS | F30: 0 | G30: 0 | H30: 0 | I30: 0 | J30: 0
E31: SUBTOTAL OTROS | F31: =SUM(F29:F30) -> 0 | G31: =SUM(G29:G30) -> 0 | H31: =SUM(H29:H30) -> 0 | I31: =SUM(I29:I30) -> 0 | J31: =SUM(J29:J30) -> 0
C33: ACTIVIDADES DE INVERSIÓN
D34: ADQUISICIÓN O VENTA DE ACTIVO FIJO | F34: 0 | G34: 0 | H34: 0 | I34: 0 | J34: 0
E35: SUBTOTAL INVERSIONES | F35: =F34 -> 0 | G35: =G34 -> 0 | H35: =H34 -> 0 | I35: =I34 -> 0 | J35: =J34 -> 0
C37: FLUJO DESPUÉS DE INVERSIONES | F37: =+F26+F35+F31 -> #REF! | G37: =+G26+G35+G31 -> #REF! | H37: =+H26+H35+H31 -> #REF! | I37: =+I26+I35+I31 -> #REF! | J37: =+J26+J35+J31 -> #REF!
C39: FUENTES DE FINANCIAMIENTO
D40: PASIVOS FINANCIEROS | F40: =PROYECCIONES!H60*-1 -> -7584 | G40: =PROYECCIONES!I60*-1 -> -2600 | H40: =PROYECCIONES!J60*-1 -> -2600 | I40: =PROYECCIONES!K60*-1 -> -1600 | J40: =PROYECCIONES!L60*-1 -> -1600
D41: ACREEDORES DIVERSOS | F41: 0 | G41: 0 | H41: 0 | I41: 0 | J41: 0
D42: DIF EN UTILIDADES RET / DECRETO DE DIVIDENDOS | F42: 0 | G42: 0 | H42: 0 | I42: 0 | J42: 0
D43: CAPITAL SOCIAL | F43: 0 | G43: 0 | H43: 0 | I43: 0 | J43: 0
D44: RESERVAS | F44: 0 | G44: 0 | H44: 0 | I44: 0 | J44: 0
D45: APORTACIONES P FUTUROS AUMEN. | F45: 0 | G45: 0 | H45: 0 | I45: 0 | J45: 0
E46: SUBTOTAL FUENTES | F46: =SUM(F40:F45) -> -7584 | G46: =SUM(G40:G45) -> -2600 | H46: =SUM(H40:H45) -> -2600 | I46: =SUM(I40:I45) -> -1600 | J46: =SUM(J40:J45) -> -1600
C48: FLUJO DESPUÉS DE FINANCIAMIENTO | F48: =+F37+F46 -> #REF! | G48: =+G37+G46 -> #REF! | H48: =+H37+H46 -> #REF! | I48: =+I37+I46 -> #REF! | J48: =+J37+J46 -> #REF!
C50: VARIACIÓN EN CAJA | F50: 0 | G50: 0 | H50: 0 | I50: 0 | J50: 0
C52: Cobertura de deuda | F52: =F26/(F40*-1) -> #REF! | G52: =G26/(G40*-1) -> #REF! | H52: =H26/(H40*-1) -> #REF! | I52: =I26/(I40*-1) -> #REF! | J52: =J26/(J40*-1) -> #REF!
C54: Cobertura de Intereses | F54: =F18/F20 -> #REF! | G54: =G18/G20 -> #REF! | H54: =H18/H20 -> #REF! | I54: =I18/I20 -> #REF! | J54: =J18/J20 -> #REF!

Sheet Proy banco
C5: =#REF! -> #REF!
C6: Proyección (Sensibilizado)
F8: Real | G8: Estimado | H8: Proyección
F9: 2008 | G9: 2009 | H9: 2010 | I9: 2011 | J9: 2012 | K9: 2013 | L9: 2014
C11: Ingresos | F11: =#REF! -> #REF! | G11: =138845+161898+10337 -> 311080 | H11: =138737+474028+11493 -> 624258 | I11: =141511+565143+11953 -> 718607 | J11: =144342+565143+12431 -> 721916 | K11: =147228+565143+12928 -> 725299 | L11: =150173+565143+13445 -> 728761
C12: Costo de Venta | F12: =#REF!+#REF! -> #REF! | G12: =+G13*G11 -> 242642.4 | H12: =+H13*H11 -> 518134.14 | I12: =+I13*I11 -> 596443.81 | J12: =+J13*J11 -> 599190.28 | K12: =+K13*K11 -> 601998.17 | L12: =+L13*L11 -> 604871.63
F13: =F12/F11 -> #REF! | G13: 0.78 | H13: 0.83 | I13: 0.83 | J13: 0.83 | K13: 0.83 | L13: 0.83
C15: Utilidad Bruta | F15: =F11-F12 -> #REF! | G15: =G11-G12 -> 68437.6 | H15: =H11-H12 -> 106123.86 | I15: =I11-I12 -> 122163.19 | J15: =J11-J12 -> 122725.72 | K15: =K11-K12 -> 123300.83 | L15: =L11-L12 -> 123889.37
F16: =F15/F11 -> #REF! | G16: =G15/G11 -> 0.22 | H16: =H15/H11 -> 0.17 | I16: =I15/I11 -> 0.17 | J16: =J15/J11 -> 0.17 | K16: =K15/K11 -> 0.17 | L16: =L15/L11 -> 0.17
C18: Gastos de Admon y Vta | F18: =#REF! -> #REF! | G18: =11636+8063+6801+3397 -> 29897 | H18: =12287+9543+3397 -> 25227 | I18: =12778+9925+3533 -> 26236 | J18: =13289+10322+3674 -> 27285 | K18: =13821+10735+3820 -> 28376 | L18: =14374+11165 -> 25539
F19: =+F18/F11 -> #REF! | G19: =+G18/G11 -> 0.096107111 | H19: =+H18/H11 -> 0.040411176 | I19: =+I18/I11 -> 0.036509525 | J19: =+J18/J11 -> 0.037795256 | K19: =+K18/K11 -> 0.039123175 | L19: =+L18/L11 -> 0.035044411
C20: Utilidad operativa | F20: =F15-F18 -> #REF! | G20: =G15-G18 -> 38540.6 | H20: =H15-H18 -> 80896.86 | I20: =I15-I18 -> 95927.19 | J20: =J15-J18 -> 95440.72 | K20: =K15-K18 -> 94924.83 | L20: =L15-L18 -> 98350.37
F21: =F20/F11 -> #REF! | G21: =G20/G11 -> 0.12389289 | H21: =H20/H11 -> 0.12958882 | I21: =I20/I11 -> 0.13349048 | J21: =J20/J11 -> 0.13220474 | K21: =K20/K11 -> 0.13087682 | L21: =L20/L11 -> 0.13495559
C23: Gastos Financieros | F23: =#REF! -> #REF! | G23: 7209 | H23: 3257 | I23: 3387 | J23: 3522 | K23: 3663 | L23: 3810
C25: Otros | F25: =#REF! -> #REF! | G25: 1964 | H25: 0 | I25: 0 | J25: 0 | K25: 0 | L25: 0
C27: Impuestos | F27: =#REF! -> #REF! | G27: 0 | H27: =H11*0.1 -> 62425.8 | I27: =I11*0.1 -> 71860.7 | J27: =J11*0.1 -> 72191.6 | K27: =K11*0.1 -> 72529.9 | L27: =L11*0.1 -> 72876.1
C29: Utilidad Neta | F29: =F20+F25-F23-F27 -> #REF! | G29: =G20+G25-G23-G27 -> 33295.6 | H29: =H20+H25-H23-H27 -> 15214.06 | I29: =I20+I25-I23-I27 -> 20679.49 | J29: =J20+J25-J23-J27 -> 19727.12 | K29: =K20+K25-K23-K27 -> 18731.93 | L29: =L20+L25-L23-L27 -> 21664.27
F30: =F29/F11 -> #REF! | G30: =G29/G11 -> 0.10703227 | H30: =H29/H11 -> 0.02437143 | I30: =I29/I11 -> 0.02877719 | J30: =J29/J11 -> 0.02732606 | K30: =K29/K11 -> 0.025826494 | L30: =L29/L11 -> 0.029727538
C32: Cuentas por Cobrar | D32: =#REF! -> #REF! | E32: =#REF! -> #REF! | F32: =F11/360*$E$32 -> #REF! | G32: =G11/360*$E$32 -> #REF! | H32: =H11/360*$E$32 -> #REF! | I32: =I11/360*$E$32 -> #REF! | J32: =J11/360*$E$32 -> #REF! | K32: =K11/360*$E$32 -> #REF! | L32: =L11/360*$E$32 -> #REF!
C33: Inventario | D33: =#REF! -> #REF! | E33: =#REF! -> #REF! | F33: =F12/360*$E$33 -> #REF! | G33: =G12/360*$E$33 -> #REF! | H33: =H12/360*$E$33 -> #REF! | I33: =I12/360*$E$33 -> #REF! | J33: =J12/360*$E$33 -> #REF! | K33: =K12/360*$E$33 -> #REF! | L33: =L12/360*$E$33 -> #REF!
C34: Proveedores | D34: =#REF! -> #REF! | E34: =#REF! -> #REF! | F34: =F12/360*$E$34 -> #REF! | G34: =G12/360*$E$34 -> #REF! | H34: =H12/360*$E$34 -> #REF! | I34: =I12/360*$E$34 -> #REF! | J34: =J12/360*$E$34 -> #REF! | K34: =K12/360*$E$34 -> #REF! | L34: =L12/360*$E$34 -> #REF!
C36: Gastos Financieros | H36: =H9 -> 2010 | I36: =I9 -> 2011 | J36: =J9 -> 2012 | K36: =K9 -> 2013 | L36: =L9 -> 2014
C37: HSBC | D37: 120 | H37: 0 | I37: 0 | J37: 0 | K37: 0 | L37: 0
C38: Frost Bank (ACCC) | D38: 12800 | H38: =D38*0.1 -> 1280 | I38: =H38 -> 1280 | J38: =I38 -> 1280 | K38: =J38 -> 1280 | L38: =K38 -> 1280
C39: SAT | D39: 4864 | H39: =D39*0.1 -> 486.4 | I39: =D39/2*0.1 -> 243.2
C40: Banregio ACCC | D40: 7000 | H40: =D40*0.1 -> 700 | I40: =+H40 -> 700 | J40: =+I40 -> 700
C41: Banregio ACS | D41: 8000 | H41: =+ACS!J10 -> 726.66667 | I41: =+ACS!K10 -> 566.66667 | J41: =+ACS!L10 -> 406.66667 | K41: =+ACS!M10 -> 246.66667 | L41: =+ACS!N10 -> 86.666667
C42: Banregio AF | D42: 3000 | H42: =+AF!J10 -> 254.16667 | I42: =+AF!K10 -> 154.16667 | J42: =+AF!L10 -> 54.166667
C47: Total | D47: =SUM(D37:D46) -> 35784 | H47: =SUM(H37:H46) -> 3447.2333 | I47: =SUM(I37:I46) -> 2944.0333 | J47: =SUM(J37:J46) -> 2440.8333 | K47: =SUM(K37:K46) -> 1526.6667 | L47: =SUM(L37:L46) -> 1366.6667
C49: Pago a Capital
C50: =C37 -> HSBC | D50: =D37 -> 120 | H50: 120
C51: =C38 -> Frost Bank (ACCC) | D51: =D38 -> 12800 | H51: 0
C52: =C39 -> SAT | D52: =D39 -> 4864 | H52: 4864 | I52: 0
C53: =C40 -> Banregio ACCC | D53: =D40 -> 7000 | H53: 0 | I53: =H53 -> 0 | J53: 0
C54: =C41 -> Banregio ACS | D54: =D41 -> 8000 | H54: =+ACS!J11 -> 1600 | I54: =+ACS!K11 -> 1600 | J54: =+ACS!L11 -> 1600 | K54: =+ACS!M11 -> 1600 | L54: =+ACS!N11 -> 1600
C55: =C42 -> Banregio AF | D55: =D42 -> 3000 | H55: =+AF!J11 -> 1000 | I55: =+AF!K11 -> 1000 | J55: =+AF!L11 -> 1000
C60: Total | D60: =SUM(D50:D59) -> 35784 | H60: =SUM(H50:H59) -> 7584 | I60: =SUM(I50:I59) -> 2600 | J60: =SUM(J50:J59) -> 2600 | K60: =SUM(K50:K59) -> 1600 | L60: =SUM(L50:L59) -> 1600
C63: Premisas de elaboración
C65: 1.- Se consideran los ingresos proyectados por el cliente
C66: 2.- Se consideran los costos y gastos con un margen de operación similar al cierre del 2008
C67: 3.- La tasa de interés se estima en 10%
C68: 4.- Se calcula un impuesto del 10% sobre ventas
C69: 5.- No se consideran otros ingresos.
C70: 6.- Se considera pagos al SAT
C71: 7.- Se consideran las amortizadciones de créditos actuales y por contratar

Sheet Flujo banco
C3: =#REF! -> #REF!
C4: Flujo de Efectivo Proyectado (Sensibilizado)
F5: =+'Proy banco'!H9 -> 2010 | G5: =+'Proy banco'!I9 -> 2011 | H5: =+'Proy banco'!J9 -> 2012 | I5: =+'Proy banco'!K9 -> 2013 | J5: =+'Proy banco'!L9 -> 2014
C7: UAFIR | F7: ='Proy banco'!H20 -> 80896.86 | G7: ='Proy banco'!I20 -> 95927.19 | H7: ='Proy banco'!J20 -> 95440.72 | I7: ='Proy banco'!K20 -> 94924.83 | J7: ='Proy banco'!L20 -> 98350.37
D9: DEPRECIACIÓN DEL EJERCICIO | F9: 0 | G9: 0 | H9: 0 | I9: 0 | J9: 0
C11: UAFIRDA | F11: =+F7+F9 -> 80896.86 | G11: =+G7+G9 -> 95927.19 | H11: =+H7+H9 -> 95440.72 | I11: =+I7+I9 -> 94924.83 | J11: =+J7+J9 -> 98350.37
D13: CUENTAS POR COBRAR | F13: ='Proy banco'!G32-'Proy banco'!H32 -> #REF! | G13: ='Proy banco'!H32-'Proy banco'!I32 -> #REF! | H13: ='Proy banco'!I32-'Proy banco'!J32 -> #REF! | I13: ='Proy banco'!J32-'Proy banco'!K32 -> #REF! | J13: ='Proy banco'!K32-'Proy banco'!L32 -> #REF!
D14: INVENTARIOS | F14: ='Proy banco'!G33-'Proy banco'!H33 -> #REF! | G14: ='Proy banco'!H33-'Proy banco'!I33 -> #REF! | H14: ='Proy banco'!I33-'Proy banco'!J33 -> #REF! | I14: ='Proy banco'!J33-'Proy banco'!K33 -> #REF! | J14: ='Proy banco'!K33-'Proy banco'!L33 -> #REF!
D15: PROVEEDORES | F15: ='Proy banco'!H34-'Proy banco'!G34 -> #REF! | G15: ='Proy banco'!I34-'Proy banco'!H34 -> #REF! | H15: ='Proy banco'!J34-'Proy banco'!I34 -> #REF! | I15: ='Proy banco'!K34-'Proy banco'!J34 -> #REF! | J15: ='Proy banco'!L34-'Proy banco'!K34 -> #REF!
E16: SUBTOTAL OPERACIÓN | F16: =SUM(F13:F15) -> #REF! | G16: =SUM(G13:G15) -> #REF! | H16: =SUM(H13:H15) -> #REF! | I16: =SUM(I13:I15) -> #REF! | J16: =SUM(J13:J15) -> #REF!
C18: FLUJO DE OPERACIÓN | F18: =+F11+F16 -> #REF! | G18: =+G11+G16 -> #REF! | H18: =+H11+H16 -> #REF! | I18: =+I11+I16 -> #REF! | J18: =+J11+J16 -> #REF!
D20: GASTOS FINANCIEROS | F20: ='Proy banco'!H23 -> 3257 | G20: ='Proy banco'!I23 -> 3387 | H20: ='Proy banco'!J23 -> 3522 | I20: ='Proy banco'!K23 -> 3663 | J20: ='Proy banco'!L23 -> 3810
C22: FLUJO ANTES DE IMPUESTOS | F22: =F18-F20 -> #REF! | G22: =G18-G20 -> #REF! | H22: =H18-H20 -> #REF! | I22: =I18-I20 -> #REF! | J22: =J18-J20 -> #REF!
D24: IMPUESTOS PAGADOS | F24: ='Proy banco'!G27 -> 0 | G24: ='Proy banco'!H27 -> 62425.8 | H24: ='Proy banco'!I27 -> 71860.7 | I24: ='Proy banco'!J27 -> 72191.6 | J24: ='Proy banco'!K27 -> 72529.9
C26: FLUJO NETO | F26: =F22-F24 -> #REF! | G26: =G22-G24 -> #REF! | H26: =H22-H24 -> #REF! | I26: =I22-I24 -> #REF! | J26: =J22-J24 -> #REF!
C28: OTRAS ACTIVIDADES
D29: DEUDORES DIVERSOS | F29: 0 | G29: 0 | H29: 0 | I29: 0 | J29: 0
D30: OTROS ACTIVOS | F30: 0 | G30: 0 | H30: 0 | I30: 0 | J30: 0
E31: SUBTOTAL OTROS | F31: =SUM(F29:F30) -> 0 | G31: =SUM(G29:G30) -> 0 | H31: =SUM(H29:H30) -> 0 | I31: =SUM(I29:I30) -> 0 | J31: =SUM(J29:J30) -> 0
C33: ACTIVIDADES DE INVERSIÓN
D34: ADQUISICIÓN O VENTA DE ACTIVO FIJO | F34: 0 | G34: 0 | H34: 0 | I34: 0 | J34: 0
E35: SUBTOTAL INVERSIONES | F35: =F34 -> 0 | G35: =G34 -> 0 | H35: =H34 -> 0 | I35: =I34 -> 0 | J35: =J34 -> 0
C37: FLUJO DESPUÉS DE INVERSIONES | F37: =+F26+F35+F31 -> #REF! | G37: =+G26+G35+G31 -> #REF! | H37: =+H26+H35+H31 -> #REF! | I37: =+I26+I35+I31 -> #REF! | J37: =+J26+J35+J31 -> #REF!
C39: FUENTES DE FINANCIAMIENTO
D40: PASIVOS FINANCIEROS | F40: ='Proy banco'!H60*-1 -> -7584 | G40: ='Proy banco'!I60*-1 -> -2600 | H40: ='Proy banco'!J60*-1 -> -2600 | I40: ='Proy banco'!K60*-1 -> -1600 | J40: ='Proy banco'!L60*-1 -> -1600
D41: ACREEDORES DIVERSOS | F41: 0 | G41: 0 | H41: 0 | I41: 0 | J41: 0
D42: DIF EN UTILIDADES RET / DECRETO DE DIVIDENDOS | F42: 0 | G42: 0 | H42: 0 | I42: 0 | J42: 0
D43: CAPITAL SOCIAL | F43: 0 | G43: 0 | H43: 0 | I43: 0 | J43: 0
D44: RESERVAS | F44: 0 | G44: 0 | H44: 0 | I44: 0 | J44: 0
D45: APORTACIONES P FUTUROS AUMEN. | F45: 0 | G45: 0 | H45: 0 | I45: 0 | J45: 0
E46: SUBTOTAL FUENTES | F46: =SUM(F40:F45) -> -7584 | G46: =SUM(G40:G45) -> -2600 | H46: =SUM(H40:H45) -> -2600 | I46: =SUM(I40:I45) -> -1600 | J46: =SUM(J40:J45) -> -1600
C48: FLUJO DESPUÉS DE FINANCIAMIENTO | F48: =+F37+F46 -> #REF! | G48: =+G37+G46 -> #REF! | H48: =+H37+H46 -> #REF! | I48: =+I37+I46 -> #REF! | J48: =+J37+J46 -> #REF!
C50: VARIACIÓN EN CAJA | F50: 0 | G50: 0 | H50: 0 | I50: 0 | J50: 0
C52: Cobertura de deuda | F52: =F26/(F40*-1) -> #REF! | G52: =G26/(G40*-1) -> #REF! | H52: =H26/(H40*-1) -> #REF! | I52: =I26/(I40*-1) -> #REF! | J52: =J26/(J40*-1) -> #REF!
C54: Cobertura de Intereses | F54: =F18/F20 -> #REF! | G54: =G18/G20 -> #REF! | H54: =H18/H20 -> #REF! | I54: =I18/I20 -> #REF! | J54: =J18/J20 -> #REF!

Sheet ACS
C6: Tipo | D6: ACS
C7: Monto | D7: 8000
C8: Tasa | D8: 0.1 | E8: =+D8/12 -> 0.0083333333
C9: Plazo | D9: 60 | E9: meses | J9: 1 | K9: 2 | L9: 3 | M9: 4 | N9: 5
H10: interes | J10: =+H23 -> 726.66667 | K10: =+H35 -> 566.66667 | L10: =+H47 -> 406.66667 | M10: =+H59 -> 246.66667 | N10: =+H71 -> 86.666667
C11: capital | E11: interes | F11: pago | G11: saldo | I11: capital | J11: =+D12*12 -> 1600 | K11: =+J11 -> 1600 | L11: =+K11 -> 1600 | M11: =+L11 -> 1600 | N11: =+M11 -> 1600
B12: 1 | C12: =+D7 -> 8000 | D12: =+C12/D9 -> 133.33333 | E12: =+C12*$E$8 -> 66.666667 | F12: =+D12+E12 -> 200 | G12: =+C12-D12 -> 7866.6667
B13: 2 | C13: =+G12 -> 7866.6667 | D13: =+D12 -> 133.33333 | E13: =+C13*$E$8 -> 65.555556 | F13: =+D13+E13 -> 198.88889 | G13: =+C13-D13 -> 7733.3333
B14: 3 | C14: =+G13 -> 7733.3333 | D14: =+D13 -> 133.33333 | E14: =+C14*$E$8 -> 64.444444 | F14: =+D14+E14 -> 197.77778 | G14: =+C14-D14 -> 7600
B15: 4 | C15: =+G14 -> 7600 | D15: =+D14 -> 133.33333 | E15: =+C15*$E$8 -> 63.333333 | F15: =+D15+E15 -> 196.66667 | G15: =+C15-D15 -> 7466.6667
B16: 5 | C16: =+G15 -> 7466.6667 | D16: =+D15 -> 133.33333 | E16: =+C16*$E$8 -> 62.222222 | F16: =+D16+E16 -> 195.55556 | G16: =+C16-D16 -> 7333.3333
B17: 6 | C17: =+G16 -> 7333.3333 | D17: =+D16 -> 133.33333 | E17: =+C17*$E$8 -> 61.111111 | F17: =+D17+E17 -> 194.44444 | G17: =+C17-D17 -> 7200
B18: 7 | C18: =+G17 -> 7200 | D18: =+D17 -> 133.33333 | E18: =+C18*$E$8 -> 60 | F18: =+D18+E18 -> 193.33333 | G18: =+C18-D18 -> 7066.6667
B19: 8 | C19: =+G18 -> 7066.6667 | D19: =+D18 -> 133.33333 | E19: =+C19*$E$8 -> 58.888889 | F19: =+D19+E19 -> 192.22222 | G19: =+C19-D19 -> 6933.3333
B20: 9 | C20: =+G19 -> 6933.3333 | D20: =+D19 -> 133.33333 | E20: =+C20*$E$8 -> 57.777778 | F20: =+D20+E20 -> 191.11111 | G20: =+C20-D20 -> 6800
B21: 10 | C21: =+G20 -> 6800 | D21: =+D20 -> 133.33333 | E21: =+C21*$E$8 -> 56.666667 | F21: =+D21+E21 -> 190 | G21: =+C21-D21 -> 6666.6667
B22: 11 | C22: =+G21 -> 6666.6667 | D22: =+D21 -> 133.33333 | E22: =+C22*$E$8 -> 55.555556 | F22: =+D22+E22 -> 188.88889 | G22: =+C22-D22 -> 6533.3333
B23: 12 | C23: =+G22 -> 6533.3333 | D23: =+D22 -> 133.33333 | E23: =+C23*$E$8 -> 54.444444 | F23: =+D23+E23 -> 187.77778 | G23: =+C23-D23 -> 6400 | H23: =SUM(E12:E23) -> 726.66667
B24: 13 | C24: =+G23 -> 6400 | D24: =+D23 -> 133.33333 | E24: =+C24*$E$8 -> 53.333333 | F24: =+D24+E24 -> 186.66667 | G24: =+C24-D24 -> 6266.6667
B25: 14 | C25: =+G24 -> 6266.6667 | D25: =+D24 -> 133.33333 | E25: =+C25*$E$8 -> 52.222222 | F25: =+D25+E25 -> 185.55556 | G25: =+C25-D25 -> 6133.3333
B26: 15 | C26: =+G25 -> 6133.3333 | D26: =+D25 -> 133.33333 | E26: =+C26*$E$8 -> 51.111111 | F26: =+D26+E26 -> 184.44444 | G26: =+C26-D26 -> 6000
B27: 16 | C27: =+G26 -> 6000 | D27: =+D26 -> 133.33333 | E27: =+C27*$E$8 -> 50 | F27: =+D27+E27 -> 183.33333 | G27: =+C27-D27 -> 5866.6667
B28: 17 | C28: =+G27 -> 5866.6667 | D28: =+D27 -> 133.33333 | E28: =+C28*$E$8 -> 48.888889 | F28: =+D28+E28 -> 182.22222 | G28: =+C28-D28 -> 5733.3333
B29: 18 | C29: =+G28 -> 5733.3333 | D29: =+D28 -> 133.33333 | E29: =+C29*$E$8 -> 47.777778 | F29: =+D29+E29 -> 181.11111 | G29: =+C29-D29 -> 5600
B30: 19 | C30: =+G29 -> 5600 | D30: =+D29 -> 133.33333 | E30: =+C30*$E$8 -> 46.666667 | F30: =+D30+E30 -> 180 | G30: =+C30-D30 -> 5466.6667
B31: 20 | C31: =+G30 -> 5466.6667 | D31: =+D30 -> 133.33333 | E31: =+C31*$E$8 -> 45.555556 | F31: =+D31+E31 -> 178.88889 | G31: =+C31-D31 -> 5333.3333
B32: 21 | C32: =+G31 -> 5333.3333 | D32: =+D31 -> 133.33333 | E32: =+C32*$E$8 -> 44.444444 | F32: =+D32+E32 -> 177.77778 | G32: =+C32-D32 -> 5200
B33: 22 | C33: =+G32 -> 5200 | D33: =+D32 -> 133.33333 | E33: =+C33*$E$8 -> 43.333333 | F33: =+D33+E33 -> 176.66667 | G33: =+C33-D33 -> 5066.6667
B34: 23 | C34: =+G33 -> 5066.6667 | D34: =+D33 -> 133.33333 | E34: =+C34*$E$8 -> 42.222222 | F34: =+D34+E34 -> 175.55556 | G34: =+C34-D34 -> 4933.3333
B35: 24 | C35: =+G34 -> 4933.3333 | D35: =+D34 -> 133.33333 | E35: =+C35*$E$8 -> 41.111111 | F35: =+D35+E35 -> 174.44444 | G35: =+C35-D35 -> 4800 | H35: =SUM(E24:E35) -> 566.66667
B36: 25 | C36: =+G35 -> 4800 | D36: =+D35 -> 133.33333 | E36: =+C36*$E$8 -> 40 | F36: =+D36+E36 -> 173.33333 | G36: =+C36-D36 -> 4666.6667
B37: 26 | C37: =+G36 -> 4666.6667 | D37: =+D36 -> 133.33333 | E37: =+C37*$E$8 -> 38.888889 | F37: =+D37+E37 -> 172.22222 | G37: =+C37-D37 -> 4533.3333
B38: 27 | C38: =+G37 -> 4533.3333 | D38: =+D37 -> 133.33333 | E38: =+C38*$E$8 -> 37.777778 | F38: =+D38+E38 -> 171.11111 | G38: =+C38-D38 -> 4400
B39: 28 | C39: =+G38 -> 4400 | D39: =+D38 -> 133.33333 | E39: =+C39*$E$8 -> 36.666667 | F39: =+D39+E39 -> 170 | G39: =+C39-D39 -> 4266.6667
B40: 29 | C40: =+G39 -> 4266.6667 | D40: =+D39 -> 133.33333 | E40: =+C40*$E$8 -> 35.555556 | F40: =+D40+E40 -> 168.88889 | G40: =+C40-D40 -> 4133.3333
B41: 30 | C41: =+G40 -> 4133.3333 | D41: =+D40 -> 133.33333 | E41: =+C41*$E$8 -> 34.444444 | F41: =+D41+E41 -> 167.77778 | G41: =+C41-D41 -> 4000
B42: 31 | C42: =+G41 -> 4000 | D42: =+D41 -> 133.33333 | E42: =+C42*$E$8 -> 33.333333 | F42: =+D42+E42 -> 166.66667 | G42: =+C42-D42 -> 3866.6667
B43: 32 | C43: =+G42 -> 3866.6667 | D43: =+D42 -> 133.33333 | E43: =+C43*$E$8 -> 32.222222 | F43: =+D43+E43 -> 165.55556 | G43: =+C43-D43 -> 3733.3333
B44: 33 | C44: =+G43 -> 3733.3333 | D44: =+D43 -> 133.33333 | E44: =+C44*$E$8 -> 31.111111 | F44: =+D44+E44 -> 164.44444 | G44: =+C44-D44 -> 3600
B45: 34 | C45: =+G44 -> 3600 | D45: =+D44 -> 133.33333 | E45: =+C45*$E$8 -> 30 | F45: =+D45+E45 -> 163.33333 | G45: =+C45-D45 -> 3466.6667
B46: 35 | C46: =+G45 -> 3466.6667 | D46: =+D45 -> 133.33333 | E46: =+C46*$E$8 -> 28.888889 | F46: =+D46+E46 -> 162.22222 | G46: =+C46-D46 -> 3333.3333
B47: 36 | C47: =+G46 -> 3333.3333 | D47: =+D46 -> 133.33333 | E47: =+C47*$E$8 -> 27.777778 | F47: =+D47+E47 -> 161.11111 | G47: =+C47-D47 -> 3200 | H47: =SUM(E36:E47) -> 406.66667
B48: 37 | C48: =+G47 -> 3200 | D48: =+D47 -> 133.33333 | E48: =+C48*$E$8 -> 26.666667 | F48: =+D48+E48 -> 160 | G48: =+C48-D48 -> 3066.6667
B49: 38 | C49: =+G48 -> 3066.6667 | D49: =+D48 -> 133.33333 | E49: =+C49*$E$8 -> 25.555556 | F49: =+D49+E49 -> 158.88889 | G49: =+C49-D49 -> 2933.3333
B50: 39 | C50: =+G49 -> 2933.3333 | D50: =+D49 -> 133.33333 | E50: =+C50*$E$8 -> 24.444444 | F50: =+D50+E50 -> 157.77778 | G50: =+C50-D50 -> 2800
B51: 40 | C51: =+G50 -> 2800 | D51: =+D50 -> 133.33333 | E51: =+C51*$E$8 -> 23.333333 | F51: =+D51+E51 -> 156.66667 | G51: =+C51-D51 -> 2666.6667
B52: 41 | C52: =+G51 -> 2666.6667 | D52: =+D51 -> 133.33333 | E52: =+C52*$E$8 -> 22.222222 | F52: =+D52+E52 -> 155.55556 | G52: =+C52-D52 -> 2533.3333
B53: 42 | C53: =+G52 -> 2533.3333 | D53: =+D52 -> 133.33333 | E53: =+C53*$E$8 -> 21.111111 | F53: =+D53+E53 -> 154.44444 | G53: =+C53-D53 -> 2400
B54: 43 | C54: =+G53 -> 2400 | D54: =+D53 -> 133.33333 | E54: =+C54*$E$8 -> 20 | F54: =+D54+E54 -> 153.33333 | G54: =+C54-D54 -> 2266.6667
B55: 44 | C55: =+G54 -> 2266.6667 | D55: =+D54 -> 133.33333 | E55: =+C55*$E$8 -> 18.888889 | F55: =+D55+E55 -> 152.22222 | G55: =+C55-D55 -> 2133.3333
B56: 45 | C56: =+G55 -> 2133.3333 | D56: =+D55 -> 133.33333 | E56: =+C56*$E$8 -> 17.777778 | F56: =+D56+E56 -> 151.11111 | G56: =+C56-D56 -> 2000
B57: 46 | C57: =+G56 -> 2000 | D57: =+D56 -> 133.33333 | E57: =+C57*$E$8 -> 16.666667 | F57: =+D57+E57 -> 150 | G57: =+C57-D57 -> 1866.6667
B58: 47 | C58: =+G57 -> 1866.6667 | D58: =+D57 -> 133.33333 | E58: =+C58*$E$8 -> 15.555556 | F58: =+D58+E58 -> 148.88889 | G58: =+C58-D58 -> 1733.3333
B59: 48 | C59: =+G58 -> 1733.3333 | D59: =+D58 -> 133.33333 | E59: =+C59*$E$8 -> 14.444444 | F59: =+D59+E59 -> 147.77778 | G59: =+C59-D59 -> 1600 | H59: =SUM(E48:E59) -> 246.66667
B60: 49 | C60: =+G59 -> 1600 | D60: =+D59 -> 133.33333 | E60: =+C60*$E$8 -> 13.333333 | F60: =+D60+E60 -> 146.66667 | G60: =+C60-D60 -> 1466.6667
B61: 50 | C61: =+G60 -> 1466.6667 | D61: =+D60 -> 133.33333 | E61: =+C61*$E$8 -> 12.222222 | F61: =+D61+E61 -> 145.55556 | G61: =+C61-D61 -> 1333.3333
B62: 51 | C62: =+G61 -> 1333.3333 | D62: =+D61 -> 133.33333 | E62: =+C62*$E$8 -> 11.111111 | F62: =+D62+E62 -> 144.44444 | G62: =+C62-D62 -> 1200
B63: 52 | C63: =+G62 -> 1200 | D63: =+D62 -> 133.33333 | E63: =+C63*$E$8 -> 10 | F63: =+D63+E63 -> 143.33333 | G63: =+C63-D63 -> 1066.6667
B64: 53 | C64: =+G63 -> 1066.6667 | D64: =+D63 -> 133.33333 | E64: =+C64*$E$8 -> 8.8888889 | F64: =+D64+E64 -> 142.22222 | G64: =+C64-D64 -> 933.33333
B65: 54 | C65: =+G64 -> 933.33333 | D65: =+D64 -> 133.33333 | E65: =+C65*$E$8 -> 7.7777778 | F65: =+D65+E65 -> 141.11111 | G65: =+C65-D65 -> 800
B66: 55 | C66: =+G65 -> 800 | D66: =+D65 -> 133.33333 | E66: =+C66*$E$8 -> 6.6666667 | F66: =+D66+E66 -> 140 | G66: =+C66-D66 -> 666.66667
B67: 56 | C67: =+G66 -> 666.66667 | D67: =+D66 -> 133.33333 | E67: =+C67*$E$8 -> 5.5555556 | F67: =+D67+E67 -> 138.88889 | G67: =+C67-D67 -> 533.33333
B68: 57 | C68: =+G67 -> 533.33333 | D68: =+D67 -> 133.33333 | E68: =+C68*$E$8 -> 4.4444444 | F68: =+D68+E68 -> 137.77778 | G68: =+C68-D68 -> 400
B69: 58 | C69: =+G68 -> 400 | D69: =+D68 -> 133.33333 | E69: =+C69*$E$8 -> 3.3333333 | F69: =+D69+E69 -> 136.66667 | G69: =+C69-D69 -> 266.66667
B70: 59 | C70: =+G69 -> 266.66667 | D70: =+D69 -> 133.33333 | E70: =+C70*$E$8 -> 2.2222222 | F70: =+D70+E70 -> 135.55556 | G70: =+C70-D70 -> 133.33333
B71: 60 | C71: =+G70 -> 133.33333 | D71: =+D70 -> 133.33333 | E71: =+C71*$E$8 -> 1.1111111 | F71: =+D71+E71 -> 134.44444 | G71: =+C71-D71 -> 6.8780537e-12 | H71: =SUM(E60:E71) -> 86.666667

Sheet AF
C6: Tipo | D6: ACS
C7: Monto | D7: 3000
C8: Tasa | D8: 0.1 | E8: =+D8/12 -> 0.0083333333
C9: Plazo | D9: 36 | E9: meses | J9: 1 | K9: 2 | L9: 3 | M9: 4 | N9: 5
H10: interes | J10: =+H23 -> 254.16667 | K10: =+H35 -> 154.16667 | L10: =+H47 -> 54.166667 | M10: =+H59 -> -45.833333 | N10: =+H71 -> -145.83333
C11: capital | E11: interes | F11: pago | G11: saldo | I11: capital | J11: =+D12*12 -> 1000 | K11: =+J11 -> 1000 | L11: =+K11 -> 1000 | M11: =+L11 -> 1000 | N11: =+M11 -> 1000
B12: 1 | C12: =+D7 -> 3000 | D12: =+C12/D9 -> 83.333333 | E12: =+C12*$E$8 -> 25 | F12: =+D12+E12 -> 108.33333 | G12: =+C12-D12 -> 2916.6667
B13: 2 | C13: =+G12 -> 2916.6667 | D13: =+D12 -> 83.333333 | E13: =+C13*$E$8 -> 24.305556 | F13: =+D13+E13 -> 107.63889 | G13: =+C13-D13 -> 2833.3333
B14: 3 | C14: =+G13 -> 2833.3333 | D14: =+D13 -> 83.333333 | E14: =+C14*$E$8 -> 23.611111 | F14: =+D14+E14 -> 106.94444 | G14: =+C14-D14 -> 2750
B15: 4 | C15: =+G14 -> 2750 | D15: =+D14 -> 83.333333 | E15: =+C15*$E$8 -> 22.916667 | F15: =+D15+E15 -> 106.25 | G15: =+C15-D15 -> 2666.6667
B16: 5 | C16: =+G15 -> 2666.6667 | D16: =+D15 -> 83.333333 | E16: =+C16*$E$8 -> 22.222222 | F16: =+D16+E16 -> 105.55556 | G16: =+C16-D16 -> 2583.3333
B17: 6 | C17: =+G16 -> 2583.3333 | D17: =+D16 -> 83.333333 | E17: =+C17*$E$8 -> 21.527778 | F17: =+D17+E17 -> 104.86111 | G17: =+C17-D17 -> 2500
B18: 7 | C18: =+G17 -> 2500 | D18: =+D17 -> 83.333333 | E18: =+C18*$E$8 -> 20.833333 | F18: =+D18+E18 -> 104.16667 | G18: =+C18-D18 -> 2416.6667
B19: 8 | C19: =+G18 -> 2416.6667 | D19: =+D18 -> 83.333333 | E19: =+C19*$E$8 -> 20.138889 | F19: =+D19+E19 -> 103.47222 | G19: =+C19-D19 -> 2333.3333
B20: 9 | C20: =+G19 -> 2333.3333 | D20: =+D19 -> 83.333333 | E20: =+C20*$E$8 -> 19.444444 | F20: =+D20+E20 -> 102.77778 | G20: =+C20-D20 -> 2250
B21: 10 | C21: =+G20 -> 2250 | D21: =+D20 -> 83.333333 | E21: =+C21*$E$8 -> 18.75 | F21: =+D21+E21 -> 102.08333 | G21: =+C21-D21 -> 2166.6667
B22: 11 | C22: =+G21 -> 2166.6667 | D22: =+D21 -> 83.333333 | E22: =+C22*$E$8 -> 18.055556 | F22: =+D22+E22 -> 101.38889 | G22: =+C22-D22 -> 2083.3333
B23: 12 | C23: =+G22 -> 2083.3333 | D23: =+D22 -> 83.333333 | E23: =+C23*$E$8 -> 17.361111 | F23: =+D23+E23 -> 100.69444 | G23: =+C23-D23 -> 2000 | H23: =SUM(E12:E23) -> 254.16667
B24: 13 | C24: =+G23 -> 2000 | D24: =+D23 -> 83.333333 | E24: =+C24*$E$8 -> 16.666667 | F24: =+D24+E24 -> 100 | G24: =+C24-D24 -> 1916.6667
B25: 14 | C25: =+G24 -> 1916.6667 | D25: =+D24 -> 83.333333 | E25: =+C25*$E$8 -> 15.972222 | F25: =+D25+E25 -> 99.305556 | G25: =+C25-D25 -> 1833.3333
B26: 15 | C26: =+G25 -> 1833.3333 | D26: =+D25 -> 83.333333 | E26: =+C26*$E$8 -> 15.277778 | F26: =+D26+E26 -> 98.611111 | G26: =+C26-D26 -> 1750
B27: 16 | C27: =+G26 -> 1750 | D27: =+D26 -> 83.333333 | E27: =+C27*$E$8 -> 14.583333 | F27: =+D27+E27 -> 97.916667 | G27: =+C27-D27 -> 1666.6667
B28: 17 | C28: =+G27 -> 1666.6667 | D28: =+D27 -> 83.333333 | E28: =+C28*$E$8 -> 13.888889 | F28: =+D28+E28 -> 97.222222 | G28: =+C28-D28 -> 1583.3333
B29: 18 | C29: =+G28 -> 1583.3333 | D29: =+D28 -> 83.333333 | E29: =+C29*$E$8 -> 13.194444 | F29: =+D29+E29 -> 96.527778 | G29: =+C29-D29 -> 1500
B30: 19 | C30: =+G29 -> 1500 | D30: =+D29 -> 83.333333 | E30: =+C30*$E$8 -> 12.5 | F30: =+D30+E30 -> 95.833333 | G30: =+C30-D30 -> 1416.6667
B31: 20 | C31: =+G30 -> 1416.6667 | D31: =+D30 -> 83.333333 | E31: =+C31*$E$8 -> 11.805556 | F31: =+D31+E31 -> 95.138889 | G31: =+C31-D31 -> 1333.3333
B32: 21 | C32: =+G31 -> 1333.3333 | D32: =+D31 -> 83.333333 | E32: =+C32*$E$8 -> 11.111111 | F32: =+D32+E32 -> 94.444444 | G32: =+C32-D32 -> 1250
B33: 22 | C33: =+G32 -> 1250 | D33: =+D32 -> 83.333333 | E33: =+C33*$E$8 -> 10.416667 | F33: =+D33+E33 -> 93.75 | G33: =+C33-D33 -> 1166.6667
B34: 23 | C34: =+G33 -> 1166.6667 | D34: =+D33 -> 83.333333 | E34: =+C34*$E$8 -> 9.7222222 | F34: =+D34+E34 -> 93.055556 | G34: =+C34-D34 -> 1083.3333
B35: 24 | C35: =+G34 -> 1083.3333 | D35: =+D34 -> 83.333333 | E35: =+C35*$E$8 -> 9.0277778 | F35: =+D35+E35 -> 92.361111 | G35: =+C35-D35 -> 1000 | H35: =SUM(E24:E35) -> 154.16667
B36: 25 | C36: =+G35 -> 1000 | D36: =+D35 -> 83.333333 | E36: =+C36*$E$8 -> 8.3333333 | F36: =+D36+E36 -> 91.666667 | G36: =+C36-D36 -> 916.66667
B37: 26 | C37: =+G36 -> 916.66667 | D37: =+D36 -> 83.333333 | E37: =+C37*$E$8 -> 7.6388889 | F37: =+D37+E37 -> 90.972222 | G37: =+C37-D37 -> 833.33333
B38: 27 | C38: =+G37 -> 833.33333 | D38: =+D37 -> 83.333333 | E38: =+C38*$E$8 -> 6.9444444 | F38: =+D38+E38 -> 90.277778 | G38: =+C38-D38 -> 750
B39: 28 | C39: =+G38 -> 750 | D39: =+D38 -> 83.333333 | E39: =+C39*$E$8 -> 6.25 | F39: =+D39+E39 -> 89.583333 | G39: =+C39-D39 -> 666.66667
B40: 29 | C40: =+G39 -> 666.66667 | D40: =+D39 -> 83.333333 | E40: =+C40*$E$8 -> 5.5555556 | F40: =+D40+E40 -> 88.888889 | G40: =+C40-D40 -> 583.33333
B41: 30 | C41: =+G40 -> 583.33333 | D41: =+D40 -> 83.333333 | E41: =+C41*$E$8 -> 4.8611111 | F41: =+D41+E41 -> 88.194444 | G41: =+C41-D41 -> 500
B42: 31 | C42: =+G41 -> 500 | D42: =+D41 -> 83.333333 | E42: =+C42*$E$8 -> 4.1666667 | F42: =+D42+E42 -> 87.5 | G42: =+C42-D42 -> 416.66667
B43: 32 | C43: =+G42 -> 416.66667 | D43: =+D42 -> 83.333333 | E43: =+C43*$E$8 -> 3.4722222 | F43: =+D43+E43 -> 86.805556 | G43: =+C43-D43 -> 333.33333
B44: 33 | C44: =+G43 -> 333.33333 | D44: =+D43 -> 83.333333 | E44: =+C44*$E$8 -> 2.7777778 | F44: =+D44+E44 -> 86.111111 | G44: =+C44-D44 -> 250
B45: 34 | C45: =+G44 -> 250 | D45: =+D44 -> 83.333333 | E45: =+C45*$E$8 -> 2.0833333 | F45: =+D45+E45 -> 85.416667 | G45: =+C45-D45 -> 166.66667
B46: 35 | C46: =+G45 -> 166.66667 | D46: =+D45 -> 83.333333 | E46: =+C46*$E$8 -> 1.3888889 | F46: =+D46+E46 -> 84.722222 | G46: =+C46-D46 -> 83.333333
B47: 36 | C47: =+G46 -> 83.333333 | D47: =+D46 -> 83.333333 | E47: =+C47*$E$8 -> 0.69444444 | F47: =+D47+E47 -> 84.027778 | G47: =+C47-D47 -> -8.8107299e-13 | H47: =SUM(E36:E47) -> 54.166667
B48: 37 | C48: =+G47 -> -8.8107299e-13 | D48: =+D47 -> 83.333333 | E48: =+C48*$E$8 -> -7.3422749e-15 | F48: =+D48+E48 -> 83.333333 | G48: =+C48-D48 -> -83.333333
B49: 38 | C49: =+G48 -> -83.333333 | D49: =+D48 -> 83.333333 | E49: =+C49*$E$8 -> -0.69444444 | F49: =+D49+E49 -> 82.638889 | G49: =+C49-D49 -> -166.66667
B50: 39 | C50: =+G49 -> -166.66667 | D50: =+D49 -> 83.333333 | E50: =+C50*$E$8 -> -1.3888889 | F50: =+D50+E50 -> 81.944444 | G50: =+C50-D50 -> -250
B51: 40 | C51: =+G50 -> -250 | D51: =+D50 -> 83.333333 | E51: =+C51*$E$8 -> -2.0833333 | F51: =+D51+E51 -> 81.25 | G51: =+C51-D51 -> -333.33333
B52: 41 | C52: =+G51 -> -333.33333 | D52: =+D51 -> 83.333333 | E52: =+C52*$E$8 -> -2.7777778 | F52: =+D52+E52 -> 80.555556 | G52: =+C52-D52 -> -416.66667
B53: 42 | C53: =+G52 -> -416.66667 | D53: =+D52 -> 83.333333 | E53: =+C53*$E$8 -> -3.4722222 | F53: =+D53+E53 -> 79.861111 | G53: =+C53-D53 -> -500
B54: 43 | C54: =+G53 -> -500 | D54: =+D53 -> 83.333333 | E54: =+C54*$E$8 -> -4.1666667 | F54: =+D54+E54 -> 79.166667 | G54: =+C54-D54 -> -583.33333
B55: 44 | C55: =+G54 -> -583.33333 | D55: =+D54 -> 83.333333 | E55: =+C55*$E$8 -> -4.8611111 | F55: =+D55+E55 -> 78.472222 | G55: =+C55-D55 -> -666.66667
B56: 45 | C56: =+G55 -> -666.66667 | D56: =+D55 -> 83.333333 | E56: =+C56*$E$8 -> -5.5555556 | F56: =+D56+E56 -> 77.777778 | G56: =+C56-D56 -> -750
B57: 46 | C57: =+G56 -> -750 | D57: =+D56 -> 83.333333 | E57: =+C57*$E$8 -> -6.25 | F57: =+D57+E57 -> 77.083333 | G57: =+C57-D57 -> -833.33333
B58: 47 | C58: =+G57 -> -833.33333 | D58: =+D57 -> 83.333333 | E58: =+C58*$E$8 -> -6.9444444 | F58: =+D58+E58 -> 76.388889 | G58: =+C58-D58 -> -916.66667
B59: 48 | C59: =+G58 -> -916.66667 | D59: =+D58 -> 83.333333 | E59: =+C59*$E$8 -> -7.6388889 | F59: =+D59+E59 -> 75.694444 | G59: =+C59-D59 -> -1000 | H59: =SUM(E48:E59) -> -45.833333
B60: 49 | C60: =+G59 -> -1000 | D60: =+D59 -> 83.333333 | E60: =+C60*$E$8 -> -8.3333333 | F60: =+D60+E60 -> 75 | G60: =+C60-D60 -> -1083.3333
B61: 50 | C61: =+G60 -> -1083.3333 | D61: =+D60 -> 83.333333 | E61: =+C61*$E$8 -> -9.0277778 | F61: =+D61+E61 -> 74.305556 | G61: =+C61-D61 -> -1166.6667
B62: 51 | C62: =+G61 -> -1166.6667 | D62: =+D61 -> 83.333333 | E62: =+C62*$E$8 -> -9.7222222 | F62: =+D62+E62 -> 73.611111 | G62: =+C62-D62 -> -1250
B63: 52 | C63: =+G62 -> -1250 | D63: =+D62 -> 83.333333 | E63: =+C63*$E$8 -> -10.416667 | F63: =+D63+E63 -> 72.916667 | G63: =+C63-D63 -> -1333.3333
B64: 53 | C64: =+G63 -> -1333.3333 | D64: =+D63 -> 83.333333 | E64: =+C64*$E$8 -> -11.111111 | F64: =+D64+E64 -> 72.222222 | G64: =+C64-D64 -> -1416.6667
B65: 54 | C65: =+G64 -> -1416.6667 | D65: =+D64 -> 83.333333 | E65: =+C65*$E$8 -> -11.805556 | F65: =+D65+E65 -> 71.527778 | G65: =+C65-D65 -> -1500
B66: 55 | C66: =+G65 -> -1500 | D66: =+D65 -> 83.333333 | E66: =+C66*$E$8 -> -12.5 | F66: =+D66+E66 -> 70.833333 | G66: =+C66-D66 -> -1583.3333
B67: 56 | C67: =+G66 -> -1583.3333 | D67: =+D66 -> 83.333333 | E67: =+C67*$E$8 -> -13.194444 | F67: =+D67+E67 -> 70.138889 | G67: =+C67-D67 -> -1666.6667
B68: 57 | C68: =+G67 -> -1666.6667 | D68: =+D67 -> 83.333333 | E68: =+C68*$E$8 -> -13.888889 | F68: =+D68+E68 -> 69.444444 | G68: =+C68-D68 -> -1750
B69: 58 | C69: =+G68 -> -1750 | D69: =+D68 -> 83.333333 | E69: =+C69*$E$8 -> -14.583333 | F69: =+D69+E69 -> 68.75 | G69: =+C69-D69 -> -1833.3333
B70: 59 | C70: =+G69 -> -1833.3333 | D70: =+D69 -> 83.333333 | E70: =+C70*$E$8 -> -15.277778 | F70: =+D70+E70 -> 68.055556 | G70: =+C70-D70 -> -1916.6667
B71: 60 | C71: =+G70 -> -1916.6667 | D71: =+D70 -> 83.333333 | E71: =+C71*$E$8 -> -15.972222 | F71: =+D71+E71 -> 67.361111 | G71: =+C71-D71 -> -2000 | H71: =SUM(E60:E71) -> -145.83333

Sheet Sheet1

Sheet TEASER
B1: TEASER COMERCIAL | F1: 46126 | H1: GESTION FINANCIERA | L1: GOOGLE | M1: =IF(M3="N/D","INFO NO DISPONIBLE",IF(M3="Si","LIMITADO","VIABLE")) -> VIABLE | P1: FLUJOS (en pesos) | U1: #
F2: FECHA | H2: AFILIADO | I2: EJECUTIVO | U2: #
B3: CLIENTE: | D3: AUTOMOTRIZ TOY DEL SURESTE SA DE CV | H3: Tipo de Crédito | I3: Credito Simple | K3: Arrendamiento | L3: ¿Aparecen noticias negativas en la primera página? | M3: No | P3: BANCO 1 | Q3: Resumen 3 bancos | U3: #
H4: Plazo | I4: 0 | K4: Cuenta Corriente | Q4: Depósitos (pesos) | R4: Saldo Prom. (pesos) | U4: #
B5: INFORMACIÓN DE LA EMPRESA | H5: Monto (miles de pesos) | I5: 0 | K5: Simple | P5: =Bancos!L16 -> 45901 | Q5: =Bancos!M16 -> 0 | R5: =Bancos!N16 -> 0 | T5: =IF(Q5>0.1,1,0) -> 0 | U5: #
B6: Sector | D6: Otros | H6: Tasa | I6: 0 | K6: Tasa "0" | L6: Tasa "0" | O6: Tasa "0" | P6: =Bancos!L17 -> 45931 | Q6: =Bancos!M17 -> 0 | R6: =Bancos!N17 -> 0 | T6: =IF(Q6>0.1,1,0) -> 0 | U6: #
B7: Actividad | H7: ULTIMO AÑO FISCAL | L7: ULTIMO PARCIAL | P7: =Bancos!L18 -> 45962 | Q7: =Bancos!M18 -> 0 | R7: =Bancos!N18 -> 0 | T7: =IF(Q7>0.1,1,0) -> 0 | U7: #
B8: CARTERA DE CLIENTES | I8: Miles de pesos | M8: Miles de pesos | P8: =Bancos!L19 -> 45992 | Q8: =Bancos!M19 -> 0 | R8: =Bancos!N19 -> 0 | T8: =IF(Q8>0.1,1,0) -> 0 | U8: #
H9: Ventas anuales | I9: =+DATOS!O6 -> 0 | K9: SI | L9: Ventas anuales | M9: =DATOS!U6 -> 0 | P9: =Bancos!L20 -> 46023 | Q9: =Bancos!M20 -> 0 | R9: =Bancos!N20 -> 0 | T9: =IF(Q9>0.1,1,0) -> 0 | U9: #
B10: INFORMACIÓN GENERAL DE LA GARANTÍA | H10: Activos Totales (AT) | I10: =+DATOS!E13 -> 0 | K10: NO | L10: Activos Totales (AT) | M10: =DATOS!I13 -> 0 | O10: NO | P10: =Bancos!L21 -> 46054 | Q10: =Bancos!M21 -> 0 | R10: =Bancos!N21 -> 0 | T10: =IF(Q10>0.1,1,0) -> 0 | U10: #
B11: Estado donde se encuentra | E11: Otros | H11: Pasivos Totales (PT) | 4 años | I11: =+DATOS!E23 -> 0 | J11: =(I11-DATOS!E25)/4 -> 0 | L11: Pasivos Totales (PT) / 4 años | M11: =DATOS!I23 -> 0 | N11: =(M11-DATOS!I25)/4 -> 0 | P11: =Bancos!L22 -> 46082 | Q11: =Bancos!M22 -> 0 | R11: =Bancos!N22 -> 0 | S11: =IF(R11>0.1,1,0) -> 0 | T11: =IF(Q11>0.1,1,0) -> 0 | U11: #
B12: Está en la capital o centro turístico? | E12: No | H12: Capital Contable (CC) | I12: =DATOS!E29 -> 0 | L12: Capital Contable (CC) | M12: =DATOS!I29 -> 0 | P12: Total Bank 1 | Q12: =IFERROR(SUM(Q5:Q11)/T12,0) -> 0 | R12: =IFERROR(SUM(R5:R11)/T12,0) -> 0 | S12: =SUM(S5:S11) -> 0 | T12: =SUM(T5:T11) -> 0 | U12: #
B13: Tipo de propiedad | H13: EBITDA | I13: =DATOS!O8+DATOS!O11 -> 0 | L13: EBITDA | M13: =DATOS!U8+DATOS!U11 -> 0 | U13: #
B14: Valor estimado (miles de pesos) | H14: Pago Anual | I14: =PMT(I6/12,I4,-I5)*12 -> #NUM! | L14: Pago Anual | M14: =PMT(I6/12,I4,-I5)*12 -> #NUM! | P14: BANCO 2 | U14: #
B15: Aforo | C15: =IFERROR(E14/I5,"N/D") -> N/D | D15: Aforo requerido | F15: =VLOOKUP(E13,Input!$B$77:$C$81,2,0) -> #N/A | Q15: Depósitos (pesos) | R15: Saldo Prom. (pesos) | U15: #
B16: Otra información relevante | D16: (Tamaño, ubicación detallada, facilidad de acceso, uso) | H16: Concepto | I16: Condición | J16: Resultado | L16: Concepto | M16: Condición | N16: Resultado | P16: =Bancos!L16 -> 45901 | Q16: 0 | R16: 0 | S16: =IF(R16>0.1,1,0) -> 0 | T16: =IF(Q16>0.1,1,0) -> 0 | U16: #
H17: Turns of EBITDA | I17: < 4 | J17: =(I14*(I4/12)+I11-DATOS!E25)/(I13+pagos_arrendamiento_mensual_full_year*12) -> #NUM! | K17: =IFERROR(IF(J17<4,0.5,0),0) -> 0 | L17: Turns of EBITDA | M17: < 4 | N17: =(M14*(I4/12)+M11-DATOS!$I$25)/(M13+pagos_arrendamiento_mensual_full_year*12) -> #NUM! | O17: =IF(AND(ISNUMBER(N17),N17<4),0.5,0) -> #NUM! | P17: =Bancos!L17 -> 45931 | Q17: 0 | R17: 0 | S17: =IF(R17>0.1,1,0) -> 0 | T17: =IF(Q17>0.1,1,0) -> 0 | U17: #
B18: =IF(OR(E11="N/D",E12="N/D",E13="N/D",E14<0,ISBLANK(E14)),"GARANTIA: INFORMACION INCOMPLETA",IF(E11<>"Otros",IF(E12="Si",IF(C15>F15,"GARANTIA: VIABLE","GARANTIA: LIMITADO"),"GARANTIA: LIMITADO"),IF(C15>F15,"GARANTIA: VIABLE","GARANTIA: LIMITADO"))) -> GARANTIA: INFORMACION INCOMPLETA | H18: Apalancamiento (PT / AT) | I18: < 70% | J18: =I11/I10 -> #DIV/0! | K18: =IF(J18<70%,1,0) -> #DIV/0! | L18: Apalancamiento (PT / AT) | M18: < 70% | N18: =M11/M10 -> #DIV/0! | O18: =IF(AND(ISNUMBER(N18),N18<70%),1,0) -> #DIV/0! | P18: =Bancos!L18 -> 45962 | Q18: 0 | R18: 0 | S18: =IF(R18>0.1,1,0) -> 0 | T18: =IF(Q18>0.1,1,0) -> 0 | U18: #
H19: Capital de trabajo neto | I19: Positivo | J19: =+DATOS!E7-DATOS!E17 -> 0 | K19: =IF(J19>1,1,0) -> 0 | L19: Capital de trabajo neto | M19: Positivo | N19: =+DATOS!I7-DATOS!I17 -> 0 | O19: =IF(AND(ISNUMBER(N19),N19>1),1,0) -> 0 | P19: =Bancos!L19 -> 45992 | Q19: 0 | R19: 0 | S19: =IF(R19>0.1,1,0) -> 0 | T19: =IF(Q19>0.1,1,0) -> 0 | U19: #
B20: DATOS DEL PROPIETARIO | H20: Cobertura de Renta Anual CS | I20: > 1.2 | J20: =+(I13+(pagos_arrendamiento_mensual_full_year*12))/((J11+I14)+pagos_arrendamiento_mensual_full_year*12) -> #NUM! | K20: =IFERROR(IF($I$3="Credito Simple",IF(J20>=1.2,1.5,0),IF(J20>=1.35,1.5,0)),0) -> 0 | L20: Cobertura de Renta Anual* | M20: > 1.2 | N20: =+(M13+pagos_arrendamiento_mensual_full_year*12)/((N11+M14)+pagos_arrendamiento_mensual_full_year*12) -> #NUM! | O20: =IF($I$3="Credito Simple",IF(N20>1.2,1.5,0),IF(N20>1.35,1.5,0)) -> #NUM! | P20: =Bancos!L20 -> 46023 | Q20: 0 | R20: 0 | S20: =IF(R20>0.1,1,0) -> 0 | T20: =IF(Q20>0.1,1,0) -> 0 | U20: #
B21: ¿Es un tercero que no tiene relación con el negocio? | E21: N/D | J21: =SUM(K17:K20)+DATOS!Q30 -> #DIV/0! | N21: =SUM(O17:O20)+DATOS!Q30 -> #NUM! | P21: =Bancos!L21 -> 46054 | Q21: 0 | R21: 0 | S21: =IF(R21>0.1,1,0) -> 0 | T21: =IF(Q21>0.1,1,0) -> 0 | U21: #
H22: =IF(DATOS!E13=0,"INFORMACION NO DISPONIBLE",IFERROR(IF(I12<0,"ULTIMO AÑO FISCAL: LIMITADO",IF(OR($J$21<=2,J20<1),"ULTIMO AÑO FISCAL: LIMITADO","ULTIMO AÑO FISCAL: VIABLE")),"ULTIMO AÑO FISCAL: LIMITADO")) -> INFORMACION NO DISPONIBLE | K22: =IF(J23<60,1,0) -> 1 | L22: =IF(DATOS!I13=0,"INFORMACION NO DISPONIBLE",IFERROR(IF(M12<0,"ULTIMO AÑO FISCAL: LIMITADO",IF(OR($N$21<=2,N20<1),"ULTIMO AÑO FISCAL: LIMITADO","ULTIMO AÑO FISCAL: VIABLE")),"ULTIMO AÑO FISCAL: LIMITADO")) -> INFORMACION NO DISPONIBLE | O22: =IF(N23<60,1,0) -> 1 | P22: =Bancos!L22 -> 46082 | Q22: 0 | R22: 0 | S22: =IF(R22>0.1,1,0) -> 0 | T22: =IF(Q22>0.1,1,0) -> 0 | U22: #
B23: ¿Está casado por sociedad conyugal? | E23: N/D | K23: =IF(J24="NO",1,0) -> 0 | O23: =IF(N24="NO",1,0) -> 0 | P23: Total Bank 2 | Q23: =IFERROR(SUM(Q16:Q22)/T23,0) -> 0 | R23: =IFERROR(SUM(R16:R22)/S23,0) -> 0 | S23: =SUM(S16:S22) -> 0 | T23: =SUM(T16:T22) -> 0 | U23: #
B24: Si está casado por conyugal, puede firmar el cónyuge? | E24: N/D | P24: Total ambos bancos | Q24: =+Q12+Q23 -> 0 | R24: =+R12+R23 -> 0
B25: =IF(TEASER!E21="Si","PROPIETARIO: LIMITADO",IF(OR(E21="N/D"),"PROPIETARIO: INFO INCOMPLETA",IF(E23="No","PROPIETARIO: VIABLE",IF(E24="N/D","PROPIETARIO: INFO INCOMPLETA",IF(E24="No puede firmar","PROPIETARIO: LIMITADO","PROPIETARIO: VIABLE"))))) -> PROPIETARIO: INFO INCOMPLETA | H25: Δ reciente de ventas | I25: =IF(M9=0,"INFORMACION RECIENTE DE VENTAS NO DISPONIBLE",IF($H$26<0,"EVOLUCION RECIENTE DE VENTAS: LIMITADO","EVOLUCION RECIENTE DE VENTAS: VIABLE")) -> INFORMACION RECIENTE DE VENTAS NO DISPONIBLE | U25: #
H26: =M9/I9-1 -> #DIV/0! | P26: Bank Flow Coverage | R26: =(R24/1000)/((N11+M14)/12) -> #NUM! | U26: #
P27: Ratio Ventas / Banco | R27: =IF(M9=0,"N/D",(M9/12*1000)/Q24) -> N/D | U27: #
B28: NECESIDAD DE CRÉDITO Y DESTINO | U28: #
H29: Δ histórica de ventas | I29: =IF(H30="N/A","INFORMACION HISTORICA NO DISPONIBLE",IF(H30>=66%,"EVOLUCIÓN HISTÓRICA DE VENTAS: VIABLE","EVOLUCIÓN HISTÓRICA DE VENTAS: LIMITADO")) -> EVOLUCIÓN HISTÓRICA DE VENTAS: LIMITADO | P29: =IFERROR(IF($R$26<1.2,"COBERTURA BANCARIA: LIMITADO","COBERTURA BANCARIA: VIABLE"),"INFO NO DISPONIBLE") -> INFO NO DISPONIBLE | U29: #
H30: =IF(MAX($B$35:$F$35)=5,((C36+D36+E36+F36)/4),IF(MAX($B$35:$F$35)=4,((D36+E36+F36)/3),IF(MAX($B$35:$F$35)=3,((E36+F36)/2),IF(MAX($B$35:$F$35)=2,((C36+D36+E36+F36)/1),"N/A")))) -> 0 | U30: #
U31: #
B32: INGRESOS HISTÓRICOS (en $ miles) | H32: ¿LE PRESTARÍAS TU PROPIO DINERO? | U32: #
B33: =C33-1 -> 2022 | C33: =D33-1 -> 2023 | D33: =E33-1 -> 2024 | E33: =DATOS!O4 -> 2025 | F33: =DATOS!S4 -> Febrero 2026 | P33: =IF(R27="N/D","INFO NO DISPONIBLE",IFERROR(IF(R27>=2,"INGRESOS VS. BANCO: LIMITADO", "INGRESOS VS. BANCO: VIABLE"),"ERROR")) -> INFO NO DISPONIBLE | U33: #
E34: =+DATOS!O6 -> 0 | F34: =+DATOS!S6 -> 0 | H34: N/D | U34: #
B35: =IF(ISNUMBER(B34),5,0) -> 0 | C35: =IF(ISNUMBER(C34),4,0) -> 0 | D35: =IF(ISNUMBER(D34),3,0) -> 0 | E35: =IF(ISNUMBER(E34),2,0) -> 2 | F35: =IF(ISNUMBER(F34),1,0) -> 1 | U35: #
C36: =IF(C34-B34>0,1,0) -> 0 | D36: =IF(D34-C34>0,1,0) -> 0 | E36: =IF(E34-D34>0,1,0) -> 0 | F36: =IF($F$34*(12/DATOS!$V$4)-E34>0,1,0) -> 0
A37: # # # # # # # # # # # # # # # # # # # # # # # # # # # # # # # # # # # # # # # # # # # # # # # # # # # # # # | B37: # # # # # # # # # # # # # # # # # # # # # # # # # # # # # # # # # # # # # # # # # # # # # # # # # # # # # # | C37: # # # # # # # # # # # # # # # # # # # # # # # # # # # # # # # # # # # # # # # # # # # # # # # # # # # # # # | D37: # # # # # # # # # # # # # # # # # # # # # # # # # # # # # # # # # # # # # # # # # # # # # # # # # # # # # # | E37: # # # # # # # # # # # # # # # # # # # # # # # # # # # # # # # # # # # # # # # # # # # # # # # # # # # # # # | F37: # # # # # # # # # # # # # # # # # # # # # # # # # # # # # # # # # # # # # # # # # # # # # # # # # # # # # # | G37: # # # # # # # # # # # # # # # # # # # # # # # # # # # # # # # # # # # # # # # # # # # # # # # # # # # # # # | H37: # # # # # # # # # # # # # # # # # # # # # # # # # # # # # # # # # # # # # # # # # # # # # # # # # # # # # # | I37: # # # # # # # # # # # # # # # # # # # # # # # # # # # # # # # # # # # # # # # # # # # # # # # # # # # # # # | J37: # # # # # # # # # # # # # # # # # # # # # # # # # # # # # # # # # # # # # # # # # # # # # # # # # # # # # # | K37: # # # # # # # # # # # # # # # # # # # # # # # # # # # # # # # # # # # # # # # # # # # # # # # # # # # # # # | L37: # # # # # # # # # # # # # # # # # # # # # # # # # # # # # # # # # # # # # # # # # # # # # # # # # # # # # # | M37: # # # # # # # # # # # # # # # # # # # # # # # # # # # # # # # # # # # # # # # # # # # # # # # # # # # # # # | N37: # # # # # # # # # # # # # # # # # # # # # # # # # # # # # # # # # # # # # # # # # # # # # # # # # # # # # # | O37: # # # # # # # # # # # # # # # # # # # # # # # # # # # # # # # # # # # # # # # # # # # # # # # # # # # # # # | P37: # # # # # # # # # # # # # # # # # # # # # # # # # # # # # # # # # # # # # # # # # # # # # # # # # # # # # # | Q37: # # # # # # # # # # # # # # # # # # # # # # # # # # # # # # # # # # # # # # # # # # # # # # # # # # # # # # | R37: # # # # # # # # # # # # # # # # # # # # # # # # # # # # # # # # # # # # # # # # # # # # # # # # # # # # # # | S37: # # # # # # # # # # # # # # # # # # # # # # # # # # # # # # # # # # # # # # # # # # # # # # # # # # # # # # | U37: #

Sheet DATOS
B2: BALANCE GENERAL | L2: ESTADO DE RESULTADOS
E3: Último año completo | I3: Último parcial disponible | O3: Último año completo | S3: Último parcial disponible | U3: =VLOOKUP($S$4,Input!$B$24:$C$35,2,0) -> 2
D4: Periódo | E4: 2025 | G4: % | I4: Febrero 2026 | N4: Periódo | O4: =E4 -> 2025 | Q4: % | S4: =I4 -> Febrero 2026 | U4: Último parcial anualizado | V4: =IF(S4=Input!B24,Input!C24,IF(S4=Input!B25,Input!C25,IF(S4=Input!B26,3,IF(S4=Input!B27,Input!C27,IF(S4=Input!B28,Input!C28,IF(S4=Input!B29,Input!C29,IF(S4=Input!B30,Input!C30,IF(S4=Input!B31,Input!C31,IF(S4=Input!B32,Input!C32,IF(S4=Input!B33,Input!C33,IF(S4=Input!B34,Input!C34,IF(S4=Input!B35,Input!C35)))))))))))) -> 2
O5: CIFRAS EN MILES
C6: ACTIVO | E6: CIFRAS EN MILES | M6: VENTAS | O6: =Input!K12/1000 -> 0 | Q6: =IF(O$6=0,"",O6/O$6) | S6: =Input!L12/1000 -> 0 | U6: =+(S6/$V$4)*12 -> 0
D7: TOTAL ACTIVOS CIRCULANTES | E7: =Input!K3/1000 -> 0 | G7: =IF(E$13=0,"",E7/E$13) | I7: =Input!L3/1000 -> 0
M8: UTILIDAD DE OPERACIÓN (Antes de impuestos y gastos financieros | O8: =Input!K13/1000 -> 0 | Q8: =IF(O$6=0,"",O8/O$6) | S8: =Input!L13/1000 -> 0 | U8: =+(S8/$V$4)*12 -> 0
D9: TOTAL ACTIVOS FIJOS | E9: =Input!K4/1000 -> 0 | G9: =IF(E$13=0,"",E9/E$13) | I9: =Input!L4/1000 -> 0
D11: TOTAL ACTIVOS DIFERIDOS | E11: =Input!K5/1000 -> 0 | G11: =IF(E$13=0,"",E11/E$13) | I11: =Input!L5/1000 -> 0 | M11: DEPRECIACIÓN (edo. de resúltados) | O11: =Input!K14/1000 -> 0 | S11: =Input!L14/1000 -> 0 | U11: =+(S11/$V$4)*12 -> 0
D13: ACTIVO TOTAL | E13: =+E11+E9+E7 -> 0 | G13: =IF(E$31=0,"",E13/E$31) | I13: =+I11+I9+I7 -> 0 | M13: Pasivo Arrendamiento ( MENSUAL - OJO: NO DEL BALANCE)
I15: =IF(OR(E13=I13,E23=I23),"Error: ultimo parcial no puede ser igual al año completo","") -> Error: ultimo parcial no puede ser igual al año completo
C16: PASIVO
D17: TOTAL PASIVO NO FINANCIERO | E17: =Input!K6/1000 -> 0 | G17: =IF(E$31=0,"",E17/E$31) | I17: =Input!L6/1000 -> 0 | O17: =IF(OR(ISBLANK(O6),ISBLANK(O8),ISBLANK(depreciacion_PL_full_year)),"N/D","") | S17: =IF(OR(ISBLANK(S6),ISBLANK(S8),ISBLANK(depreciacion_PL_last_partial)),"N/D","")
D19: TOTAL PASIVO FINANCIERO | E19: =Input!K7/1000 -> 0 | G19: =IF(E$31=0,"",E19/E$31) | I19: =Input!L7/1000 -> 0
D21: TOTAL PASIVO DIFERIDO | E21: =Input!K8/1000 -> 0 | G21: =IF(E$31=0,"",E21/E$31) | I21: =Input!L8/1000 -> 0
L22: BURÓ DE CRÉDITO
D23: PASIVO TOTAL | E23: =SUM(E17,E19,E21) -> 0 | G23: =IF(E$31=0,"",E23/E$31) | I23: =SUM(I17,I19,I21) -> 0
Q24: Rating
D25: CXP Proveedores | E25: =Input!K9/1000 -> 0 | I25: =Input!L9/1000 -> 0
M26: Máximo de días de atraso | O26: N/D | Q26: =IF($O$26="60 o mas",-0.5,0) -> 0
C28: CAPITAL | M28: Claves de prevención (quita, quebranto, etc.) | O28: N/D | Q28: =IF($O$28="Si",-0.5,0) -> 0
D29: CAPITAL CONTABLE TOTAL | E29: =Input!K10/1000 -> 0 | G29: =IF(E$31=0,"",E29/E$31) | I29: =Input!L10/1000 -> 0 | Q29: =SUM($Q$26,$Q$28) -> 0
Q30: =SUM(Q26,Q28) -> 0
D31: PASIVO + CAPITAL CONTABLE | E31: =+E29+E23 -> 0 | G31: =IF(E$31=0,"",E31/E$31) | I31: =+I29+I23 -> 0
E33: =EXACT(E31,E13) -> TRUE | I33: =EXACT(I31,I13) -> TRUE
D34: Diferencia
E35: =+E13-E23-E29 -> 0

Sheet Bancos
B2: BANCO 1 | C2: 0 | G2: BANCO 2 | H2: 0 | L2: BANCO 3 | M2: 0 | Q2: BANCO 4 | R2: 0 | U2: BANCO 5 | V2: 0 | Z2: BANCO 6 | AA2: 0 | AE2: BANCO 7 | AF2: 0 | AJ2: BANCO 8 | AK2: 0 | AO2: BANCO 9 | AP2: 0 | AT2: BANCO 10 | AU2: 0 | AY2: BANCO 11 | AZ2: 0 | BD2: BANCO 12 | BE2: 0 | BI2: BANCO 13 | BJ2: 0 | BN2: BANCO 14 | BO2: 0
C3: Depósitos (pesos) | D3: Saldo Prom. (pesos) | H3: Depósitos (pesos) | I3: Saldo Prom. (pesos) | M3: Depósitos (pesos) | N3: Saldo Prom. (pesos) | R3: Depósitos (pesos) | S3: Saldo Prom. (pesos) | V3: Depósitos (pesos) | W3: Saldo Prom. (pesos) | AA3: Depósitos (pesos) | AB3: Saldo Prom. (pesos) | AF3: Depósitos (pesos) | AG3: Saldo Prom. (pesos) | AK3: Depósitos (pesos) | AL3: Saldo Prom. (pesos) | AP3: Depósitos (pesos) | AQ3: Saldo Prom. (pesos) | AU3: Depósitos (pesos) | AV3: Saldo Prom. (pesos) | AZ3: Depósitos (pesos) | BA3: Saldo Prom. (pesos) | BE3: Depósitos (pesos) | BF3: Saldo Prom. (pesos) | BJ3: Depósitos (pesos) | BK3: Saldo Prom. (pesos) | BO3: Depósitos (pesos) | BP3: Saldo Prom. (pesos)
B4: 45901 | C4: 0 | D4: 0 | G4: =B4 -> 45901 | H4: 0 | I4: 0 | L4: =B4 -> 45901 | M4: 0 | N4: 0 | Q4: =B4 -> 45901 | R4: 0 | S4: 0 | U4: =B4 -> 45901 | V4: 0 | W4: 0 | Z4: =B4 -> 45901 | AA4: 0 | AB4: 0 | AE4: =B4 -> 45901 | AF4: 0 | AG4: 0 | AJ4: =B4 -> 45901 | AK4: 0 | AL4: 0 | AO4: =B4 -> 45901 | AP4: 0 | AQ4: 0 | AT4: =B4 -> 45901 | AU4: 0 | AV4: 0 | AY4: =AT4 -> 45901 | AZ4: 0 | BA4: 0 | BD4: 45901 | BE4: 0 | BF4: 0 | BI4: =BD4 -> 45901 | BJ4: 0 | BK4: 0 | BN4: =BI4 -> 45901 | BO4: 0 | BP4: 0
B5: 45931 | C5: 0 | D5: 0 | G5: =B5 -> 45931 | H5: 0 | I5: 0 | L5: =B5 -> 45931 | M5: 0 | N5: 0 | Q5: =B5 -> 45931 | R5: 0 | S5: 0 | U5: =B5 -> 45931 | V5: 0 | W5: 0 | Z5: =B5 -> 45931 | AA5: 0 | AB5: 0 | AE5: =B5 -> 45931 | AF5: 0 | AG5: 0 | AJ5: =B5 -> 45931 | AK5: 0 | AL5: 0 | AO5: =B5 -> 45931 | AP5: 0 | AQ5: 0 | AT5: =B5 -> 45931 | AU5: 0 | AV5: 0 | AY5: =AT5 -> 45931 | AZ5: 0 | BA5: 0 | BD5: 45931 | BE5: 0 | BF5: 0 | BI5: =BD5 -> 45931 | BJ5: 0 | BK5: 0 | BN5: =BI5 -> 45931 | BO5: 0 | BP5: 0
B6: 45962 | C6: 0 | D6: 0 | G6: =B6 -> 45962 | H6: 0 | I6: 0 | L6: =B6 -> 45962 | M6: 0 | N6: 0 | Q6: =B6 -> 45962 | R6: 0 | S6: 0 | U6: =B6 -> 45962 | V6: 0 | W6: 0 | Z6: =B6 -> 45962 | AA6: 0 | AB6: 0 | AE6: =B6 -> 45962 | AF6: 0 | AG6: 0 | AJ6: =B6 -> 45962 | AK6: 0 | AL6: 0 | AO6: =B6 -> 45962 | AP6: 0 | AQ6: 0 | AT6: =B6 -> 45962 | AU6: 0 | AV6: 0 | AY6: =AT6 -> 45962 | AZ6: 0 | BA6: 0 | BD6: 45962 | BE6: 0 | BF6: 0 | BI6: =BD6 -> 45962 | BJ6: 0 | BK6: 0 | BN6: =BI6 -> 45962 | BO6: 0 | BP6: 0
B7: 45992 | C7: 0 | D7: 0 | G7: =B7 -> 45992 | H7: 0 | I7: 0 | L7: =B7 -> 45992 | M7: 0 | N7: 0 | Q7: =B7 -> 45992 | R7: 0 | S7: 0 | U7: =B7 -> 45992 | V7: 0 | W7: 0 | Z7: =B7 -> 45992 | AA7: 0 | AB7: 0 | AE7: =B7 -> 45992 | AF7: 0 | AG7: 0 | AJ7: =B7 -> 45992 | AK7: 0 | AL7: 0 | AO7: =B7 -> 45992 | AP7: 0 | AQ7: 0 | AT7: =B7 -> 45992 | AU7: 0 | AV7: 0 | AY7: =AT7 -> 45992 | AZ7: 0 | BA7: 0 | BD7: 45992 | BE7: 0 | BF7: 0 | BI7: =BD7 -> 45992 | BJ7: 0 | BK7: 0 | BN7: =BI7 -> 45992 | BO7: 0 | BP7: 0
B8: 46023 | C8: 0 | D8: 0 | G8: =B8 -> 46023 | H8: 0 | I8: 0 | L8: =B8 -> 46023 | M8: 0 | N8: 0 | Q8: =B8 -> 46023 | R8: 0 | S8: 0 | U8: =B8 -> 46023 | V8: 0 | W8: 0 | Z8: =B8 -> 46023 | AA8: 0 | AB8: 0 | AE8: =B8 -> 46023 | AF8: 0 | AG8: 0 | AJ8: =B8 -> 46023 | AK8: 0 | AL8: 0 | AO8: =B8 -> 46023 | AP8: 0 | AQ8: 0 | AT8: =B8 -> 46023 | AU8: 0 | AV8: 0 | AY8: =AT8 -> 46023 | AZ8: 0 | BA8: 0 | BD8: 46023 | BE8: 0 | BF8: 0 | BI8: =BD8 -> 46023 | BJ8: 0 | BK8: 0 | BN8: =BI8 -> 46023 | BO8: 0 | BP8: 0
B9: 46054 | C9: 0 | D9: 0 | G9: =B9 -> 46054 | H9: 0 | I9: 0 | L9: =B9 -> 46054 | M9: 0 | N9: 0 | Q9: =B9 -> 46054 | R9: 0 | S9: 0 | U9: =B9 -> 46054 | V9: 0 | W9: 0 | Z9: =B9 -> 46054 | AA9: 0 | AB9: 0 | AE9: =B9 -> 46054 | AF9: 0 | AG9: 0 | AJ9: =B9 -> 46054 | AK9: 0 | AL9: 0 | AO9: =B9 -> 46054 | AP9: 0 | AQ9: 0 | AT9: =B9 -> 46054 | AU9: 0 | AV9: 0 | AY9: =AT9 -> 46054 | AZ9: 0 | BA9: 0 | BD9: 46054 | BE9: 0 | BF9: 0 | BI9: =BD9 -> 46054 | BJ9: 0 | BK9: 0 | BN9: =BI9 -> 46054 | BO9: 0 | BP9: 0
B10: 46082 | C10: 0 | D10: 0 | G10: =B10 -> 46082 | H10: 0 | I10: 0 | L10: =B10 -> 46082 | M10: 0 | N10: 0 | Q10: =B10 -> 46082 | R10: 0 | S10: 0 | U10: =B10 -> 46082 | V10: 0 | W10: 0 | Z10: =B10 -> 46082 | AA10: 0 | AB10: 0 | AE10: =B10 -> 46082 | AF10: 0 | AG10: 0 | AJ10: =B10 -> 46082 | AK10: 0 | AL10: 0 | AO10: =B10 -> 46082 | AP10: 0 | AQ10: 0 | AT10: =B10 -> 46082 | AU10: 0 | AV10: 0 | AY10: =AT10 -> 46082 | AZ10: 0 | BA10: 0 | BD10: 46082 | BE10: 0 | BF10: 0 | BI10: =BD10 -> 46082 | BJ10: 0 | BK10: 0 | BN10: =BI10 -> 46082 | BO10: 0 | BP10: 0
B11: Total Bank 1 | C11: =IFERROR(SUM(C4:C10)/E11,0) -> 0 | D11: =IFERROR(SUM(D4:D10)/E11,0) -> 0 | E11: 7 | G11: Total Bank 2 | H11: =IFERROR(SUM(H4:H10)/J11,0) -> 0 | I11: =IFERROR(SUM(I4:I10)/J11,0) -> 0 | J11: 7 | L11: Total Bank 3 | M11: =IFERROR(SUM(M4:M10)/O11,0) -> 0 | N11: =IFERROR(SUM(N4:N10)/O11,0) -> 0 | O11: 7 | Q11: Total Bank 4 | R11: =IFERROR(SUM(R4:R10)/T11,0) -> 0 | S11: =IFERROR(SUM(S4:S10)/T11,0) -> 0 | T11: 7 | U11: Total Bank 5 | V11: =IFERROR(SUM(V4:V10)/X11,0) -> 0 | W11: =IFERROR(SUM(W4:W10)/X11,0) -> 0 | X11: 7 | Z11: Total Bank 6 | AA11: =IFERROR(SUM(AA4:AA10)/AC11,0) -> 0 | AB11: =IFERROR(SUM(AB4:AB10)/AC11,0) -> 0 | AC11: 7 | AE11: Total Bank 7 | AF11: =IFERROR(SUM(AF4:AF10)/AH11,0) -> 0 | AG11: =IFERROR(SUM(AG4:AG10)/AH11,0) -> 0 | AH11: 7 | AJ11: Total Bank 8 | AK11: =IFERROR(SUM(AK4:AK10)/AM11,0) -> 0 | AL11: =IFERROR(SUM(AL4:AL10)/AM11,0) -> 0 | AM11: 7 | AO11: Total Bank 9 | AP11: =IFERROR(SUM(AP4:AP10)/AR11,0) -> 0 | AQ11: =IFERROR(SUM(AQ4:AQ10)/AR11,0) -> 0 | AR11: 7 | AT11: Total Bank 10 | AU11: =IFERROR(SUM(AU4:AU10)/AW11,0) -> 0 | AV11: =IFERROR(SUM(AV4:AV10)/AW11,0) -> 0 | AW11: 7 | AY11: Total Bank 11 | AZ11: =IFERROR(SUM(AZ4:AZ10)/BB11,0) -> 0 | BA11: =IFERROR(SUM(BA4:BA10)/BB11,0) -> 0 | BB11: 7 | BD11: Total Bank 12 | BE11: =IFERROR(SUM(BE4:BE10)/BG11,0) -> 0 | BF11: =IFERROR(SUM(BF4:BF10)/BG11,0) -> 0 | BG11: 7 | BI11: Total Bank 13 | BJ11: =IFERROR(SUM(BJ4:BJ10)/BL11,0) -> 0 | BK11: =IFERROR(SUM(BK4:BK10)/BL11,0) -> 0 | BL11: 7 | BN11: Total Bank 14 | BO11: =IFERROR(SUM(BO4:BO10)/BQ11,0) -> 0 | BP11: =IFERROR(SUM(BP4:BP10)/BQ11,0) -> 0 | BQ11: 7
L14: TOTAL BANCOS
B15: BANCO USD | E15: T.C | M15: Depósitos (pesos) | N15: Saldo Prom. (pesos)
C16: Depósitos (dolares) | D16: Saldo Prom. (dolares) | F16: Depósitos (pesos) | G16: Saldo Prom. (pesos) | L16: =B4 -> 45901 | M16: =C4+H4+M4+F17+R4+V4+AA4+AF4+AK4+AP4+AU4+AZ4+BE4+BJ4+BO4 -> 0 | N16: =D4+I4+N4+G17+S4+W4+AB4+AG4+AL4+AQ4+AV4+BA4+BF4+BK4+BP4 -> 0
B17: =B4 -> 45901 | C17: 0 | D17: 0 | E17: 16.9377 | F17: =+C17*E17 -> 0 | G17: =+D17*E17 -> 0 | L17: =B5 -> 45931 | M17: =C5+H5+M5+F18+R5+V5+AA5+AF5+AK5+AP5+AU5+AZ5+BE5+BJ5+BO5 -> 0 | N17: =D5+I5+N5+G18+S5+W5+AB5+AG5+AL5+AQ5+AV5+BA5+BF5+BK5+BP5 -> 0
B18: =B5 -> 45931 | C18: 0 | D18: 0 | E18: 18.3773 | F18: =+C18*E18 -> 0 | G18: =+D18*E18 -> 0 | L18: =B6 -> 45962 | M18: =C6+H6+M6+F19+R6+V6+AA6+AF6+AK6+AP6+AU6+AZ6+BE6+BJ6+BO6 -> 0 | N18: =D6+I6+N6+G19+S6+W6+AB6+AG6+AL6+AQ6+AV6+BA6+BF6+BK6+BP6 -> 0
B19: =B6 -> 45962 | C19: 0 | D19: 0 | E19: 18.79 | F19: =+C19*E19 -> 0 | G19: =+D19*E19 -> 0 | L19: =B7 -> 45992 | M19: =C7+H7+M7+F20+R7+V7+AA7+AF7+AK7+AP7+AU7+AZ7+BE7+BJ7+BO7 -> 0 | N19: =D7+I7+N7+G20+S7+W7+AB7+AG7+AL7+AQ7+AV7+BA7+BF7+BK7+BP7 -> 0
B20: =B7 -> 45992 | C20: 0 | D20: 0 | E20: 19.8168 | F20: =+C20*E20 -> 0 | G20: =+D20*E20 -> 0 | L20: =B8 -> 46023 | M20: =C8+H8+M8+F21+R8+V8+AA8+AF8+AK8+AP8+AU8+AZ8+BE8+BJ8+BO8 -> 0 | N20: =D8+I8+N8+G21+S8+W8+AB8+AG8+AL8+AQ8+AV8+BA8+BF8+BK8+BP8 -> 0
B21: =B8 -> 46023 | C21: 0 | D21: 0 | E21: 19.6697 | F21: =+C21*E21 -> 0 | G21: =+D21*E21 -> 0 | L21: =B9 -> 46054 | M21: =C9+H9+M9+F22+R9+V9+AA9+AF9+AK9+AP9+AU9+AZ9+BE9+BJ9+BO9 -> 0 | N21: =D9+I9+N9+G22+S9+W9+AB9+AG9+AL9+AQ9+AV9+BA9+BF9+BK9+BP9 -> 0
B22: =B9 -> 46054 | C22: 0 | D22: 0 | E22: 20.1617 | F22: =+C22*E22 -> 0 | G22: =+D22*E22 -> 0 | L22: =B10 -> 46082 | M22: =C10+H10+M10+F23+R10+V10+AA10+AF10+AK10+AP10+AU10+AZ10+BE10+BJ10+BO10 -> 0 | N22: =D10+I10+N10+G23+S10+W10+AB10+AG10+AL10+AQ10+AV10+BA10+BF10+BK10+BP10 -> 0
B23: =B10 -> 46082 | C23: 0 | D23: 0 | F23: =+C23*E23 -> 0 | G23: =+D23*E23 -> 0 | L23: Total Bancos | M23: =IFERROR(SUM(M16:M22)/#REF!,0) -> 0 | N23: =IFERROR(SUM(N16:N22)/#REF!,0) -> 0 | O23: 7
B24: Total Bank 4 | C24: =IFERROR(SUM(C17:C23)/F24,0) -> 0 | D24: =IFERROR(SUM(D17:D23)/F24,0) -> 0 | F24: =IFERROR(SUM(F17:F23)/M11,0) -> 0 | G24: =IFERROR(SUM(G17:G23)/M11,0) -> 0

Sheet AYUDA
B1: HOJA DE AYUDA
B3: Dato requerido | C3: Información
B4: DEPRECIACIÓN (edo. de resúltados) | C4: Es el valor que ha perdido un activo en el transcurso de un tiempo determinado. Hay dos grandes fomas de obtenerlo 1) Directamente de los Resultados de Pérdida y Ganancia 2) Comparando la Amortización Acumulada de dos periodos del Balance. Por ejemplo, si a Diciembre 2017 tiene $29M y a Diciembre 2018 tiene $30, significa que la Depreciación fue de $1M. En caso de tener un periodo menor a un año, se divide entre el número de meses y se multiplica por 12. Por ejemplo, si tuviera $30M a Septiembre de 2018, sería una Depreciación de $1M en 9 meses, por tanto 111,111 mensuales * 12 meses = 1,333,333 anual
B5: Pasivo Arrendamiento (PAGO MENSUAL) | C5: Es el pago que hace la empresa por arrendamientos de equipos, que entran en el Estado de Resultados. No siempre lo reportan, la vía más rápida para este punto del proceso es preguntar al cliente cuánta pagan mensualmente de arrendamientos

Sheet Input
B1: Copiado de K1 | J1: DATOS DEL CAF
K2: =DATOS!E4 -> 2025 | L2: =DATOS!I4 -> Febrero 2026
B3: Credito Simple | C3: 1.2 | J3: TOTAL ACTIVOS CIRCULANTES
B4: Arrendamiento | C4: 1.35 | J4: TOTAL ACTIVOS FIJOS
J5: TOTAL ACTIVOS DIFERIDOS
B6: Valoración final | J6: TOTAL PASIVO NO FINANCIERO
B7: Limitado | J7: TOTAL PASIVO FINANCIERO
B8: Viable | J8: TOTAL PASIVO DIFERIDO
J9: CXP Proveedores
B10: Google | D10: Buro | J10: CAPITAL CONTABLE TOTAL
B11: N/D
B12: Si | D12: Si | J12: VENTAS
B13: No | D13: No | J13: UTILIDAD DE OPERACIÓN (Antes de impuestos y gastos financieros
J14: DEPRECIACIÓN (edo. de resúltados)
B15: Ubicación
B16: N/D
B17: Tamaulipas
B18: Veracruz
B19: Michoacán
B20: Guerrero
B21: Otros
B23: Meses
B24: =CONCATENATE(Input!D24," ",DATOS!$E$4+1) -> Enero 2026 | C24: 1 | D24: Enero
B25: =CONCATENATE(Input!D25," ",DATOS!$E$4+1) -> Febrero 2026 | C25: 2 | D25: Febrero
B26: =CONCATENATE(Input!D26," ",DATOS!$E$4+1) -> Marzo 2026 | C26: 3 | D26: Marzo
B27: =CONCATENATE(Input!D27," ",DATOS!$E$4+1) -> Abril 2026 | C27: 4 | D27: Abril
B28: =CONCATENATE(Input!D28," ",DATOS!$E$4+1) -> Mayo 2026 | C28: 5 | D28: Mayo
B29: =CONCATENATE(Input!D29," ",DATOS!$E$4+1) -> Junio 2026 | C29: 6 | D29: Junio
B30: =CONCATENATE(Input!D30," ",DATOS!$E$4+1) -> Julio 2026 | C30: 7 | D30: Julio
B31: =CONCATENATE(Input!D31," ",DATOS!$E$4+1) -> Agosto 2026 | C31: 8 | D31: Agosto
B32: =CONCATENATE(Input!D32," ",DATOS!$E$4+1) -> Septiembre 2026 | C32: 9 | D32: Septiembre
B33: =CONCATENATE(Input!D33," ",DATOS!$E$4+1) -> Octubre 2026 | C33: 10 | D33: Octubre
B34: =CONCATENATE(Input!D34," ",DATOS!$E$4+1) -> Noviembre 2026 | C34: 11 | D34: Noviembre
B35: =CONCATENATE(Input!D35," ",DATOS!$E$4+1) -> Diciembre 2026 | C35: 12 | D35: Diciembre
B41: Año fecha
B42: =YEAR(TODAY()) -> 2026
B46: Crecimiento requerido para historico de ventas
B47: 0.05
B50: Buro
B51: Si
B52: No
B53: N/D
B56: Atrasos
B57: N/D
B58: 0 a 59
B59: 60 o mas
B61: Sector
B62: Antros
B63: Armas y Explosivos
B64: Casas de Cambio
... B76: Tipo de propiedad
B77: Habitacional | C77: 2
B78: Oficinas | C78: 2
B79: Comercial | C79: 2
B80: Terreno | C80: 3
B81: N/D | C81: N/D
B84: Regimen conyugal
B85: N/D
B86: No está casado por conyugal
B87: No puede firmar
B88: Si puede firmar
